Workbook
Name UPDATE: 'Data Sheet'!$E$1

Sheet Financials>
B2: ="Historical Financial Statement - "&UPDATE -> Historical Financial Statement - Tata Motors
B3: Years | C3: ='Data Sheet'!B16 -> 42460 | D3: ='Data Sheet'!C16 -> 42825 | E3: ='Data Sheet'!D16 -> 43190 | F3: ='Data Sheet'!E16 -> 43555 | G3: ='Data Sheet'!F16 -> 43921 | H3: ='Data Sheet'!G16 -> 44286 | I3: ='Data Sheet'!H16 -> 44651 | J3: ='Data Sheet'!I16 -> 45016 | ... L3: ='Data Sheet'!K16 -> 45747 | M3: LTM
A5: x | B5: Income Statement
B7: Sales | C7: =IFERROR('Data Sheet'!B17,0) -> 273045.6 | D7: =IFERROR('Data Sheet'!C17,0) -> 269692.51 | E7: =IFERROR('Data Sheet'!D17,0) -> 291550.48 | F7: =IFERROR('Data Sheet'!E17,0) -> 301938.4 | G7: =IFERROR('Data Sheet'!F17,0) -> 261067.97 | H7: =IFERROR('Data Sheet'!G17,0) -> 249794.75 | I7: =IFERROR('Data Sheet'!H17,0) -> 278453.62 | J7: =IFERROR('Data Sheet'!I17,0) -> 345966.97 | ... L7: =IFERROR('Data Sheet'!K17,0) -> 439695 | M7: =IFERROR(SUM('Data Sheet'!H42:K42),0) -> 437968
B8: Sales Growth | C8: =IFERROR(C7/B7-1, "-") -> - | D8: =IFERROR(D7/C7-1, 0) -> -0.01228033 | E8: =IFERROR(E7/D7-1, 0) -> 0.081047746 | F8: =IFERROR(F7/E7-1, 0) -> 0.035629919 | G8: =IFERROR(G7/F7-1, 0) -> -0.13536016 | H8: =IFERROR(H7/G7-1, 0) -> -0.043181168 | I8: =IFERROR(I7/H7-1, 0) -> 0.11472967 | J8: =IFERROR(J7/I7-1, 0) -> 0.24245815 | K8: =IFERROR(K7/J7-1, 0) -> 0.25450126 | ... M8: =IFERROR(M7/L7-1, 0) -> -0.0039277226
B10: COGS | C10: =IFERROR(SUM('Data Sheet'!B18,'Data Sheet'!B20,'Data Sheet'!B21) - 1 *'Data Sheet'!B19, 0) -> 176628.18 | D10: =IFERROR(SUM('Data Sheet'!C18,'Data Sheet'!C20,'Data Sheet'!C21) - 1 *'Data Sheet'!C19, 0) -> 177121.35 | E10: =IFERROR(SUM('Data Sheet'!D18,'Data Sheet'!D20,'Data Sheet'!D21) - 1 *'Data Sheet'!D19, 0) -> 198129.74 | F10: =IFERROR(SUM('Data Sheet'!E18,'Data Sheet'!E20,'Data Sheet'!E21) - 1 *'Data Sheet'!E19, 0) -> 209601.66 | G10: =IFERROR(SUM('Data Sheet'!F18,'Data Sheet'!F20,'Data Sheet'!F21) - 1 *'Data Sheet'!F19, 0) -> 179937.47 | H10: =IFERROR(SUM('Data Sheet'!G18,'Data Sheet'!G20,'Data Sheet'!G21) - 1 *'Data Sheet'!G19, 0) -> 167677.56 | I10: =IFERROR(SUM('Data Sheet'!H18,'Data Sheet'!H20,'Data Sheet'!H21) - 1 *'Data Sheet'!H19, 0) -> 192491.49 | J10: =IFERROR(SUM('Data Sheet'!I18,'Data Sheet'!I20,'Data Sheet'!I21) - 1 *'Data Sheet'!I19, 0) -> 240748.94 | ... L10: =IFERROR(SUM('Data Sheet'!K18,'Data Sheet'!K20,'Data Sheet'!K21) - 1 *'Data Sheet'!K19, 0) -> 293042 | M10: =IFERROR(SUM('Data Sheet'!H43:K43),0) -> 386344
B11: COGS as % of Sales | C11: =IFERROR(C10/C7, 0) -> 0.64688162 | D11: =IFERROR(D10/D7, 0) -> 0.65675294 | E11: =IFERROR(E10/E7, 0) -> 0.67957268 | F11: =IFERROR(F10/F7, 0) -> 0.69418683 | G11: =IFERROR(G10/G7, 0) -> 0.6892361 | H11: =IFERROR(H10/H7, 0) -> 0.67126135 | I11: =IFERROR(I10/I7, 0) -> 0.69128744 | J11: =IFERROR(J10/J7, 0) -> 0.69587261 | ... M11: =IFERROR(M10/M7, 0) -> 0.88212837
B13: Gross Profit | C13: =IFERROR(C7-C10, 0) -> 96417.42 | D13: =IFERROR(D7-D10, 0) -> 92571.16 | E13: =IFERROR(E7-E10, 0) -> 93420.74 | F13: =IFERROR(F7-F10, 0) -> 92336.74 | G13: =IFERROR(G7-G10, 0) -> 81130.5 | H13: =IFERROR(H7-H10, 0) -> 82117.19 | I13: =IFERROR(I7-I10, 0) -> 85962.13 | J13: =IFERROR(J7-J10, 0) -> 105218.03 | ... M13: =IFERROR(M7-M10, 0) -> 51624
B14: Gross Margin | C14: =C13/C7 -> 0.35311838 | D14: =D13/D7 -> 0.34324706 | E14: =E13/E7 -> 0.32042732 | F14: =F13/F7 -> 0.30581317 | G14: =G13/G7 -> 0.3107639 | H14: =H13/H7 -> 0.32873865 | I14: =I13/I7 -> 0.30871256 | J14: =J13/J7 -> 0.30412739 | ... M14: =M13/M7 -> 0.11787163
B16: Selling & General Expenses | C16: =IFERROR(SUM('Data Sheet'!B23:B24),0) -> 29141.28 | D16: =IFERROR(SUM('Data Sheet'!C23:C24),0) -> 34649.58 | E16: =IFERROR(SUM('Data Sheet'!D23:D24),0) -> 31662.97 | F16: =IFERROR(SUM('Data Sheet'!E23:E24),0) -> 34428.54 | G16: =IFERROR(SUM('Data Sheet'!F23:F24),0) -> 32704.83 | H16: =IFERROR(SUM('Data Sheet'!G23:G24),0) -> 22181.28 | I16: =IFERROR(SUM('Data Sheet'!H23:H24),0) -> 30433.52 | J16: =IFERROR(SUM('Data Sheet'!I23:I24),0) -> 39747.53 | ... M16: =IFERROR(SUM('Data Sheet'!L23:L24),0) -> 0
B17: Selling Exp % | C17: =IFERROR(C16/C7, 0) -> 0.10672679 | D17: =IFERROR(D16/D7, 0) -> 0.1284781 | E17: =IFERROR(E16/E7, 0) -> 0.10860202 | F17: =IFERROR(F16/F7, 0) -> 0.11402505 | G17: =IFERROR(G16/G7, 0) -> 0.12527324 | H17: =IFERROR(H16/H7, 0) -> 0.088798023 | I17: =IFERROR(I16/I7, 0) -> 0.10929475 | J17: =IFERROR(J16/J7, 0) -> 0.11488822 | ... M17: =IFERROR(M16/M7, 0) -> 0
B19: EBITDA | C19: =IFERROR(C13-C16,0) -> 67276.14 | D19: =IFERROR(D13-D16,0) -> 57921.58 | E19: =IFERROR(E13-E16,0) -> 61757.77 | F19: =IFERROR(F13-F16,0) -> 57908.2 | G19: =IFERROR(G13-G16,0) -> 48425.67 | H19: =IFERROR(H13-H16,0) -> 59935.91 | I19: =IFERROR(I13-I16,0) -> 55528.61 | J19: =IFERROR(J13-J16,0) -> 65470.5 | ... M19: =IFERROR(M13-M16,0) -> 51624
B20: EBITDA Margins | C20: =C19/C7 -> 0.24639159 | D20: =D19/D7 -> 0.21476896 | E20: =E19/E7 -> 0.21182531 | F20: =F19/F7 -> 0.19178813 | G20: =G19/G7 -> 0.18549066 | H20: =H19/H7 -> 0.23994063 | I20: =I19/I7 -> 0.19941781 | J20: =J19/J7 -> 0.18923916 | ... M20: =M19/M7 -> 0.11787163
B22: Interest | C22: =IFERROR('Data Sheet'!B27,0) -> 4889.08 | D22: =IFERROR('Data Sheet'!C27,0) -> 4238.01 | E22: =IFERROR('Data Sheet'!D27,0) -> 4681.79 | F22: =IFERROR('Data Sheet'!E27,0) -> 5758.6 | G22: =IFERROR('Data Sheet'!F27,0) -> 7243.33 | H22: =IFERROR('Data Sheet'!G27,0) -> 8097.17 | I22: =IFERROR('Data Sheet'!H27,0) -> 9311.86 | J22: =IFERROR('Data Sheet'!I27,0) -> 10225.48 | ... L22: =IFERROR('Data Sheet'!K27,0) -> 5083 | M22: =IFERROR(SUM('Data Sheet'!H46:K46),0) -> 5167
B23: Interest as a % of Sales | C23: =IFERROR(C22/C7,0) -> 0.017905727 | D23: =IFERROR(D22/D7,0) -> 0.01571423 | E23: =IFERROR(E22/E7,0) -> 0.016058248 | F23: =IFERROR(F22/F7,0) -> 0.019072102 | G23: =IFERROR(G22/G7,0) -> 0.027744997 | H23: =IFERROR(H22/H7,0) -> 0.032415293 | I23: =IFERROR(I22/I7,0) -> 0.033441332 | J23: =IFERROR(J22/J7,0) -> 0.029556232 | ... M23: =IFERROR(M22/M7,0) -> 0.011797666
B25: Depriciation | C25: ='Data Sheet'!B26 -> 16710.78 | D25: ='Data Sheet'!C26 -> 17904.99 | E25: ='Data Sheet'!D26 -> 21553.59 | F25: ='Data Sheet'!E26 -> 23590.63 | G25: ='Data Sheet'!F26 -> 21425.43 | H25: ='Data Sheet'!G26 -> 23546.71 | I25: ='Data Sheet'!H26 -> 24835.69 | J25: ='Data Sheet'!I26 -> 24860.36 | ... L25: ='Data Sheet'!K26 -> 23256 | M25: =IFERROR(SUM('Data Sheet'!H45:K45),0) -> 22019
B26: Depriciation as a % of Sales | C26: =IFERROR(C25/C7,0) -> 0.061201426 | D26: =IFERROR(D25/D7,0) -> 0.066390387 | E26: =IFERROR(E25/E7,0) -> 0.073927472 | F26: =IFERROR(F25/F7,0) -> 0.078130605 | G26: =IFERROR(G25/G7,0) -> 0.082068398 | H26: =IFERROR(H25/H7,0) -> 0.094264231 | I26: =IFERROR(I25/I7,0) -> 0.089191478 | J26: =IFERROR(J25/J7,0) -> 0.071857611 | ... M26: =IFERROR(M25/M7,0) -> 0.050275363
B28: EBT | C28: =IFERROR(C19- (C22+C25), 0) -> 45676.28 | D28: =IFERROR(D19- (D22+D25), 0) -> 35778.58 | E28: =IFERROR(E19- (E22+E25), 0) -> 35522.39 | F28: =IFERROR(F19- (F22+F25), 0) -> 28558.97 | G28: =IFERROR(G19- (G22+G25), 0) -> 19756.91 | H28: =IFERROR(H19- (H22+H25), 0) -> 28292.03 | I28: =IFERROR(I19- (I22+I25), 0) -> 21381.06 | J28: =IFERROR(J19- (J22+J25), 0) -> 30384.66 | ... M28: =IFERROR(M19- (M22+M25), 0) -> 24438
B29: EBT as a % of Sales | C29: =IFERROR(C28/C7,0) -> 0.16728444 | D29: =IFERROR(D28/D7,0) -> 0.13266434 | E29: =IFERROR(E28/E7,0) -> 0.12183959 | F29: =IFERROR(F28/F7,0) -> 0.094585419 | G29: =IFERROR(G28/G7,0) -> 0.075677265 | H29: =IFERROR(H28/H7,0) -> 0.11326111 | I29: =IFERROR(I28/I7,0) -> 0.076784996 | J29: =IFERROR(J28/J7,0) -> 0.08782532 | ... M29: =IFERROR(M28/M7,0) -> 0.055798597
B31: Tax | C31: =IFERROR('Data Sheet'!B29,0) -> 3025.05 | D31: =IFERROR('Data Sheet'!C29,0) -> 3251.23 | E31: =IFERROR('Data Sheet'!D29,0) -> 4341.93 | F31: =IFERROR('Data Sheet'!E29,0) -> -2437.45 | G31: =IFERROR('Data Sheet'!F29,0) -> 395.25 | H31: =IFERROR('Data Sheet'!G29,0) -> 2541.86 | I31: =IFERROR('Data Sheet'!H29,0) -> 4231.29 | J31: =IFERROR('Data Sheet'!I29,0) -> 704.06 | ... L31: =IFERROR('Data Sheet'!K29,0) -> 10502 | M31: =IFERROR(SUM('Data Sheet'!H48:K48),0) -> 8943
B32: Effective Tax Rate | C32: =C31/C28 -> 0.066228029 | D32: =D31/D28 -> 0.090870851 | E32: =E31/E28 -> 0.1222308 | F32: =F31/F28 -> -0.085347966 | G32: =G31/G28 -> 0.020005659 | H32: =H31/H28 -> 0.089843677 | I32: =I31/I28 -> 0.19789898 | J32: =J31/J28 -> 0.023171561 | ... M32: =M31/M28 -> 0.36594648
B34: Net Profit | C34: =IFERROR(C28-C31,0) -> 42651.23 | D34: =IFERROR(D28-D31,0) -> 32527.35 | E34: =IFERROR(E28-E31,0) -> 31180.46 | F34: =IFERROR(F28-F31,0) -> 30996.42 | G34: =IFERROR(G28-G31,0) -> 19361.66 | H34: =IFERROR(H28-H31,0) -> 25750.17 | I34: =IFERROR(I28-I31,0) -> 17149.77 | J34: =IFERROR(J28-J31,0) -> 29680.6 | ... M34: =IFERROR(M28-M31,0) -> 15495
B35: Net Margins | C35: =C34/C7 -> 0.15620552 | D35: =D34/D7 -> 0.12060902 | E35: =E34/E7 -> 0.10694704 | F35: =F34/F7 -> 0.10265809 | G35: =G34/G7 -> 0.074163292 | H35: =H34/H7 -> 0.10308531 | I35: =I34/I7 -> 0.061589323 | J35: =J34/J7 -> 0.085790271 | ... M35: =M34/M7 -> 0.035379297
B37: No. of Equity Shares | C37: =IFERROR('Data Sheet'!B93,0) -> 288.72 | D37: =IFERROR('Data Sheet'!C93,0) -> 288.73 | E37: =IFERROR('Data Sheet'!D93,0) -> 288.73 | F37: =IFERROR('Data Sheet'!E93,0) -> 288.73 | G37: =IFERROR('Data Sheet'!F93,0) -> 308.9 | H37: =IFERROR('Data Sheet'!G93,0) -> 332.03 | I37: =IFERROR('Data Sheet'!H93,0) -> 332.07 | J37: =IFERROR('Data Sheet'!I93,0) -> 332.13 | ... L37: =IFERROR('Data Sheet'!K93,0) -> 368.13
B38: Earning Per Share | C38: =C34/C37 -> 147.72524 | D38: =D34/D37 -> 112.65663 | E38: =E34/E37 -> 107.99176 | F38: =F34/F37 -> 107.35434 | G38: =G34/G37 -> 62.679378 | H38: =H34/H37 -> 77.553745 | I38: =I34/I37 -> 51.645045 | J38: =J34/J37 -> 89.364406 | ... L38: =L34/L37 -> 174.23736
B39: Earning Growth % | D39: =IFERROR(D38/C38-1,0) -> -0.23739073 | E39: =IFERROR(E38/D38-1,0) -> -0.041407923 | F39: =IFERROR(F38/E38-1,0) -> -0.0059024145 | G39: =IFERROR(G38/F38-1,0) -> -0.41614493 | H39: =IFERROR(H38/G38-1,0) -> 0.23730878 | I39: =IFERROR(I38/H38-1,0) -> -0.33407414 | J39: =IFERROR(J38/I38-1,0) -> 0.73035779 | K39: =IFERROR(K38/J38-1,0) -> 1.3232405 | ... M39: =IFERROR(M38/L38-1,0) -> -1
B41: Dividend Per Share | C41: =IFERROR('Data Sheet'!B31/'Financials>'!C37,0) -> 0.23524522 | D41: =IFERROR('Data Sheet'!C31/'Financials>'!D37,0) -> 0 | E41: =IFERROR('Data Sheet'!D31/'Financials>'!E37,0) -> 0 | F41: =IFERROR('Data Sheet'!E31/'Financials>'!F37,0) -> 0 | G41: =IFERROR('Data Sheet'!F31/'Financials>'!G37,0) -> 0 | H41: =IFERROR('Data Sheet'!G31/'Financials>'!H37,0) -> 0 | I41: =IFERROR('Data Sheet'!H31/'Financials>'!I37,0) -> 0 | J41: =IFERROR('Data Sheet'!I31/'Financials>'!J37,0) -> 2.3063861 | ... M41: =IFERROR('Data Sheet'!L31/'Financials>'!M37,0) -> 0
B42: Dividend Payout Ratio | C42: =IFERROR(C41/C38,0) -> 0.0015924511 | D42: =IFERROR(D41/D38,0) -> 0 | E42: =IFERROR(E41/E38,0) -> 0 | F42: =IFERROR(F41/F38,0) -> 0 | G42: =IFERROR(G41/G38,0) -> 0 | H42: =IFERROR(H41/H38,0) -> 0 | I42: =IFERROR(I41/I38,0) -> 0 | J42: =IFERROR(J41/J38,0) -> 0.025808777 | ... M42: =IFERROR(M41/M38,0) -> 0
B44: Retained Earnings | C44: =IFERROR(IF(C38>C41,1-C42,0),0) -> 0.99840755 | D44: =IFERROR(IF(D38>D41,1-D42,0),0) -> 1 | E44: =IFERROR(IF(E38>E41,1-E42,0),0) -> 1 | F44: =IFERROR(IF(F38>F41,1-F42,0),0) -> 1 | G44: =IFERROR(IF(G38>G41,1-G42,0),0) -> 1 | H44: =IFERROR(IF(H38>H41,1-H42,0),0) -> 1 | I44: =IFERROR(IF(I38>I41,1-I42,0),0) -> 1 | J44: =IFERROR(IF(J38>J41,1-J42,0),0) -> 0.97419122 | ... M44: =IFERROR(IF(M38>M41,1-M42,0),0) -> 0
A46: x | B46: Balance Sheet
B48: Equity Share Capital | C48: =IFERROR('Data Sheet'!B57,0) -> 679.18 | D48: =IFERROR('Data Sheet'!C57,0) -> 679.22 | E48: =IFERROR('Data Sheet'!D57,0) -> 679.22 | F48: =IFERROR('Data Sheet'!E57,0) -> 679.22 | G48: =IFERROR('Data Sheet'!F57,0) -> 719.54 | H48: =IFERROR('Data Sheet'!G57,0) -> 765.81 | I48: =IFERROR('Data Sheet'!H57,0) -> 765.88 | J48: =IFERROR('Data Sheet'!I57,0) -> 766.02 | ... L48: =IFERROR('Data Sheet'!K57,0) -> 736
B49: Reserves | C49: =IFERROR('Data Sheet'!B58,0) -> 78273.23 | D49: =IFERROR('Data Sheet'!C58,0) -> 57382.67 | E49: =IFERROR('Data Sheet'!D58,0) -> 94748.69 | F49: =IFERROR('Data Sheet'!E58,0) -> 59500.34 | G49: =IFERROR('Data Sheet'!F58,0) -> 62358.99 | H49: =IFERROR('Data Sheet'!G58,0) -> 54480.91 | I49: =IFERROR('Data Sheet'!H58,0) -> 43795.36 | J49: =IFERROR('Data Sheet'!I58,0) -> 44555.77 | ... L49: =IFERROR('Data Sheet'!K58,0) -> 115408
B50: Borrowings | C50: =IFERROR('Data Sheet'!B59,0) -> 69359.96 | D50: =IFERROR('Data Sheet'!C59,0) -> 78603.98 | E50: =IFERROR('Data Sheet'!D59,0) -> 88950.47 | F50: =IFERROR('Data Sheet'!E59,0) -> 106175.34 | G50: =IFERROR('Data Sheet'!F59,0) -> 124787.64 | H50: =IFERROR('Data Sheet'!G59,0) -> 142130.57 | I50: =IFERROR('Data Sheet'!H59,0) -> 146449.03 | J50: =IFERROR('Data Sheet'!I59,0) -> 134113.44 | ... L50: =IFERROR('Data Sheet'!K59,0) -> 71540
B51: Other Liabilities | C51: =IFERROR('Data Sheet'!B60,0) -> 114871.75 | D51: =IFERROR('Data Sheet'!C60,0) -> 135914.49 | E51: =IFERROR('Data Sheet'!D60,0) -> 142813.43 | F51: =IFERROR('Data Sheet'!E60,0) -> 139348.59 | G51: =IFERROR('Data Sheet'!F60,0) -> 132313.22 | H51: =IFERROR('Data Sheet'!G60,0) -> 144192.62 | I51: =IFERROR('Data Sheet'!H60,0) -> 138051.22 | J51: =IFERROR('Data Sheet'!I60,0) -> 155239.2 | ... L51: =IFERROR('Data Sheet'!K60,0) -> 189289
B52: Total Liabilities | C52: =IFERROR('Data Sheet'!B61,0) -> 263184.12 | D52: =IFERROR('Data Sheet'!C61,0) -> 272580.36 | E52: =IFERROR('Data Sheet'!D61,0) -> 327191.81 | F52: =IFERROR('Data Sheet'!E61,0) -> 305703.49 | G52: =IFERROR('Data Sheet'!F61,0) -> 320179.39 | H52: =IFERROR('Data Sheet'!G61,0) -> 341569.91 | I52: =IFERROR('Data Sheet'!H61,0) -> 329061.49 | J52: =IFERROR('Data Sheet'!I61,0) -> 334674.43 | ... L52: =IFERROR('Data Sheet'!K61,0) -> 376973
B54: Fixed Assest Net Block | C54: =IFERROR('Data Sheet'!B62,0) -> 107231.76 | D54: =IFERROR('Data Sheet'!C62,0) -> 95944.08 | E54: =IFERROR('Data Sheet'!D62,0) -> 121413.86 | F54: =IFERROR('Data Sheet'!E62,0) -> 111234.47 | G54: =IFERROR('Data Sheet'!F62,0) -> 127107.14 | H54: =IFERROR('Data Sheet'!G62,0) -> 138707.61 | I54: =IFERROR('Data Sheet'!H62,0) -> 138855.45 | J54: =IFERROR('Data Sheet'!I62,0) -> 132079.76 | ... L54: =IFERROR('Data Sheet'!K62,0) -> 115697
B55: Capital Work in Progress | C55: =IFERROR('Data Sheet'!B63,0) -> 25918.94 | D55: =IFERROR('Data Sheet'!C63,0) -> 33698.84 | E55: =IFERROR('Data Sheet'!D63,0) -> 40033.5 | F55: =IFERROR('Data Sheet'!E63,0) -> 31883.84 | G55: =IFERROR('Data Sheet'!F63,0) -> 35622.29 | H55: =IFERROR('Data Sheet'!G63,0) -> 20963.93 | I55: =IFERROR('Data Sheet'!H63,0) -> 10251.09 | J55: =IFERROR('Data Sheet'!I63,0) -> 14274.5 | ... L55: =IFERROR('Data Sheet'!K63,0) -> 65806
B56: Investments | C56: =IFERROR('Data Sheet'!B64,0) -> 23767.02 | D56: =IFERROR('Data Sheet'!C64,0) -> 20337.92 | E56: =IFERROR('Data Sheet'!D64,0) -> 20812.75 | F56: =IFERROR('Data Sheet'!E64,0) -> 15770.72 | G56: =IFERROR('Data Sheet'!F64,0) -> 16308.48 | H56: =IFERROR('Data Sheet'!G64,0) -> 24620.28 | I56: =IFERROR('Data Sheet'!H64,0) -> 29379.53 | J56: =IFERROR('Data Sheet'!I64,0) -> 26379.16 | ... L56: =IFERROR('Data Sheet'!K64,0) -> 35656
B57: Other Assets | C57: =IFERROR('Data Sheet'!B65 - SUM(C60:C62),0) -> 29579.36 | D57: =IFERROR('Data Sheet'!C65 - SUM(D60:D62),0) -> 37360.78 | E57: =IFERROR('Data Sheet'!D65 - SUM(E60:E62),0) -> 48286.86 | F57: =IFERROR('Data Sheet'!E65 - SUM(F60:F62),0) -> 56155.74 | G57: =IFERROR('Data Sheet'!F65 - SUM(G60:G62),0) -> 58784.94 | H57: =IFERROR('Data Sheet'!G65 - SUM(H60:H62),0) -> 61717.96 | I57: =IFERROR('Data Sheet'!H65 - SUM(I60:I62),0) -> 62223.77 | J57: =IFERROR('Data Sheet'!I65 - SUM(J60:J62),0) -> 68432.09 | ... L57: =IFERROR('Data Sheet'!K65 - SUM(L60:L62),0) -> 58463
B58: Total Non Current Assests | C58: =SUM(C54:C57) -> 186497.08 | D58: =SUM(D54:D57) -> 187341.62 | E58: =SUM(E54:E57) -> 230546.97 | F58: =SUM(F54:F57) -> 215044.77 | G58: =SUM(G54:G57) -> 237822.85 | H58: =SUM(H54:H57) -> 246009.78 | I58: =SUM(I54:I57) -> 240709.84 | J58: =SUM(J54:J57) -> 241165.51 | ... L58: =SUM(L54:L57) -> 275622
B60: Receivables | C60: =IFERROR('Data Sheet'!B67,0) -> 13570.91 | D60: =IFERROR('Data Sheet'!C67,0) -> 14075.55 | E60: =IFERROR('Data Sheet'!D67,0) -> 19893.3 | F60: =IFERROR('Data Sheet'!E67,0) -> 18996.17 | G60: =IFERROR('Data Sheet'!F67,0) -> 11172.69 | H60: =IFERROR('Data Sheet'!G67,0) -> 12679.08 | I60: =IFERROR('Data Sheet'!H67,0) -> 12442.12 | J60: =IFERROR('Data Sheet'!I67,0) -> 15737.97 | ... L60: =IFERROR('Data Sheet'!K67,0) -> 13248
B61: Inventory | C61: =IFERROR('Data Sheet'!B68,0) -> 32655.73 | D61: =IFERROR('Data Sheet'!C68,0) -> 35085.31 | E61: =IFERROR('Data Sheet'!D68,0) -> 42137.63 | F61: =IFERROR('Data Sheet'!E68,0) -> 39013.73 | G61: =IFERROR('Data Sheet'!F68,0) -> 37456.88 | H61: =IFERROR('Data Sheet'!G68,0) -> 36088.59 | I61: =IFERROR('Data Sheet'!H68,0) -> 35240.34 | J61: =IFERROR('Data Sheet'!I68,0) -> 40755.39 | ... L61: =IFERROR('Data Sheet'!K68,0) -> 47269
B62: Cash & Bank | C62: =IFERROR('Data Sheet'!B69,0) -> 30460.4 | D62: =IFERROR('Data Sheet'!C69,0) -> 36077.88 | E62: =IFERROR('Data Sheet'!D69,0) -> 34613.91 | F62: =IFERROR('Data Sheet'!E69,0) -> 32648.82 | G62: =IFERROR('Data Sheet'!F69,0) -> 33726.97 | H62: =IFERROR('Data Sheet'!G69,0) -> 46792.46 | I62: =IFERROR('Data Sheet'!H69,0) -> 40669.19 | J62: =IFERROR('Data Sheet'!I69,0) -> 37015.56 | ... L62: =IFERROR('Data Sheet'!K69,0) -> 40834
B63: Total Current Assests | C63: =SUM(C60:C62) -> 76687.04 | D63: =SUM(D60:D62) -> 85238.74 | E63: =SUM(E60:E62) -> 96644.84 | F63: =SUM(F60:F62) -> 90658.72 | G63: =SUM(G60:G62) -> 82356.54 | H63: =SUM(H60:H62) -> 95560.13 | I63: =SUM(I60:I62) -> 88351.65 | J63: =SUM(J60:J62) -> 93508.92 | ... L63: =SUM(L60:L62) -> 101351
B65: Total Assests | C65: =IFERROR(SUM(C58,C63),0) -> 263184.12 | D65: =IFERROR(SUM(D58,D63),0) -> 272580.36 | E65: =IFERROR(SUM(E58,E63),0) -> 327191.81 | F65: =IFERROR(SUM(F58,F63),0) -> 305703.49 | G65: =IFERROR(SUM(G58,G63),0) -> 320179.39 | H65: =IFERROR(SUM(H58,H63),0) -> 341569.91 | I65: =IFERROR(SUM(I58,I63),0) -> 329061.49 | J65: =IFERROR(SUM(J58,J63),0) -> 334674.43 | ... L65: =IFERROR(SUM(L58,L63),0) -> 376973
B67: Balance | C67: =C52=C65 -> TRUE | D67: =D52=D65 -> TRUE | E67: =E52=E65 -> TRUE | F67: =F52=F65 -> TRUE | G67: =G52=G65 -> TRUE | H67: =H52=H65 -> TRUE | I67: =I52=I65 -> TRUE | J67: =J52=J65 -> TRUE | ... L67: =L52=L65 -> TRUE
A69: x | B69: Cash Flow Statement
B71: Operating Activities
B72: Profit from operations | C72: ='Cash Flow Data'!E4 -> 38626 | D72: ='Cash Flow Data'!F4 -> 28840 | E72: ='Cash Flow Data'!G4 -> 33312 | F72: ='Cash Flow Data'!H4 -> 28771 | G72: ='Cash Flow Data'!I4 -> 23352 | H72: ='Cash Flow Data'!J4 -> 31198 | I72: ='Cash Flow Data'!K4 -> 26943 | J72: ='Cash Flow Data'!L4 -> 41694 | ... L72: ='Cash Flow Data'!N4 -> 58937
B73: Receivables | C73: ='Cash Flow Data'!E5 -> -2223 | D73: ='Cash Flow Data'!F5 -> -4152 | E73: ='Cash Flow Data'!G5 -> -10688 | F73: ='Cash Flow Data'!H5 -> -9109 | G73: ='Cash Flow Data'!I5 -> 9950 | H73: ='Cash Flow Data'!J5 -> -5505 | I73: ='Cash Flow Data'!K5 -> 185 | J73: ='Cash Flow Data'!L5 -> -2213 | ... L73: ='Cash Flow Data'!N5 -> 3573
B74: Inventory | C74: ='Cash Flow Data'!E6 -> -5743 | D74: ='Cash Flow Data'!F6 -> -6621 | E74: ='Cash Flow Data'!G6 -> -3560 | F74: ='Cash Flow Data'!H6 -> 2069 | G74: ='Cash Flow Data'!I6 -> 2326 | H74: ='Cash Flow Data'!J6 -> 3814 | I74: ='Cash Flow Data'!K6 -> 472 | J74: ='Cash Flow Data'!L6 -> -5665 | ... L74: ='Cash Flow Data'!N6 -> 2127
B75: Payables | C75: ='Cash Flow Data'!E7 -> 3947 | D75: ='Cash Flow Data'!F7 -> 9301 | E75: ='Cash Flow Data'!G7 -> 7320 | F75: ='Cash Flow Data'!H7 -> -4692 | G75: ='Cash Flow Data'!I7 -> -8085 | H75: ='Cash Flow Data'!J7 -> 5748 | I75: ='Cash Flow Data'!K7 -> -7012 | J75: ='Cash Flow Data'!L7 -> 6945 | ... L75: ='Cash Flow Data'!N7 -> 1303
B76: Loans Advances | C76: ='Cash Flow Data'!E8 -> -520 | D76: ='Cash Flow Data'!F8 -> 0 | E76: ='Cash Flow Data'!G8 -> 0 | F76: ='Cash Flow Data'!H8 -> 0 | G76: ='Cash Flow Data'!I8 -> 0 | H76: ='Cash Flow Data'!J8 -> 0 | I76: ='Cash Flow Data'!K8 -> 0 | J76: ='Cash Flow Data'!L8 -> 0 | ... L76: ='Cash Flow Data'!N8 -> 0
B77: Other WC items | C77: ='Cash Flow Data'!E9 -> 5852 | D77: ='Cash Flow Data'!F9 -> 4727 | E77: ='Cash Flow Data'!G9 -> 494 | F77: ='Cash Flow Data'!H9 -> 4512 | G77: ='Cash Flow Data'!I9 -> 875 | H77: ='Cash Flow Data'!J9 -> -4150 | I77: ='Cash Flow Data'!K9 -> -4396 | J77: ='Cash Flow Data'!L9 -> -2194 | ... L77: ='Cash Flow Data'!N9 -> 1153
B78: Working capital changes | C78: ='Cash Flow Data'!E10 -> 1313 | D78: ='Cash Flow Data'!F10 -> 3254 | E78: ='Cash Flow Data'!G10 -> -6434 | F78: ='Cash Flow Data'!H10 -> -7221 | G78: ='Cash Flow Data'!I10 -> 5065 | H78: ='Cash Flow Data'!J10 -> -93 | I78: ='Cash Flow Data'!K10 -> -10750 | J78: ='Cash Flow Data'!L10 -> -3127 | ... L78: ='Cash Flow Data'!N10 -> 8156
B79: Direct taxes | C79: ='Cash Flow Data'!E11 -> -2040 | D79: ='Cash Flow Data'!F11 -> -1895 | E79: ='Cash Flow Data'!G11 -> -3021 | F79: ='Cash Flow Data'!H11 -> -2659 | G79: ='Cash Flow Data'!I11 -> -1785 | H79: ='Cash Flow Data'!J11 -> -2105 | I79: ='Cash Flow Data'!K11 -> -1910 | J79: ='Cash Flow Data'!L11 -> -3179 | ... L79: ='Cash Flow Data'!N11 -> -3991
B80: Cash From Operating Activities | C80: =SUM(C72:C79) -> 39212 | D80: =SUM(D72:D79) -> 33454 | E80: =SUM(E72:E79) -> 17423 | F80: =SUM(F72:F79) -> 11671 | G80: =SUM(G72:G79) -> 31698 | H80: =SUM(H72:H79) -> 28907 | I80: =SUM(I72:I79) -> 3532 | J80: =SUM(J72:J79) -> 32261 | ... L80: =SUM(L72:L79) -> 71258
B82: Investing Activites
B83: Fixed assets purchased | C83: ='Cash Flow Data'!E13 -> -31503 | D83: ='Cash Flow Data'!F13 -> -16072 | E83: ='Cash Flow Data'!G13 -> -35079 | F83: ='Cash Flow Data'!H13 -> -35304 | G83: ='Cash Flow Data'!I13 -> -29702 | H83: ='Cash Flow Data'!J13 -> -20205 | I83: ='Cash Flow Data'!K13 -> -15168 | J83: ='Cash Flow Data'!L13 -> -19230 | ... L83: ='Cash Flow Data'!N13 -> -38042
B84: Fixed assets sold | C84: ='Cash Flow Data'!E14 -> 59 | D84: ='Cash Flow Data'!F14 -> 53 | E84: ='Cash Flow Data'!G14 -> 30 | F84: ='Cash Flow Data'!H14 -> 67 | G84: ='Cash Flow Data'!I14 -> 171 | H84: ='Cash Flow Data'!J14 -> 351 | I84: ='Cash Flow Data'!K14 -> 230 | J84: ='Cash Flow Data'!L14 -> 285 | ... L84: ='Cash Flow Data'!N14 -> 974
B85: Investments purchased | C85: ='Cash Flow Data'!E15 -> -4728 | D85: ='Cash Flow Data'!F15 -> -6 | E85: ='Cash Flow Data'!G15 -> -329 | F85: ='Cash Flow Data'!H15 -> -130 | G85: ='Cash Flow Data'!I15 -> -1439 | H85: ='Cash Flow Data'!J15 -> -7530 | I85: ='Cash Flow Data'!K15 -> -3008 | J85: ='Cash Flow Data'!L15 -> -50 | ... L85: ='Cash Flow Data'!N15 -> -12677
B86: Investments sold | C86: ='Cash Flow Data'!E16 -> 89 | D86: ='Cash Flow Data'!F16 -> 1965 | E86: ='Cash Flow Data'!G16 -> 2381 | F86: ='Cash Flow Data'!H16 -> 5644 | G86: ='Cash Flow Data'!I16 -> 21 | H86: ='Cash Flow Data'!J16 -> 226 | I86: ='Cash Flow Data'!K16 -> 104 | J86: ='Cash Flow Data'!L16 -> 6895 | ... L86: ='Cash Flow Data'!N16 -> 111
B87: Interest received | C87: ='Cash Flow Data'!E17 -> 731 | D87: ='Cash Flow Data'!F17 -> 638 | E87: ='Cash Flow Data'!G17 -> 690 | F87: ='Cash Flow Data'!H17 -> 761 | G87: ='Cash Flow Data'!I17 -> 1104 | H87: ='Cash Flow Data'!J17 -> 428 | I87: ='Cash Flow Data'!K17 -> 653 | J87: ='Cash Flow Data'!L17 -> 973 | ... L87: ='Cash Flow Data'!N17 -> 2420
B88: Dividends received | C88: ='Cash Flow Data'!E18 -> 58 | D88: ='Cash Flow Data'!F18 -> 620 | E88: ='Cash Flow Data'!G18 -> 1797 | F88: ='Cash Flow Data'!H18 -> 232 | G88: ='Cash Flow Data'!I18 -> 21 | H88: ='Cash Flow Data'!J18 -> 18 | I88: ='Cash Flow Data'!K18 -> 32 | J88: ='Cash Flow Data'!L18 -> 46 | ... L88: ='Cash Flow Data'!N18 -> 64
B89: Investment in group cos | C89: ='Cash Flow Data'!E19 -> 0 | D89: ='Cash Flow Data'!F19 -> -107 | E89: ='Cash Flow Data'!G19 -> -4 | F89: ='Cash Flow Data'!H19 -> -9 | G89: ='Cash Flow Data'!I19 -> -606 | H89: ='Cash Flow Data'!J19 -> -10 | I89: ='Cash Flow Data'!K19 -> 0 | J89: ='Cash Flow Data'!L19 -> 0 | ... L89: ='Cash Flow Data'!N19 -> 0
B90: Redemp n Canc of Shares | C90: ='Cash Flow Data'!E20 -> 0 | D90: ='Cash Flow Data'!F20 -> 0 | E90: ='Cash Flow Data'!G20 -> 14 | F90: ='Cash Flow Data'!H20 -> 533 | G90: ='Cash Flow Data'!I20 -> 0 | H90: ='Cash Flow Data'!J20 -> 0 | I90: ='Cash Flow Data'!K20 -> 0 | J90: ='Cash Flow Data'!L20 -> 19 | ... L90: ='Cash Flow Data'!N20 -> 765
B91: Acquisition of companies | C91: ='Cash Flow Data'!E21 -> -111 | D91: ='Cash Flow Data'!F21 -> 0 | E91: ='Cash Flow Data'!G21 -> 0 | F91: ='Cash Flow Data'!H21 -> -8 | G91: ='Cash Flow Data'!I21 -> -27 | H91: ='Cash Flow Data'!J21 -> 0 | I91: ='Cash Flow Data'!K21 -> -98 | J91: ='Cash Flow Data'!L21 -> 0 | ... L91: ='Cash Flow Data'!N21 -> -688
B92: Inter corporate deposits | C92: ='Cash Flow Data'!E22 -> 0 | D92: ='Cash Flow Data'!F22 -> 0 | E92: ='Cash Flow Data'!G22 -> 0 | F92: ='Cash Flow Data'!H22 -> 0 | G92: ='Cash Flow Data'!I22 -> 0 | H92: ='Cash Flow Data'!J22 -> 0 | I92: ='Cash Flow Data'!K22 -> 0 | J92: ='Cash Flow Data'!L22 -> 0 | ... L92: ='Cash Flow Data'!N22 -> -20
B93: Other investing items | C93: ='Cash Flow Data'!E23 -> -1289 | D93: ='Cash Flow Data'!F23 -> -26663 | E93: ='Cash Flow Data'!G23 -> 5360 | F93: ='Cash Flow Data'!H23 -> 7335 | G93: ='Cash Flow Data'!I23 -> -2659 | H93: ='Cash Flow Data'!J23 -> 1051 | I93: ='Cash Flow Data'!K23 -> 12813 | J93: ='Cash Flow Data'!L23 -> -4357 | ... L93: ='Cash Flow Data'!N23 -> -2889
B94: Cash From Investing Activites | C94: =SUM(C83:C93) -> -36694 | D94: =SUM(D83:D93) -> -39572 | E94: =SUM(E83:E93) -> -25140 | F94: =SUM(F83:F93) -> -20879 | G94: =SUM(G83:G93) -> -33116 | H94: =SUM(H83:H93) -> -25671 | I94: =SUM(I83:I93) -> -4442 | J94: =SUM(J83:J93) -> -15419 | ... L94: =SUM(L83:L93) -> -49982
B96: Financing Activities
B97: Proceeds from shares | C97: ='Cash Flow Data'!E25 -> 7433 | D97: ='Cash Flow Data'!F25 -> 5 | E97: ='Cash Flow Data'!G25 -> 0 | F97: ='Cash Flow Data'!H25 -> 0 | G97: ='Cash Flow Data'!I25 -> 3889 | H97: ='Cash Flow Data'!J25 -> 2603 | I97: ='Cash Flow Data'!K25 -> 19 | J97: ='Cash Flow Data'!L25 -> 20 | ... L97: ='Cash Flow Data'!N25 -> 1108
B98: Redemption of debentures | C98: ='Cash Flow Data'!E26 -> 0 | D98: ='Cash Flow Data'!F26 -> 0 | E98: ='Cash Flow Data'!G26 -> 0 | F98: ='Cash Flow Data'!H26 -> 0 | G98: ='Cash Flow Data'!I26 -> 0 | H98: ='Cash Flow Data'!J26 -> 0 | I98: ='Cash Flow Data'!K26 -> 0 | J98: ='Cash Flow Data'!L26 -> 0 | ... L98: ='Cash Flow Data'!N26 -> 0
B99: Proceeds from borrowings | C99: ='Cash Flow Data'!E27 -> 19519 | D99: ='Cash Flow Data'!F27 -> 33390 | E99: ='Cash Flow Data'!G27 -> 37482 | F99: ='Cash Flow Data'!H27 -> 51128 | G99: ='Cash Flow Data'!I27 -> 38297 | H99: ='Cash Flow Data'!J27 -> 46641 | I99: ='Cash Flow Data'!K27 -> 46578 | J99: ='Cash Flow Data'!L27 -> 43934 | ... L99: ='Cash Flow Data'!N27 -> 13384
B100: Repayment of borrowings | C100: ='Cash Flow Data'!E28 -> -24924 | D100: ='Cash Flow Data'!F28 -> -21732 | E100: ='Cash Flow Data'!G28 -> -29964 | F100: ='Cash Flow Data'!H28 -> -35198 | G100: ='Cash Flow Data'!I28 -> -29847 | H100: ='Cash Flow Data'!J28 -> -29709 | I100: ='Cash Flow Data'!K28 -> -42816 | J100: ='Cash Flow Data'!L28 -> -62557 | ... L100: ='Cash Flow Data'!N28 -> -21443
B101: Interest paid fin | C101: ='Cash Flow Data'!E29 -> -5716 | D101: ='Cash Flow Data'!F29 -> -5336 | E101: ='Cash Flow Data'!G29 -> -5411 | F101: ='Cash Flow Data'!H29 -> -7005 | G101: ='Cash Flow Data'!I29 -> -7518 | H101: ='Cash Flow Data'!J29 -> -8123 | I101: ='Cash Flow Data'!K29 -> -9251 | J101: ='Cash Flow Data'!L29 -> -9336 | ... L101: ='Cash Flow Data'!N29 -> -5814
B102: Dividends paid | C102: ='Cash Flow Data'!E30 -> -108 | D102: ='Cash Flow Data'!F30 -> -121 | E102: ='Cash Flow Data'!G30 -> -96 | F102: ='Cash Flow Data'!H30 -> -95 | G102: ='Cash Flow Data'!I30 -> -57 | H102: ='Cash Flow Data'!J30 -> -30 | I102: ='Cash Flow Data'!K30 -> -100 | J102: ='Cash Flow Data'!L30 -> -141 | ... L102: ='Cash Flow Data'!N30 -> -2492
B103: Financial liabilities | C103: ='Cash Flow Data'!E31 -> 0 | D103: ='Cash Flow Data'!F31 -> 0 | E103: ='Cash Flow Data'!G31 -> 0 | F103: ='Cash Flow Data'!H31 -> 0 | G103: ='Cash Flow Data'!I31 -> -1346 | H103: ='Cash Flow Data'!J31 -> -1477 | I103: ='Cash Flow Data'!K31 -> -1559 | J103: ='Cash Flow Data'!L31 -> -1517 | ... L103: ='Cash Flow Data'!N31 -> -2393
B104: Other financing items | C104: ='Cash Flow Data'!E32 -> 0 | D104: ='Cash Flow Data'!F32 -> 0 | E104: ='Cash Flow Data'!G32 -> 0 | F104: ='Cash Flow Data'!H32 -> 0 | G104: ='Cash Flow Data'!I32 -> -29 | H104: ='Cash Flow Data'!J32 -> 0 | I104: ='Cash Flow Data'!K32 -> 3750 | J104: ='Cash Flow Data'!L32 -> 3355 | ... L104: ='Cash Flow Data'!N32 -> -1136
B105: Cash From Financing Activites | C105: =SUM(C97:C104) -> -3796 | D105: =SUM(D97:D104) -> 6206 | E105: =SUM(E97:E104) -> 2011 | F105: =SUM(F97:F104) -> 8830 | G105: =SUM(G97:G104) -> 3389 | H105: =SUM(H97:H104) -> 9905 | I105: =SUM(I97:I104) -> -3379 | J105: =SUM(J97:J104) -> -26242 | ... L105: =SUM(L97:L104) -> -18786
B106: Net Cash Flow | C106: =SUM(C80,C94,C105) -> -1278 | D106: =SUM(D80,D94,D105) -> 88 | E106: =SUM(E80,E94,E105) -> -5706 | F106: =SUM(F80,F94,F105) -> -378 | G106: =SUM(G80,G94,G105) -> 1971 | H106: =SUM(H80,H94,H105) -> 13141 | I106: =SUM(I80,I94,I105) -> -4289 | J106: =SUM(J80,J94,J105) -> -9400 | ... L106: =SUM(L80,L94,L105) -> 2490

Sheet Ratio Analysis
B2: ="Ratio Analysis - "&UPDATE -> Ratio Analysis - Tata Motors
B3: Years | C3: ='Data Sheet'!B16 -> 42460 | D3: ='Data Sheet'!C16 -> 42825 | E3: ='Data Sheet'!D16 -> 43190 | F3: ='Data Sheet'!E16 -> 43555 | G3: ='Data Sheet'!F16 -> 43921 | H3: ='Data Sheet'!G16 -> 44286 | I3: ='Data Sheet'!H16 -> 44651 | J3: ='Data Sheet'!I16 -> 45016 | ... L3: ='Data Sheet'!K16 -> 45747 | M3: Trends | N3: Mean | O3: Median
B5: Sales Growth | C5: ='Financials>'!C8 -> - | D5: ='Financials>'!D8 -> -0.01228033 | E5: ='Financials>'!E8 -> 0.081047746 | F5: ='Financials>'!F8 -> 0.035629919 | G5: ='Financials>'!G8 -> -0.13536016 | H5: ='Financials>'!H8 -> -0.043181168 | I5: ='Financials>'!I8 -> 0.11472967 | J5: ='Financials>'!J8 -> 0.24245815 | ... L5: ='Financials>'!L8 -> 0.013084771 | N5: =IFERROR(AVERAGE(D5:L5), 0) -> 0.061181096 | O5: =IFERROR(MEDIAN(C5:L5), 0) -> 0.035629919
B6: EBITDA Growth | C6: =IFERROR('Financials>'!C19/'Financials>'!B19 - 1, "-") -> - | D6: =IFERROR('Financials>'!D19/'Financials>'!C19 - 1, "-") -> -0.13904722 | E6: =IFERROR('Financials>'!E19/'Financials>'!D19 - 1, "-") -> 0.066230755 | F6: =IFERROR('Financials>'!F19/'Financials>'!E19 - 1, "-") -> -0.062333371 | G6: =IFERROR('Financials>'!G19/'Financials>'!F19 - 1, "-") -> -0.16375107 | H6: =IFERROR('Financials>'!H19/'Financials>'!G19 - 1, "-") -> 0.23768881 | I6: =IFERROR('Financials>'!I19/'Financials>'!H19 - 1, "-") -> -0.073533546 | J6: =IFERROR('Financials>'!J19/'Financials>'!I19 - 1, "-") -> 0.17904086 | ... L6: =IFERROR('Financials>'!L19/'Financials>'!K19 - 1, "-") -> 0.031749053 | N6: =IFERROR(AVERAGE(D6:L6), 0) -> 0.066734308 | O6: =IFERROR(MEDIAN(C6:L6), 0) -> 0.031749053
B7: EBT Growth | C7: =IFERROR('Financials>'!C28/'Financials>'!B28-1,"-") -> - | D7: =IFERROR('Financials>'!D28/'Financials>'!C28-1,"-") -> -0.21669234 | E7: =IFERROR('Financials>'!E28/'Financials>'!D28-1,"-") -> -0.0071604295 | F7: =IFERROR('Financials>'!F28/'Financials>'!E28-1,"-") -> -0.19602904 | G7: =IFERROR('Financials>'!G28/'Financials>'!F28-1,"-") -> -0.30820649 | H7: =IFERROR('Financials>'!H28/'Financials>'!G28-1,"-") -> 0.43200683 | I7: =IFERROR('Financials>'!I28/'Financials>'!H28-1,"-") -> -0.24427268 | J7: =IFERROR('Financials>'!J28/'Financials>'!I28-1,"-") -> 0.42110167 | ... L7: =IFERROR('Financials>'!L28/'Financials>'!K28-1,"-") -> 0.14870501 | N7: =IFERROR(AVERAGE(D7:L7), 0) -> 0.12978495 | O7: =IFERROR(MEDIAN(C7:L7), 0) -> -0.0071604295
B8: Net Profit Growth | C8: =IFERROR('Financials>'!C34/'Financials>'!B34 - 1, "-") -> - | D8: =IFERROR('Financials>'!D34/'Financials>'!C34 - 1, "-") -> -0.23736432 | E8: =IFERROR('Financials>'!E34/'Financials>'!D34 - 1, "-") -> -0.041407923 | F8: =IFERROR('Financials>'!F34/'Financials>'!E34 - 1, "-") -> -0.0059024145 | G8: =IFERROR('Financials>'!G34/'Financials>'!F34 - 1, "-") -> -0.37535819 | H8: =IFERROR('Financials>'!H34/'Financials>'!G34 - 1, "-") -> 0.32995673 | I8: =IFERROR('Financials>'!I34/'Financials>'!H34 - 1, "-") -> -0.33399391 | J8: =IFERROR('Financials>'!J34/'Financials>'!I34 - 1, "-") -> 0.73067044 | ... L8: =IFERROR('Financials>'!L34/'Financials>'!K34 - 1, "-") -> -0.070473154 | N8: =IFERROR(AVERAGE(D8:L8), 0) -> 0.14678295 | O8: =IFERROR(MEDIAN(C8:L8), 0) -> -0.041407923
B9: Dividend Growth | C9: =IFERROR('Financials>'!C41/'Financials>'!B41 - 1, "-") -> - | D9: =IFERROR('Financials>'!D41/'Financials>'!C41 - 1, "-") -> -1 | E9: =IFERROR('Financials>'!E41/'Financials>'!D41 - 1, "-") -> - | F9: =IFERROR('Financials>'!F41/'Financials>'!E41 - 1, "-") -> - | G9: =IFERROR('Financials>'!G41/'Financials>'!F41 - 1, "-") -> - | H9: =IFERROR('Financials>'!H41/'Financials>'!G41 - 1, "-") -> - | I9: =IFERROR('Financials>'!I41/'Financials>'!H41 - 1, "-") -> - | J9: =IFERROR('Financials>'!J41/'Financials>'!I41 - 1, "-") -> - | ... L9: =IFERROR('Financials>'!L41/'Financials>'!K41 - 1, "-") -> -0.1336307 | N9: =IFERROR(AVERAGE(D9:L9), 0) -> 0.2893461 | O9: =IFERROR(MEDIAN(C9:L9), 0) -> -0.1336307
B11: Gross Margin | C11: =IFERROR('Financials>'!C14, "0") -> 0.35311838 | D11: =IFERROR('Financials>'!D14, "0") -> 0.34324706 | E11: =IFERROR('Financials>'!E14, "0") -> 0.32042732 | F11: =IFERROR('Financials>'!F14, "0") -> 0.30581317 | G11: =IFERROR('Financials>'!G14, "0") -> 0.3107639 | H11: =IFERROR('Financials>'!H14, "0") -> 0.32873865 | I11: =IFERROR('Financials>'!I14, "0") -> 0.30871256 | J11: =IFERROR('Financials>'!J14, "0") -> 0.30412739 | ... L11: =IFERROR('Financials>'!L14, "0") -> 0.33353347 | N11: =IFERROR(AVERAGE(C11:L11), 0) -> 0.32347971 | O11: =IFERROR(MEDIAN(C11:L11),0) -> 0.32337124
B12: EBITDA Margin | C12: =IFERROR('Financials>'!C20, "-") -> 0.24639159 | D12: =IFERROR('Financials>'!D20, "-") -> 0.21476896 | E12: =IFERROR('Financials>'!E20, "-") -> 0.21182531 | F12: =IFERROR('Financials>'!F20, "-") -> 0.19178813 | G12: =IFERROR('Financials>'!G20, "-") -> 0.18549066 | H12: =IFERROR('Financials>'!H20, "-") -> 0.23994063 | I12: =IFERROR('Financials>'!I20, "-") -> 0.19941781 | J12: =IFERROR('Financials>'!J20, "-") -> 0.18923916 | ... L12: =IFERROR('Financials>'!L20, "-") -> 0.23421463 | N12: =IFERROR(AVERAGE(C12:L12), 0) -> 0.21430546 | O12: =IFERROR(MEDIAN(C12:L12),0) -> 0.21329713
B13: EBIT Margin | C13: =IFERROR(('Financials>'!C19 - 'Financials>'!C25)/'Financials>'!C7, "-") -> 0.18519017 | D13: =IFERROR(('Financials>'!D19 - 'Financials>'!D25)/'Financials>'!D7, "-") -> 0.14837857 | E13: =IFERROR(('Financials>'!E19 - 'Financials>'!E25)/'Financials>'!E7, "-") -> 0.13789784 | F13: =IFERROR(('Financials>'!F19 - 'Financials>'!F25)/'Financials>'!F7, "-") -> 0.11365752 | G13: =IFERROR(('Financials>'!G19 - 'Financials>'!G25)/'Financials>'!G7, "-") -> 0.10342226 | H13: =IFERROR(('Financials>'!H19 - 'Financials>'!H25)/'Financials>'!H7, "-") -> 0.1456764 | I13: =IFERROR(('Financials>'!I19 - 'Financials>'!I25)/'Financials>'!I7, "-") -> 0.11022633 | J13: =IFERROR(('Financials>'!J19 - 'Financials>'!J25)/'Financials>'!J7, "-") -> 0.11738155 | ... L13: =IFERROR(('Financials>'!L19 - 'Financials>'!L25)/'Financials>'!L7, "-") -> 0.18132342 | N13: =IFERROR(AVERAGE(C13:L13), 0) -> 0.14103714 | O13: =IFERROR(MEDIAN(C13:L13),0) -> 0.14178712
B14: EBT Margin | C14: ='Financials>'!C29 -> 0.16728444 | D14: ='Financials>'!D29 -> 0.13266434 | E14: ='Financials>'!E29 -> 0.12183959 | F14: ='Financials>'!F29 -> 0.094585419 | G14: ='Financials>'!G29 -> 0.075677265 | H14: ='Financials>'!H29 -> 0.11326111 | I14: ='Financials>'!I29 -> 0.076784996 | J14: ='Financials>'!J29 -> 0.08782532 | ... L14: ='Financials>'!L29 -> 0.16976313 | N14: =IFERROR(AVERAGE(C14:L14), 0) -> 0.11894059 | O14: =IFERROR(MEDIAN(C14:L14),0) -> 0.11755035
B15: Net Profit Margin | C15: ='Financials>'!C35 -> 0.15620552 | D15: ='Financials>'!D35 -> 0.12060902 | E15: ='Financials>'!E35 -> 0.10694704 | F15: ='Financials>'!F35 -> 0.10265809 | G15: ='Financials>'!G35 -> 0.074163292 | H15: ='Financials>'!H35 -> 0.10308531 | I15: ='Financials>'!I35 -> 0.061589323 | J15: ='Financials>'!J35 -> 0.085790271 | ... L15: ='Financials>'!L35 -> 0.14587839 | N15: =IFERROR(AVERAGE(C15:L15), 0) -> 0.11159181 | O15: =IFERROR(MEDIAN(C15:L15),0) -> 0.10501618
B17: Sales Expenses% of Sales | C17: =IFERROR('Financials>'!C17, "-") -> 0.10672679 | D17: =IFERROR('Financials>'!D17, "-") -> 0.1284781 | E17: =IFERROR('Financials>'!E17, "-") -> 0.10860202 | F17: =IFERROR('Financials>'!F17, "-") -> 0.11402505 | G17: =IFERROR('Financials>'!G17, "-") -> 0.12527324 | H17: =IFERROR('Financials>'!H17, "-") -> 0.088798023 | I17: =IFERROR('Financials>'!I17, "-") -> 0.10929475 | J17: =IFERROR('Financials>'!J17, "-") -> 0.11488822 | ... L17: =IFERROR('Financials>'!L17, "-") -> 0.099318846 | N17: =IFERROR(AVERAGE(C17:L17), 0) -> 0.10917425 | O17: =IFERROR(MEDIAN(C17:L17),0) -> 0.10894839
B18: Depriciation% of Sales | C18: =IFERROR('Financials>'!C26,"-") -> 0.061201426 | D18: =IFERROR('Financials>'!D26,"-") -> 0.066390387 | E18: =IFERROR('Financials>'!E26,"-") -> 0.073927472 | F18: =IFERROR('Financials>'!F26,"-") -> 0.078130605 | G18: =IFERROR('Financials>'!G26,"-") -> 0.082068398 | H18: =IFERROR('Financials>'!H26,"-") -> 0.094264231 | I18: =IFERROR('Financials>'!I26,"-") -> 0.089191478 | J18: =IFERROR('Financials>'!J26,"-") -> 0.071857611 | ... L18: =IFERROR('Financials>'!L26,"-") -> 0.052891209 | N18: =IFERROR(AVERAGE(C18:L18), 0) -> 0.073268318 | O18: =IFERROR(MEDIAN(C18:L18),0) -> 0.072892542
B19: Operating Income% of Sales | C19: =C13 -> 0.18519017 | D19: =D13 -> 0.14837857 | E19: =E13 -> 0.13789784 | F19: =F13 -> 0.11365752 | G19: =G13 -> 0.10342226 | H19: =H13 -> 0.1456764 | I19: =I13 -> 0.11022633 | J19: =J13 -> 0.11738155 | ... L19: =L13 -> 0.18132342 | N19: =IFERROR(AVERAGE(C19:L19), 0) -> 0.14103714 | O19: =IFERROR(MEDIAN(C19:L19),0) -> 0.14178712
B21: Return on Capital Employed | C21: =('Financials>'!C19 -'Financials>'!C25)/SUM('Financials>'!C48:C50) -> 0.34093825 | D21: =('Financials>'!D19 -'Financials>'!D25)/SUM('Financials>'!D48:D50) -> 0.29280602 | E21: =('Financials>'!E19 -'Financials>'!E25)/SUM('Financials>'!E48:E50) -> 0.21805257 | F21: =('Financials>'!F19 -'Financials>'!F25)/SUM('Financials>'!F48:F50) -> 0.20629131 | G21: =('Financials>'!G19 -'Financials>'!G25)/SUM('Financials>'!G48:G50) -> 0.14372061 | H21: =('Financials>'!H19 -'Financials>'!H25)/SUM('Financials>'!H48:H50) -> 0.18436366 | I21: =('Financials>'!I19 -'Financials>'!I25)/SUM('Financials>'!I48:I50) -> 0.16068728 | J21: =('Financials>'!J19 -'Financials>'!J25)/SUM('Financials>'!J48:J50) -> 0.226322 | ... L21: =('Financials>'!L19 -'Financials>'!L25)/SUM('Financials>'!L48:L50) -> 0.4247938 | N21: =IFERROR(AVERAGE(C21:L21), 0) -> 0.25756123 | O21: =IFERROR(MEDIAN(C21:L21),0) -> 0.22218729 | Q21: EBIT/(EQ+DEBT) or EBIT/ Equity + Reserves + Borrowings
B22: Retained Earnings% | C22: ='Financials>'!C44 -> 0.99840755 | D22: ='Financials>'!D44 -> 1 | E22: ='Financials>'!E44 -> 1 | F22: ='Financials>'!F44 -> 1 | G22: ='Financials>'!G44 -> 1 | H22: ='Financials>'!H44 -> 1 | I22: ='Financials>'!I44 -> 1 | J22: ='Financials>'!J44 -> 0.97419122 | ... L22: ='Financials>'!L44 -> 0.96557638 | N22: =IFERROR(AVERAGE(C22:L22), 0) -> 0.99048297 | O22: =IFERROR(MEDIAN(C22:L22),0) -> 1
B23: Return on Equity% | C23: =IFERROR('Financials>'!C34/SUM('Financials>'!C48:C49), "-") -> 0.54021442 | D23: =IFERROR('Financials>'!D34/SUM('Financials>'!D48:D49), "-") -> 0.56021859 | E23: =IFERROR('Financials>'!E34/SUM('Financials>'!E48:E49), "-") -> 0.32674361 | F23: =IFERROR('Financials>'!F34/SUM('Financials>'!F48:F49), "-") -> 0.51506558 | G23: =IFERROR('Financials>'!G34/SUM('Financials>'!G48:G49), "-") -> 0.30694533 | H23: =IFERROR('Financials>'!H34/SUM('Financials>'!H48:H49), "-") -> 0.4660941 | I23: =IFERROR('Financials>'!I34/SUM('Financials>'!I48:I49), "-") -> 0.38485846 | J23: =IFERROR('Financials>'!J34/SUM('Financials>'!J48:J49), "-") -> 0.65488587 | ... L23: =IFERROR('Financials>'!L34/SUM('Financials>'!L48:L49), "-") -> 0.55226271 | N23: =IFERROR(AVERAGE(C23:L23), 0) -> 0.51198961 | O23: =IFERROR(MEDIAN(C23:L23),0) -> 0.52764 | Q23: Net Profit/ Shareholder funds (Share equity Capital + Reserves)
B24: Self Sustain Growth Rate | C24: =C22*C23 -> 0.53935415 | D24: =D22*D23 -> 0.56021859 | E24: =E22*E23 -> 0.32674361 | F24: =F22*F23 -> 0.51506558 | G24: =G22*G23 -> 0.30694533 | H24: =H22*H23 -> 0.4660941 | I24: =I22*I23 -> 0.38485846 | J24: =J22*J23 -> 0.63798407 | ... L24: =L22*L23 -> 0.53325183 | N24: =IFERROR(AVERAGE(C24:L24), 0) -> 0.50560264 | O24: =IFERROR(MEDIAN(C24:L24),0) -> 0.5241587 | Q24: G = B * R
B25: Interest Covering Ratio | C25: =('Financials>'!C19-'Financials>'!C25)/'Financials>'!C22 -> 10.34251 | D25: =('Financials>'!D19-'Financials>'!D25)/'Financials>'!D22 -> 9.4423066 | E25: =('Financials>'!E19-'Financials>'!E25)/'Financials>'!E22 -> 8.5873523 | F25: =('Financials>'!F19-'Financials>'!F25)/'Financials>'!F22 -> 5.9593599 | G25: =('Financials>'!G19-'Financials>'!G25)/'Financials>'!G22 -> 3.7276004 | H25: =('Financials>'!H19-'Financials>'!H25)/'Financials>'!H22 -> 4.494064 | I25: =('Financials>'!I19-'Financials>'!I25)/'Financials>'!I22 -> 3.2961106 | J25: =('Financials>'!J19-'Financials>'!J25)/'Financials>'!J22 -> 3.9714654 | ... L25: =('Financials>'!L19-'Financials>'!L25)/'Financials>'!L22 -> 15.685029 | N25: =IFERROR(AVERAGE(C25:L25), 0) -> 7.5062685 | O25: =IFERROR(MEDIAN(C25:L25),0) -> 7.2733561 | Q25: How much money do you have before interest so that you can pay interest for n times
B27: Debtor Turnover Ratio | C27: =IFERROR('Financials>'!C7/'Financials>'!C60, "-") -> 20.119918 | D27: =IFERROR('Financials>'!D7/'Financials>'!D60, "-") -> 19.160353 | E27: =IFERROR('Financials>'!E7/'Financials>'!E60, "-") -> 14.655712 | F27: =IFERROR('Financials>'!F7/'Financials>'!F60, "-") -> 15.894699 | G27: =IFERROR('Financials>'!G7/'Financials>'!G60, "-") -> 23.366617 | H27: =IFERROR('Financials>'!H7/'Financials>'!H60, "-") -> 19.701331 | I27: =IFERROR('Financials>'!I7/'Financials>'!I60, "-") -> 22.379918 | J27: =IFERROR('Financials>'!J7/'Financials>'!J60, "-") -> 21.982948 | ... L27: =IFERROR('Financials>'!L7/'Financials>'!L60, "-") -> 33.189538 | N27: =IFERROR(AVERAGE(C27:L27), 0) -> 21.605368 | O27: =IFERROR(MEDIAN(C27:L27),0) -> 21.051433 | Q27: Sales/Debtor (Recievables)
B28: Creditor Turnover Ratio | C28: =IFERROR('Financials>'!C7/'Financials>'!C51, "-") -> 2.3769604 | D28: =IFERROR('Financials>'!D7/'Financials>'!D51, "-") -> 1.9842808 | E28: =IFERROR('Financials>'!E7/'Financials>'!E51, "-") -> 2.041478 | F28: =IFERROR('Financials>'!F7/'Financials>'!F51, "-") -> 2.1667848 | G28: =IFERROR('Financials>'!G7/'Financials>'!G51, "-") -> 1.9731057 | H28: =IFERROR('Financials>'!H7/'Financials>'!H51, "-") -> 1.7323685 | I28: =IFERROR('Financials>'!I7/'Financials>'!I51, "-") -> 2.0170312 | J28: =IFERROR('Financials>'!J7/'Financials>'!J51, "-") -> 2.2286057 | ... L28: =IFERROR('Financials>'!L7/'Financials>'!L51, "-") -> 2.3228767 | N28: =IFERROR(AVERAGE(C28:L28), 0) -> 2.1290872 | O28: =IFERROR(MEDIAN(C28:L28),0) -> 2.1041314 | Q28: Payables * (x) = Sales
B29: Inventory Turnover Ratio | C29: =IFERROR('Financials>'!C7/'Financials>'!C61, "-") -> 8.3613381 | D29: =IFERROR('Financials>'!D7/'Financials>'!D61, "-") -> 7.6867643 | E29: =IFERROR('Financials>'!E7/'Financials>'!E61, "-") -> 6.9190052 | F29: =IFERROR('Financials>'!F7/'Financials>'!F61, "-") -> 7.7392856 | G29: =IFERROR('Financials>'!G7/'Financials>'!G61, "-") -> 6.9698269 | H29: =IFERROR('Financials>'!H7/'Financials>'!H61, "-") -> 6.9217099 | I29: =IFERROR('Financials>'!I7/'Financials>'!I61, "-") -> 7.9015588 | J29: =IFERROR('Financials>'!J7/'Financials>'!J61, "-") -> 8.4888642 | ... L29: =IFERROR('Financials>'!L7/'Financials>'!L61, "-") -> 9.3019738 | N29: =IFERROR(AVERAGE(C29:L29), 0) -> 7.937244 | O29: =IFERROR(MEDIAN(C29:L29),0) -> 7.8204222 | Q29: Inventory * (x) = Sales
B30: Fixed Assets Turnover Ratio | C30: =IFERROR('Financials>'!C7/'Financials>'!C54, "-") -> 2.5463128 | D30: =IFERROR('Financials>'!D7/'Financials>'!D54, "-") -> 2.8109343 | E30: =IFERROR('Financials>'!E7/'Financials>'!E54, "-") -> 2.4012949 | F30: =IFERROR('Financials>'!F7/'Financials>'!F54, "-") -> 2.714432 | G30: =IFERROR('Financials>'!G7/'Financials>'!G54, "-") -> 2.0539206 | H30: =IFERROR('Financials>'!H7/'Financials>'!H54, "-") -> 1.8008727 | I30: =IFERROR('Financials>'!I7/'Financials>'!I54, "-") -> 2.0053489 | J30: =IFERROR('Financials>'!J7/'Financials>'!J54, "-") -> 2.6193792 | ... L30: =IFERROR('Financials>'!L7/'Financials>'!L54, "-") -> 3.800401 | N30: =IFERROR(AVERAGE(C30:L30), 0) -> 2.6331377 | O30: =IFERROR(MEDIAN(C30:L30),0) -> 2.582846 | Q30: Fixed Assests * (x) = Sales
B31: Capital Turnover Ratio | C31: =IFERROR('Financials>'!C7/SUM('Financials>'!C48:C49), "-") -> 3.4583567 | D31: =IFERROR('Financials>'!D7/SUM('Financials>'!D48:D49), "-") -> 4.6449144 | E31: =IFERROR('Financials>'!E7/SUM('Financials>'!E48:E49), "-") -> 3.0551909 | F31: =IFERROR('Financials>'!F7/SUM('Financials>'!F48:F49), "-") -> 5.0172916 | G31: =IFERROR('Financials>'!G7/SUM('Financials>'!G48:G49), "-") -> 4.138777 | H31: =IFERROR('Financials>'!H7/SUM('Financials>'!H48:H49), "-") -> 4.5214404 | I31: =IFERROR('Financials>'!I7/SUM('Financials>'!I48:I49), "-") -> 6.2487853 | J31: =IFERROR('Financials>'!J7/SUM('Financials>'!J48:J49), "-") -> 7.6335681 | ... L31: =IFERROR('Financials>'!L7/SUM('Financials>'!L48:L49), "-") -> 3.7857746 | N31: =IFERROR(AVERAGE(C31:L31), 0) -> 4.76151 | O31: =IFERROR(MEDIAN(C31:L31),0) -> 4.5831774 | Q31: Capital Turnover Ratio * (x) = Sales
B33: Debtor Days | C33: =IFERROR(365/C27, 0) -> 18.141227 | D33: =IFERROR(365/D27, 0) -> 19.049753 | E33: =IFERROR(365/E27, 0) -> 24.904965 | F33: =IFERROR(365/F27, 0) -> 22.963631 | G33: =IFERROR(365/G27, 0) -> 15.620575 | H33: =IFERROR(365/H27, 0) -> 18.526667 | I33: =IFERROR(365/I27, 0) -> 16.309265 | J33: =IFERROR(365/J27, 0) -> 16.603779 | ... L33: =IFERROR(365/L27, 0) -> 10.997441 | N33: =IFERROR(AVERAGE(C33:L33), 0) -> 17.737364 | O33: =IFERROR(MEDIAN(C33:L33),0) -> 17.372503
B34: Creditor Days | C34: =IFERROR(365/C28, 0) -> 153.55746 | D34: =IFERROR(365/D28, 0) -> 183.94574 | E34: =IFERROR(365/E28, 0) -> 178.79203 | F34: =IFERROR(365/F28, 0) -> 168.45236 | G34: =IFERROR(365/G28, 0) -> 184.98755 | H34: =IFERROR(365/H28, 0) -> 210.69421 | I34: =IFERROR(365/I28, 0) -> 180.95902 | J34: =IFERROR(365/J28, 0) -> 163.77953 | ... L34: =IFERROR(365/L28, 0) -> 157.13275 | N34: =IFERROR(AVERAGE(C34:L34), 0) -> 173.14397 | O34: =IFERROR(MEDIAN(C34:L34),0) -> 173.62219
B35: Inventory Days | C35: =IFERROR(365/C29, 0) -> 43.6533 | D35: =IFERROR(365/D29, 0) -> 47.484219 | E35: =IFERROR(365/E29, 0) -> 52.753249 | F35: =IFERROR(365/F29, 0) -> 47.161976 | G35: =IFERROR(365/G29, 0) -> 52.368589 | H35: =IFERROR(365/H29, 0) -> 52.732635 | I35: =IFERROR(365/I29, 0) -> 46.193417 | J35: =IFERROR(365/J29, 0) -> 42.997507 | ... L35: =IFERROR(365/L29, 0) -> 39.238984 | N35: =IFERROR(AVERAGE(C35:L35), 0) -> 46.477276 | O35: =IFERROR(MEDIAN(C35:L35),0) -> 46.677696
B36: Cash Conversion Cycle | C36: =SUM(C33,C35)-C34 -> -91.762933 | D36: =SUM(D33,D35)-D34 -> -117.41177 | E36: =SUM(E33,E35)-E34 -> -101.13382 | F36: =SUM(F33,F35)-F34 -> -98.326751 | G36: =SUM(G33,G35)-G34 -> -116.99839 | H36: =SUM(H33,H35)-H34 -> -139.4349 | I36: =SUM(I33,I35)-I34 -> -118.45634 | J36: =SUM(J33,J35)-J34 -> -104.17824 | ... L36: =SUM(L33,L35)-L34 -> -106.89633 | N36: =IFERROR(AVERAGE(C36:L36), 0) -> -108.92933 | O36: =IFERROR(MEDIAN(C36:L36),0) -> -105.53729
B38: CFO/Sales | C38: =IFERROR('Financials>'!C80/'Financials>'!C7, "0") -> 0.14360971 | D38: =IFERROR('Financials>'!D80/'Financials>'!D7, "0") -> 0.12404497 | E38: =IFERROR('Financials>'!E80/'Financials>'!E7, "0") -> 0.059759806 | F38: =IFERROR('Financials>'!F80/'Financials>'!F7, "0") -> 0.03865358 | G38: =IFERROR('Financials>'!G80/'Financials>'!G7, "0") -> 0.12141666 | H38: =IFERROR('Financials>'!H80/'Financials>'!H7, "0") -> 0.11572301 | I38: =IFERROR('Financials>'!I80/'Financials>'!I7, "0") -> 0.012684339 | J38: =IFERROR('Financials>'!J80/'Financials>'!J7, "0") -> 0.093248786 | ... L38: =IFERROR('Financials>'!L80/'Financials>'!L7, "0") -> 0.16206234 | N38: =IFERROR(AVERAGE(C38:L38), 0) -> 0.10445609 | O38: =IFERROR(MEDIAN(C38:L38),0) -> 0.11856983
B39: CFO/Total Assests | C39: =IFERROR('Financials>'!C80/'Financials>'!C65, "0") -> 0.14899075 | D39: =IFERROR('Financials>'!D80/'Financials>'!D65, "0") -> 0.12273078 | E39: =IFERROR('Financials>'!E80/'Financials>'!E65, "0") -> 0.05325011 | F39: =IFERROR('Financials>'!F80/'Financials>'!F65, "0") -> 0.038177516 | G39: =IFERROR('Financials>'!G80/'Financials>'!G65, "0") -> 0.099000751 | H39: =IFERROR('Financials>'!H80/'Financials>'!H65, "0") -> 0.08462982 | I39: =IFERROR('Financials>'!I80/'Financials>'!I65, "0") -> 0.010733556 | J39: =IFERROR('Financials>'!J80/'Financials>'!J65, "0") -> 0.096395174 | ... L39: =IFERROR('Financials>'!L80/'Financials>'!L65, "0") -> 0.1890268 | N39: =IFERROR(AVERAGE(C39:L39), 0) -> 0.10465502 | O39: =IFERROR(MEDIAN(C39:L39),0) -> 0.097697963
B40: CFO/Total Debt | C40: =IFERROR('Financials>'!C80/'Financials>'!C50, "0") -> 0.56534058 | D40: =IFERROR('Financials>'!D80/'Financials>'!D50, "0") -> 0.42560186 | E40: =IFERROR('Financials>'!E80/'Financials>'!E50, "0") -> 0.19587305 | F40: =IFERROR('Financials>'!F80/'Financials>'!F50, "0") -> 0.10992195 | G40: =IFERROR('Financials>'!G80/'Financials>'!G50, "0") -> 0.25401554 | H40: =IFERROR('Financials>'!H80/'Financials>'!H50, "0") -> 0.20338341 | I40: =IFERROR('Financials>'!I80/'Financials>'!I50, "0") -> 0.024117606 | J40: =IFERROR('Financials>'!J80/'Financials>'!J50, "0") -> 0.24055009 | ... L40: =IFERROR('Financials>'!L80/'Financials>'!L50, "0") -> 0.99605815 | N40: =IFERROR(AVERAGE(C40:L40), 0) -> 0.37163091 | O40: =IFERROR(MEDIAN(C40:L40),0) -> 0.24728282

Sheet Forecasting
B3: Year Weight | C3: Years | D3: Sales | E3: Growth
B4: 1 | C4: 2014 | D4: 232834
B5: =B4+1 -> 2 | C5: =C4+1 -> 2015 | D5: 263159 | E5: =D5/D4-1 -> 0.13024301
B6: =B5+1 -> 3 | C6: =C5+1 -> 2016 | D6: 273046 | E6: =D6/D5-1 -> 0.037570442 | I6: 13 | J6: 2026 | K6: =$I$35+B16*$I$36 -> 398918.7 | L6: =K6/D15-1 -> -0.0927377 | M6: Formula that is used here, = Intercept + Weight * Year Weight
B7: =B6+1 -> 4 | C7: =C6+1 -> 2017 | D7: 269693 | E7: =D7/D6-1 -> -0.012279982 | I7: 14 | J7: 2027 | K7: =$I$35+B17*$I$36 -> 413608.56 | L7: =K7/D16-1 -> 0.036824204
B8: =B7+1 -> 5 | C8: =C7+1 -> 2018 | D8: 291550 | E8: =D8/D7-1 -> 0.081044002 | I8: 15 | J8: 2028 | K8: =$I$35+B18*$I$36 -> 428298.42 | L8: =K8/D17-1 -> 0.035516343
B9: =B8+1 -> 6 | C9: =C8+1 -> 2019 | D9: 301938 | E9: =D9/D8-1 -> 0.035630252 | I9: 16 | J9: 2029 | K9: =$I$35+B19*$I$36 -> 442988.29 | L9: =K9/D18-1 -> 0.034298197
B10: =B9+1 -> 7 | C10: =C9+1 -> 2020 | D10: 261068 | E10: =D10/D9-1 -> -0.13535891 | I10: 17 | J10: 2030 | K10: =$I$35+B20*$I$36 -> 457678.15 | L10: =K10/D19-1 -> 0.03316084
B11: =B10+1 -> 8 | C11: =C10+1 -> 2021 | D11: 249795 | E11: =D11/D10-1 -> -0.043180321
B12: =B11+1 -> 9 | C12: =C11+1 -> 2022 | D12: 278454 | E12: =D12/D11-1 -> 0.11473008
B13: =B12+1 -> 10 | C13: =C12+1 -> 2023 | D13: 345967 | E13: =D13/D12-1 -> 0.24245656
B14: =B13+1 -> 11 | C14: =C13+1 -> 2024 | D14: 434016 | E14: =D14/D13-1 -> 0.25450115
B15: =B14+1 -> 12 | C15: =C14+1 -> 2025 | D15: 439695 | E15: =D15/D14-1 -> 0.013084771
B16: 13 | C16: =C15+1 -> 2026 | D16: =FORECAST(B16,$D$4:$D$15,$B$4:$B$15) -> 398918.7 | E16: =D16/D15-1 -> -0.0927377
B17: 14 | C17: =C16+1 -> 2027 | D17: =FORECAST(B17,$D$4:$D$15,$B$4:$B$15) -> 413608.56 | E17: =D17/D16-1 -> 0.036824204
B18: 15 | C18: =C17+1 -> 2028 | D18: =FORECAST(B18,$D$4:$D$15,$B$4:$B$15) -> 428298.42 | E18: =D18/D17-1 -> 0.035516343
B19: 16 | C19: =C18+1 -> 2029 | D19: =FORECAST(B19,$D$4:$D$15,$B$4:$B$15) -> 442988.29 | E19: =D19/D18-1 -> 0.034298197 | H19: SUMMARY OUTPUT
B20: 17 | C20: =C19+1 -> 2030 | D20: =FORECAST(B20,$D$4:$D$15,$B$4:$B$15) -> 457678.15 | E20: =D20/D19-1 -> 0.03316084
H21: Regression Statistics
H22: Multiple R | I22: 0.77380616
H23: R Square | I23: 0.59877597
H24: Adjusted R Square | I24: 0.55865356
B25: Arthimetic Mean (Growth) | C25: =AVERAGE(E5:E15) -> 0.065312823 | H25: Standard Error | I25: 45472.316
B26: Geometric Mean | C26: =_xlfn.RRI(B15,D4,D15) -> 0.054408166 | H26: Observations | I26: 12
B27: Harcoded Formula | C27: =(D15/D4)^(1/B15)-1 -> 0.054408166
H28: ANOVA
B29: Standard Deviation | C29: =_xlfn.STDEV.S(E5:E15) -> 0.11684032 | I29: df | J29: SS | K29: MS | L29: F | M29: Significance F
H30: Regression | I30: 1 | J30: 3.0858269e+10 | K30: 3.0858269e+10 | L30: 14.923731 | M30: 0.0031441948
H31: Residual | I31: 10 | J31: 2.0677315e+10 | K31: 2.0677315e+09
H32: Total | I32: 11 | J32: 5.1535584e+10
I34: Coefficients | J34: Standard Error | K34: t Stat | L34: P-value | M34: Lower 95% | N34: Upper 95% | O34: Lower 95.0% | P34: Upper 95.0%
H35: Intercept | I35: 207950.47 | J35: 27986.276 | K35: 7.4304446 | L35: 2.2349424e-05 | M35: 145593.16 | N35: 270307.78 | O35: 145593.16 | P35: 270307.78
H36: Year Weight | I36: 14689.864 | J36: 3802.5861 | K36: 3.8631246 | L36: 0.0031441948 | M36: 6217.1739 | N36: 23162.553 | O36: 6217.1739 | P36: 23162.553

Sheet WACC
F6: Beta = “how jumpy” the stock is
B7: Weighted Average Cost of Capital
B9: All Figures are in INR unless Stated otherwise
B11: Peer Comps
J12: Debt/ | K12: Debt/ | L12: Levered/ | M12: Unlevered/
B13: Name of the Comp | F13: Country | G13: Total Debt | H13: Total Equity | I13: Tax Rate 1 | J13: Equity | K13: Capital | L13: Beta 2 | M13: Beta 3
B15: Eternal Ltd | F15: India | G15: ='Retailing Companies'!E4 -> 2045 | H15: ='Retailing Companies'!D4 -> 316965.77 | I15: 0.3 | J15: =G15/H15 -> 0.0064518008 | K15: =G15/(G15+H15) -> 0.0064104419 | L15: 1.57 | M15: =L15/(1+(1-I15)*J15) -> 1.5629413 | N15: LB/(1+(1 - Tax)* Debt/Equity)
B16: Avenue Super. | F16: India | G16: ='Retailing Companies'!E5 -> 819.62 | H16: ='Retailing Companies'!D5 -> 287519.9 | I16: 0.3 | J16: =G16/H16 -> 0.0028506549 | K16: =G16/(G16+H16) -> 0.0028425517 | L16: 1.23 | M16: =L16/(1+(1-I16)*J16) -> 1.2275505
B17: Trent | F17: India | G17: ='Retailing Companies'!E6 -> 2237.19 | H17: ='Retailing Companies'!D6 -> 171192.1 | I17: 0.3 | J17: =G17/H17 -> 0.013068302 | K17: =G17/(G17+H17) -> 0.012899724 | L17: 1.38 | M17: =L17/(1+(1-I17)*J17) -> 1.3674905
B18: Swiggy | F18: India | G18: ='Retailing Companies'!E7 -> 1702.95 | H18: ='Retailing Companies'!D7 -> 103199.58 | I18: 0.3 | J18: =G18/H18 -> 0.016501521 | K18: =G18/(G18+H18) -> 0.016233641 | L18: 1.61 | M18: =L18/(1+(1-I18)*J18) -> 1.5916152
B19: Info Edg.(India) | F19: India | G19: ='Retailing Companies'!E8 -> 267.34 | H19: ='Retailing Companies'!D8 -> 86492.82 | I19: 0.3 | J19: =G19/H19 -> 0.0030908924 | K19: =G19/(G19+H19) -> 0.0030813682 | L19: 1.62 | M19: =L19/(1+(1-I19)*J19) -> 1.6165025
H21: Average | I21: =AVERAGE(I15:I19) -> 0.3 | J21: =AVERAGE(J15:J19) -> 0.0083926341 | K21: =AVERAGE(K15:K19) -> 0.0082935454 | L21: =AVERAGE(L15:L19) -> 1.482 | M21: =AVERAGE(M15:M19) -> 1.47322
H22: Median | I22: =MEDIAN(I15:I19) -> 0.3 | J22: =MEDIAN(J15:J19) -> 0.0064518008 | K22: =MEDIAN(K15:K19) -> 0.0064104419 | L22: =MEDIAN(L15:L19) -> 1.57 | M22: =MEDIAN(M15:M19) -> 1.5629413
B25: Cost of Debt | I25: Cost of Equity
B26: Pre-Tax Cost of Debt | G26: =83/819 -> 0.1013431 | I26: Risk Free Rate | M26: 0.06514
B27: Tax Rate | G27: 0.3 | I27: Equity Risk Premium | M27: ='Market Return'!G6-WACC!M26 -> 0.102008
B28: After-Tax Cost of Debt | G28: =G26* (1 - G27) -> 0.070940171 | I28: Levered Beta 4 | M28: =M37 -> 1.4798734
I29: Cost of Equity | M29: =M26+M27*M28 -> 0.21609893
B32: Capital Structure | I32: Levered Beta
D34: Current | E34: Target | I34: Comps Median Unlevered Beta | M34: =M21 -> 1.47322
B35: Total Debt | C35: =G16 -> 819.62 | D35: =C35/$C$37 -> 0.0028425517 | E35: =K22 -> 0.0064104419 | I35: Target Debt/Equity | M35: =E39 -> 0.0064518008
B36: Market Capitalization | C36: =H16 -> 287519.9 | D36: =C36/$C$37 -> 0.99715745 | E36: =E37-E35 -> 0.99358956 | I36: Tax Rate | M36: =G27 -> 0.3
B37: Total Capital | C37: =SUM(C35:C36) -> 288339.52 | D37: =C37/$C$37 -> 1 | E37: 1 | I37: Levered Beta | M37: =M34 * (1 + (1 - M36) * M35) -> 1.4798734
B39: Debt/Equity | D39: =D35/D36 -> 0.0028506549 | E39: =E35/E36 -> 0.0064518008
I40: Weighted Average Cost of Capital
I42: Total Equity | M42: =M29 -> 0.21609893
I43: Equity Weight | M43: =E36 -> 0.99358956
I45: Total Debt | M45: =G28 -> 0.070940171
I46: Debt Weight | M46: =E35 -> 0.0064104419
I48: WACC | M48: =(M42*M43)+(M45*M46) -> 0.2151684

Sheet Beta
B2: Avenue SuperMart!
D3: Beta formula = how much stock and market move together (covariance), divided by how volatile the market is (variance). Website Used - Investor.Com, PrimeInvestor.com, Screener | T3: Hindustan | AJ3: Eternal
C7: Beta Calculation - Regression
C9: Avenue SuperMart Data
AL10: Date | AM10: Closing Price | AN10: Return | AP10: Market
C11: Date | D11: Closing Price | E11: Return | G11: Closing Price | H11: Return | J11: Beta Drifting | O11: Beta 1 | P11: =SLOPE(E13:E116,H13:H116) -> 1.2295363 | V11: Date | W11: Closing Price | X11: Return | Z11: Closing Price | AA11: Return | AD11: Beta Rifting | AG11: Beta Calculation | AL11: 44402 | AM11: 133.5 | AR11: Beta 1 | AS11: =_xlfn.COVARIANCE.S(AN12:AN93,AP12:AP93)/_xlfn.VAR.S(AP12:AP93) -> 1.5670688 | AU11: Beta | AW11: =AT37 -> 1.5670688
C12: 44248 | D12: 2994.2 | G12: 14529.15 | J12: Raw Levered Beta | K12: =P11 -> 1.2295363 | O12: Beta 2 | P12: =_xlfn.COVARIANCE.S(E12:E116,H12:H116)/_xlfn.VAR.S(H12:H116) -> 1.2295363 | V12: 44248 | W12: 2123.59 | Z12: 14529.15 | AD12: Raw Leverred Beta | AE12: =AH14 -> 0.65936329 | AG12: Beta 1 | AH12: =SLOPE(X13:X116,AA13:AA116) -> 0.65936329 | AL12: 44409 | AM12: 131.35 | AN12: -0.0161 | AP12: 0.0301
C13: 44255 | D13: 3286.1 | E13: 0.0975 | G13: 14938.1 | H13: 0.0281 | J13: Beta Weight | K13: 0.75 | V13: 44255 | W13: 2192.37 | X13: 0.0324 | Z13: 14938.1 | AA13: 0.0281 | AD13: Beta Weight | AE13: 0.25 | AG13: Beta 2 | AH13: =_xlfn.COVARIANCE.S(X13:X116,AA13:AA116)/_xlfn.VAR.S(AA13:AA116) -> 0.65936329 | AL13: 44416 | AM13: 137.35 | AN13: 0.0457 | AP13: 0.0179
C14: 44262 | D14: 3129.35 | E14: -0.0477 | G14: 15030.95 | H14: 0.0062 | O14: Beta 3 | P14: =K93 -> 1.2295363 | V14: 44262 | W14: 2196.01 | X14: 0.0017 | Z14: 15030.95 | AA14: 0.0062 | AG14: Beta 3 | AH14: =AD42 -> 0.65936329 | AL14: 44423 | AM14: 139.3 | AN14: 0.0142 | AP14: -0.0048 | AR14: Beta | AS14: =SLOPE(AN12:AN93,AP12:AP93) -> 1.5670688
C15: 44269 | D15: 2960.3 | E15: -0.054 | G15: 14744 | H15: -0.0191 | J15: Market Beta | K15: 1 | V15: 44269 | W15: 2302.88 | X15: 0.0487 | Z15: 14744 | AA15: -0.0191 | AD15: Market Beta | AE15: 1 | AL15: 44430 | AM15: 124.7 | AN15: -0.1048 | AP15: 0.0155
C16: 44276 | D16: 2855.2 | E16: -0.0355 | G16: 14507.3 | H16: -0.0161 | J16: Market Weight Beta | K16: 0.25 | V16: 44276 | W16: 2308.71 | X16: 0.0025 | Z16: 14507.3 | AA16: -0.0161 | AD16: Market Weight | AE16: 0.75 | AL16: 44437 | AM16: 149.75 | AN16: 0.2009 | AP16: 0.037
C17: 44283 | D17: 2912.7 | E17: 0.0201 | G17: 14867.35 | H17: 0.0248 | V17: 44283 | W17: 2389.58 | X17: 0.035 | Z17: 14867.35 | AA17: 0.0248 | AL17: 44444 | AM17: 141.6 | AN17: -0.0544 | AP17: 0.0026 | AR17: Beta | AS17: =_xlfn.COVARIANCE.S(AP12:AP93,AN12:AN93)/_xlfn.VAR.S(AP12:AP93) -> 1.5670688
C18: 44290 | D18: 2947.75 | E18: 0.012 | G18: 14834.85 | H18: -0.0022 | J18: Adjusted Beta | K18: =(K12*K13)+(K15*K16) -> 1.1721522 | V18: 44290 | W18: 2466.18 | X18: 0.0321 | Z18: 14834.85 | AA18: -0.0022 | AD18: Adjusted Beta | AE18: =(AE12*AE13)+(AE15*AE16) -> 0.91484082 | AL18: 44451 | AM18: 137.9 | AN18: -0.0261 | AP18: 0.0124
C19: 44297 | D19: 2919.9 | E19: -0.0094 | G19: 14617.85 | H19: -0.0146 | V19: 44297 | W19: 2449.15 | X19: -0.0069 | Z19: 14617.85 | AA19: -0.0146 | AL19: 44458 | AM19: 136.65 | AN19: -0.0091 | AP19: 0.0152
C20: 44304 | D20: 2713.7 | E20: -0.0706 | G20: 14341.35 | H20: -0.0189 | V20: 44304 | W20: 2298.6 | X20: -0.0615 | Z20: 14341.35 | AA20: -0.0189 | AL20: 44465 | AM20: 138 | AN20: 0.0099 | AP20: -0.018 | AS20: SUMMARY OUTPUT
C21: 44311 | D21: 2852.9 | E21: 0.0513 | G21: 14631.1 | H21: 0.0202 | V21: 44311 | W21: 2344.42 | X21: 0.0199 | Z21: 14631.1 | AA21: 0.0202 | AL21: 44472 | AM21: 136.15 | AN21: -0.0134 | AP21: 0.0207
C22: 44318 | D22: 2895.5 | E22: 0.0149 | G22: 14823.15 | H22: 0.0131 | V22: 44318 | W22: 2401.64 | X22: 0.0244 | Z22: 14823.15 | AA22: 0.0131 | AL22: 44479 | AM22: 135 | AN22: -0.0084 | AP22: 0.0248 | AS22: Regression Statistics
C23: 44325 | D23: 2844.65 | E23: -0.0176 | G23: 14677.8 | H23: -0.0098 | V23: 44325 | W23: 2367.42 | X23: -0.0142 | Z23: 14677.8 | AA23: -0.0098 | AL23: 44486 | AM23: 137.75 | AN23: 0.0204 | AP23: -0.0122 | AS23: Multiple R | AT23: 0.429841
C24: 44332 | D24: 3034.15 | E24: 0.0666 | G24: 15175.3 | H24: 0.0339 | V24: 44332 | W24: 2352.88 | X24: -0.0061 | Z24: 15175.3 | AA24: 0.0339 | AL24: 44493 | AM24: 131.55 | AN24: -0.045 | AP24: -0.0245 | AS24: R Square | AT24: 0.18476328
C25: 44339 | D25: 3022.1 | E25: -0.004 | G25: 15435.65 | H25: 0.0172 | V25: 44339 | W25: 2312.49 | X25: -0.0172 | Z25: 15435.65 | AA25: 0.0172 | AC25: SUMMARY OUTPUT | AL25: 44500 | AM25: 131.35 | AN25: -0.0015 | AP25: 0.0139 | AS25: Adjusted R Square | AT25: 0.17457282
C26: 44346 | D26: 3197 | E26: 0.0579 | G26: 15670.25 | H26: 0.0152 | V26: 44346 | W26: 2332.76 | X26: 0.0088 | Z26: 15670.25 | AA26: 0.0152 | AL26: 44507 | AM26: 153 | AN26: 0.1648 | AP26: 0.0104 | AS26: Standard Error | AT26: 0.070983179
C27: 44353 | D27: 3175.55 | E27: -0.0067 | G27: 15799.35 | H27: 0.0082 | V27: 44353 | W27: 2357.11 | X27: 0.0104 | Z27: 15799.35 | AA27: 0.0082 | AC27: Regression Statistics | AL27: 44514 | AM27: 154.7 | AN27: 0.0111 | AP27: -0.0187 | AS27: Observations | AT27: 82
C28: 44360 | D28: 3317.7 | E28: 0.0448 | G28: 15683.35 | H28: -0.0073 | V28: 44360 | W28: 2473.05 | X28: 0.0492 | Z28: 15683.35 | AA28: -0.0073 | AC28: Multiple R | AD28: 0.40799237 | AL28: 44521 | AM28: 148.15 | AN28: -0.0423 | AP28: -0.0416
C29: 44367 | D29: 3315.35 | E29: -0.0007 | G29: 15860.35 | H29: 0.0113 | V29: 44367 | W29: 2438.94 | X29: -0.0138 | Z29: 15860.35 | AA29: 0.0113 | AC29: R Square | AD29: 0.16645777 | AL29: 44528 | AM29: 144.9 | AN29: -0.0219 | AP29: 0.01 | AS29: ANOVA
C30: 44374 | D30: 3314.3 | E30: -0.0003 | G30: 15722.2 | H30: -0.0087 | V30: 44374 | W30: 2477.44 | X30: 0.0158 | Z30: 15722.2 | AA30: -0.0087 | AC30: Adjusted R Square | AD30: 0.15828579 | AL30: 44535 | AM30: 140.55 | AN30: -0.03 | AP30: 0.0183 | AT30: df | AU30: SS | AV30: MS | AW30: F | AX30: Significance F
C31: 44381 | D31: 3377.6 | E31: 0.0191 | G31: 15689.8 | H31: -0.0021 | V31: 44381 | W31: 2441.73 | X31: -0.0144 | Z31: 15689.8 | AA31: -0.0021 | AC31: Standard Error | AD31: 0.030143772 | AL31: 44542 | AM31: 135.35 | AN31: -0.037 | AP31: -0.03 | AS31: Regression | AT31: 1 | AU31: 0.091355103 | AV31: 0.091355103 | AW31: 18.131007 | AX31: 5.5742683e-05
C32: 44388 | D32: 3349.2 | E32: -0.0084 | G32: 15923.4 | H32: 0.0149 | V32: 44388 | W32: 2407.81 | X32: -0.0139 | Z32: 15923.4 | AA32: 0.0149 | AC32: Observations | AD32: 104 | AL32: 44549 | AM32: 131.45 | AN32: -0.0288 | AP32: 0.0011 | AS32: Residual | AT32: 80 | AU32: 0.40308893 | AV32: 0.0050386117
C33: 44395 | D33: 3413.2 | E33: 0.0191 | G33: 15856.05 | H33: -0.0042 | V33: 44395 | W33: 2348.75 | X33: -0.0245 | Z33: 15856.05 | AA33: -0.0042 | AL33: 44556 | AM33: 137.4 | AN33: 0.0453 | AP33: 0.0206 | AS33: Total | AT33: 81 | AU33: 0.49444404
C34: 44402 | D34: 3500.8 | E34: 0.0257 | G34: 15763.05 | H34: -0.0059 | V34: 44402 | W34: 2324.05 | X34: -0.0105 | Z34: 15763.05 | AA34: -0.0059 | AC34: ANOVA | AL34: 44563 | AM34: 129.25 | AN34: -0.0593 | AP34: 0.0264
C35: 44409 | D35: 3529.2 | E35: 0.0081 | G35: 16238.2 | H35: 0.0301 | V35: 44409 | W35: 2362.09 | X35: 0.0164 | Z35: 16238.2 | AA35: 0.0301 | AD35: df | AE35: SS | AF35: MS | AG35: F | AH35: Significance F | AL35: 44570 | AM35: 133.6 | AN35: 0.0337 | AP35: 0.0249 | AT35: Coefficients | AU35: Standard Error | AV35: t Stat | AW35: P-value | AX35: Lower 95% | AY35: Upper 95% | AZ35: Lower 95.0% | BA35: Upper 95.0%
C36: 44416 | D36: 3594.55 | E36: 0.0185 | G36: 16529.1 | H36: 0.0179 | V36: 44416 | W36: 2394.96 | X36: 0.0139 | Z36: 16529.1 | AA36: 0.0179 | AC36: Regression | AD36: 1 | AE36: 0.018508526 | AF36: 0.018508526 | AG36: 20.369325 | AH36: 1.7153431e-05 | AL36: 44577 | AM36: 113.65 | AN36: -0.1493 | AP36: -0.035 | AS36: Intercept | AT36: -0.010142178 | AU36: 0.0078575385 | AV36: -1.2907577 | AW36: 0.20050552 | AX36: -0.025779178 | AY36: 0.0054948217 | AZ36: -0.025779178 | BA36: 0.0054948217
C37: 44423 | D37: 3643.1 | E37: 0.0135 | G37: 16450.5 | H37: -0.0048 | V37: 44423 | W37: 2609.01 | X37: 0.0894 | Z37: 16450.5 | AA37: -0.0048 | AC37: Residual | AD37: 102 | AE37: 0.092681992 | AF37: 0.00090864698 | AL37: 44584 | AM37: 89.55 | AN37: -0.2121 | AP37: -0.0292 | AS37: X Variable 1 | AT37: 1.5670688 | AU37: 0.36802482 | AV37: 4.258052 | AW37: 5.5742683e-05 | AX37: 0.83467609 | AY37: 2.2994616 | AZ37: 0.83467609 | BA37: 2.2994616
C38: 44430 | D38: 3833.05 | E38: 0.0521 | G38: 16705.2 | H38: 0.0155 | V38: 44430 | W38: 2667.33 | X38: 0.0224 | Z38: 16705.2 | AA38: 0.0155 | AC38: Total | AD38: 103 | AE38: 0.11119052 | AL38: 44591 | AM38: 94.2 | AN38: 0.0519 | AP38: 0.0242
C39: 44437 | D39: 3938.9 | E39: 0.0276 | G39: 17323.6 | H39: 0.037 | V39: 44437 | W39: 2755.73 | X39: 0.0331 | Z39: 17323.6 | AA39: 0.037 | AL39: 44598 | AM39: 88.7 | AN39: -0.0584 | AP39: -0.0081
C40: 44444 | D40: 3950.5 | E40: 0.0029 | G40: 17369.25 | H40: 0.0026 | V40: 44444 | W40: 2799.5 | X40: 0.0159 | Z40: 17369.25 | AA40: 0.0026 | AD40: Coefficients | AE40: Standard Error | AF40: t Stat | AG40: P-value | AH40: Lower 95% | AL40: 44605 | AM40: 85.9 | AN40: -0.0316 | AP40: -0.0057
C41: 44451 | D41: 4239.65 | E41: 0.0732 | G41: 17585.15 | H41: 0.0124 | V41: 44451 | W41: 2711.45 | X41: -0.0315 | Z41: 17585.15 | AA41: 0.0124 | AC41: Intercept | AD41: 0.00070350567 | AE41: 0.0029698487 | AF41: 0.23688266 | AG41: 0.81322291 | AH41: -0.0051871752 | AL41: 44612 | AM41: 78.8 | AN41: -0.0827 | AP41: -0.0358
C42: 44458 | D42: 4422.35 | E42: 0.0431 | G42: 17853.2 | H42: 0.0152 | V42: 44458 | W42: 2735.76 | X42: 0.009 | Z42: 17853.2 | AA42: 0.0152 | AC42: X Variable 1 | AD42: 0.65936329 | AE42: 0.14609537 | AF42: 4.5132389 | AG42: 1.7153431e-05 | AH42: 0.36958382 | AL42: 44619 | AM42: 80.2 | AN42: 0.0178 | AP42: -0.0248
C43: 44465 | D43: 4235.6 | E43: -0.0422 | G43: 17532.05 | H43: -0.018 | V43: 44465 | W43: 2693.33 | X43: -0.0155 | Z43: 17532.05 | AA43: -0.018 | AL43: 44626 | AM43: 79.9 | AN43: -0.0037 | AP43: 0.0237
C44: 44472 | D44: 4407.95 | E44: 0.0407 | G44: 17895.2 | H44: 0.0207 | V44: 44472 | W44: 2629.58 | X44: -0.0237 | Z44: 17895.2 | AA44: 0.0207 | AL44: 44633 | AM44: 80.85 | AN44: 0.0119 | AP44: 0.0395
C45: 44479 | D45: 5323.75 | E45: 0.2078 | G45: 18338.55 | H45: 0.0248 | V45: 44479 | W45: 2639.04 | X45: 0.0036 | Z45: 18338.55 | AA45: 0.0248 | AL45: 44640 | AM45: 80.6 | AN45: -0.0031 | AP45: -0.0078
C46: 44486 | D46: 4521.45 | E46: -0.1507 | G46: 18114.9 | H46: -0.0122 | V46: 44486 | W46: 2444.37 | X46: -0.0738 | Z46: 18114.9 | AA46: -0.0122 | AL46: 44647 | AM46: 84.3 | AN46: 0.0459 | AP46: 0.0302
C47: 44493 | D47: 4635.45 | E47: 0.0252 | G47: 17671.65 | H47: -0.0245 | V47: 44493 | W47: 2383.66 | X47: -0.0248 | Z47: 17671.65 | AA47: -0.0245 | AL47: 44654 | AM47: 83.4 | AN47: -0.0107 | AP47: 0.0064
C48: 44500 | D48: 4783.7 | E48: 0.032 | G48: 17916.8 | H48: 0.0139 | V48: 44500 | W48: 2413.24 | X48: 0.0124 | Z48: 17916.8 | AA48: 0.0139 | AL48: 44661 | AM48: 83.9 | AN48: 0.006 | AP48: -0.0174
C49: 44507 | D49: 5078.55 | E49: 0.0616 | G49: 18102.75 | H49: 0.0104 | V49: 44507 | W49: 2395.41 | X49: -0.0074 | Z49: 18102.75 | AA49: 0.0104 | AL49: 44668 | AM49: 81.2 | AN49: -0.0322 | AP49: -0.0174
C50: 44514 | D50: 5080.9 | E50: 0.0005 | G50: 17764.8 | H50: -0.0187 | V50: 44514 | W50: 2389.88 | X50: -0.0023 | Z50: 17764.8 | AA50: -0.0187 | AL50: 44675 | AM50: 71.75 | AN50: -0.1164 | AP50: -0.004
C51: 44521 | D51: 4718.75 | E51: -0.0713 | G51: 17026.45 | H51: -0.0416 | V51: 44521 | W51: 2325.84 | X51: -0.0268 | Z51: 17026.45 | AA51: -0.0416 | AL51: 44682 | AM51: 60.5 | AN51: -0.1568 | AP51: -0.0404
C52: 44528 | D52: 4799.05 | E52: 0.017 | G52: 17196.7 | H52: 0.01 | V52: 44528 | W52: 2334.35 | X52: 0.0037 | Z52: 17196.7 | AA52: 0.01 | AL52: 44689 | AM52: 56.85 | AN52: -0.0603 | AP52: -0.0383
C53: 44535 | D53: 4796.6 | E53: -0.0005 | G53: 17511.3 | H53: 0.0183 | V53: 44535 | W53: 2323.55 | X53: -0.0046 | Z53: 17511.3 | AA53: 0.0183 | AL53: 44696 | AM53: 58.05 | AN53: 0.0211 | AP53: 0.0307
C54: 44542 | D54: 4697.8 | E54: -0.0206 | G54: 16985.2 | H54: -0.03 | V54: 44542 | W54: 2221.41 | X54: -0.044 | Z54: 16985.2 | AA54: -0.03 | AL54: 44703 | AM54: 62.05 | AN54: 0.0689 | AP54: 0.0053
... C75: 44689 | D75: 3230.6 | E75: -0.1188 | G75: 15782.15 | H75: -0.0383 | V75: 44689 | W75: 2185.4 | X75: 0.0209 | Z75: 15782.15 | AA75: -0.0383 | AL75: 44850 | AM75: 61.8 | AN75: -0.0016 | AP75: 0.0227
C76: 44696 | D76: 3630.4 | E76: 0.1238 | G76: 16266.15 | H76: 0.0307 | J76: SUMMARY OUTPUT | V76: 44696 | W76: 2316.73 | X76: 0.0601 | Z76: 16266.15 | AA76: 0.0307 | AL76: 44857 | AM76: 62.6 | AN76: 0.0129 | AP76: 0.012
C77: 44703 | D77: 3613.85 | E77: -0.0046 | G77: 16352.45 | H77: 0.0053 | V77: 44703 | W77: 2321.36 | X77: 0.002 | Z77: 16352.45 | AA77: 0.0053 | AL77: 44864 | AM77: 63 | AN77: 0.0064 | AP77: 0.0186
C78: 44710 | D78: 3820.1 | E78: 0.0571 | G78: 16584.3 | H78: 0.0142 | J78: Regression Statistics | V78: 44710 | W78: 2282.86 | X78: -0.0166 | Z78: 16584.3 | AA78: 0.0142 | AL78: 44871 | AM78: 72.8 | AN78: 0.1556 | AP78: 0.0128
C79: 44717 | D79: 3755.65 | E79: -0.0169 | G79: 16201.8 | H79: -0.0231 | J79: Multiple R | K79: 0.51030043 | V79: 44717 | W79: 2191.18 | X79: -0.0402 | Z79: 16201.8 | AA79: -0.0231 | AL79: 44878 | AM79: 67.15 | AN79: -0.0776 | AP79: -0.0023
C80: 44724 | D80: 3460.55 | E80: -0.0786 | G80: 15293.5 | H80: -0.0561 | J80: R Square | K80: 0.26040652 | V80: 44724 | W80: 2102.08 | X80: -0.0407 | Z80: 15293.5 | AA80: -0.0561 | AL80: 44885 | AM80: 64 | AN80: -0.0469 | AP80: 0.0112
C81: 44731 | D81: 3412 | E81: -0.014 | G81: 15699.25 | H81: 0.0265 | J81: Adjusted R Square | K81: 0.25315561 | V81: 44731 | W81: 2294.76 | X81: 0.0917 | Z81: 15699.25 | AA81: 0.0265 | AL81: 44892 | AM81: 68.55 | AN81: 0.0711 | AP81: 0.0099
C82: 44738 | D82: 3388.75 | E82: -0.0068 | G82: 15752.05 | H82: 0.0034 | J82: Standard Error | K82: 0.042332412 | V82: 44738 | W82: 2273.3 | X82: -0.0094 | Z82: 15752.05 | AA82: 0.0034 | AL82: 44899 | AM82: 64.15 | AN82: -0.0642 | AP82: -0.0107
C83: 44745 | D83: 3941.7 | E83: 0.1632 | G83: 16220.6 | H83: 0.0297 | J83: Observations | K83: 104 | V83: 44745 | W83: 2486.95 | X83: 0.094 | Z83: 16220.6 | AA83: 0.0297 | AL83: 44906 | AM83: 62.15 | AN83: -0.0312 | AP83: -0.0123
C84: 44752 | D84: 3926.8 | E84: -0.0038 | G84: 16049.2 | H84: -0.0106 | V84: 44752 | W84: 2558.31 | X84: 0.0287 | Z84: 16049.2 | AA84: -0.0106 | AL84: 44913 | AM84: 53.65 | AN84: -0.1368 | AP84: -0.0253
C85: 44759 | D85: 3963.4 | E85: 0.0093 | G85: 16719.45 | H85: 0.0418 | J85: ANOVA | V85: 44759 | W85: 2630.13 | X85: 0.0281 | Z85: 16719.45 | AA85: 0.0418 | AL85: 44920 | AM85: 59.3 | AN85: 0.1053 | AP85: 0.0168
C86: 44766 | D86: 4243.85 | E86: 0.0708 | G86: 17158.25 | H86: 0.0262 | K86: df | L86: SS | M86: MS | N86: F | O86: Significance F | V86: 44766 | W86: 2626.94 | X86: -0.0012 | Z86: 17158.25 | AA86: 0.0262 | AL86: 44927 | AM86: 55.25 | AN86: -0.0683 | AP86: -0.0136
C87: 44773 | D87: 4232.25 | E87: -0.0027 | G87: 17397.5 | H87: 0.0139 | J87: Regression | K87: 1 | L87: 0.064358364 | M87: 0.064358364 | N87: 35.913602 | O87: 3.1350217e-08 | V87: 44773 | W87: 2634.91 | X87: 0.003 | Z87: 17397.5 | AA87: 0.0139 | AL87: 44934 | AM87: 53.25 | AN87: -0.0362 | AP87: 0.0054
C88: 44780 | D88: 4336.7 | E88: 0.0247 | G88: 17698.15 | H88: 0.0173 | J88: Residual | K88: 102 | L88: 0.18278738 | M88: 0.0017920331 | V88: 44780 | W88: 2584.66 | X88: -0.0191 | Z88: 17698.15 | AA88: 0.0173 | AL88: 44941 | AM88: 51.45 | AN88: -0.0338 | AP88: 0.004
C89: 44787 | D89: 4382 | E89: 0.0104 | G89: 17758.45 | H89: 0.0034 | J89: Total | K89: 103 | L89: 0.24714575 | V89: 44787 | W89: 2624.1 | X89: 0.0153 | Z89: 17758.45 | AA89: 0.0034 | AL89: 44948 | AM89: 46.95 | AN89: -0.0875 | AP89: -0.0235
C90: 44794 | D90: 4409.65 | E90: 0.0063 | G90: 17558.9 | H90: -0.0112 | V90: 44794 | W90: 2561.35 | X90: -0.0239 | Z90: 17558.9 | AA90: -0.0112 | AL90: 44955 | AM90: 48.75 | AN90: 0.0383 | AP90: 0.0142
C91: 44801 | D91: 4576.8 | E91: 0.0379 | G91: 17539.45 | H91: -0.0011 | K91: Coefficients | L91: Standard Error | M91: t Stat | N91: P-value | O91: Lower 95% | P91: Upper 95% | Q91: Lower 95.0% | R91: Upper 95.0% | V91: 44801 | W91: 2593.27 | X91: 0.0125 | Z91: 17539.45 | AA91: -0.0011 | AL91: 44962 | AM91: 53.3 | AN91: 0.0933 | AP91: 0.0001
C92: 44808 | D92: 4386.1 | E92: -0.0417 | G92: 17833.35 | H92: 0.0168 | J92: Intercept | K92: 0.00024348184 | L92: 0.0041707077 | M92: 0.058379022 | N92: 0.95356094 | O92: -0.0080290972 | P92: 0.0085160608 | Q92: -0.0080290972 | R92: 0.0085160608 | V92: 44808 | W92: 2578.43 | X92: -0.0057 | Z92: 17833.35 | AA92: 0.0168 | AL92: 44969 | AM92: 51.8 | AN92: -0.0281 | AP92: 0.0049
C93: 44815 | D93: 4327.55 | E93: -0.0133 | G93: 17530.85 | H93: -0.017 | J93: X Variable 1 | K93: 1.2295363 | L93: 0.20516906 | M93: 5.9927958 | N93: 3.1350217e-08 | O93: 0.82258442 | P93: 1.6364881 | Q93: 0.82258442 | R93: 1.6364881 | V93: 44815 | W93: 2518.12 | X93: -0.0234 | Z93: 17530.85 | AA93: -0.017 | AL93: 44976 | AM93: 54.45 | AN93: 0.0512 | AP93: -0.0267
C94: 44822 | D94: 4367 | E94: 0.0091 | G94: 17327.35 | H94: -0.0116 | V94: 44822 | W94: 2671.41 | X94: 0.0609 | Z94: 17327.35 | AA94: -0.0116
C95: 44829 | D95: 4386.55 | E95: 0.0045 | G95: 17094.35 | H95: -0.0134 | V95: 44829 | W95: 2685.76 | X95: 0.0054 | Z95: 17094.35 | AA95: -0.0134
C96: 44836 | D96: 4471.45 | E96: 0.0194 | G96: 17314.65 | H96: 0.0129 | V96: 44836 | W96: 2589.39 | X96: -0.0359 | Z96: 17314.65 | AA96: 0.0129
C97: 44843 | D97: 4306.15 | E97: -0.037 | G97: 17185.7 | H97: -0.0074 | V97: 44843 | W97: 2565.58 | X97: -0.0092 | Z97: 17185.7 | AA97: -0.0074
C98: 44850 | D98: 4215.55 | E98: -0.021 | G98: 17576.3 | H98: 0.0227 | V98: 44850 | W98: 2643.38 | X98: 0.0303 | Z98: 17576.3 | AA98: 0.0227
C99: 44857 | D99: 4307.35 | E99: 0.0218 | G99: 17786.8 | H99: 0.012 | V99: 44857 | W99: 2514.24 | X99: -0.0489 | Z99: 17786.8 | AA99: 0.012
C100: 44864 | D100: 4167.35 | E100: -0.0325 | G100: 18117.15 | H100: 0.0186 | V100: 44864 | W100: 2510.35 | X100: -0.0015 | Z100: 18117.15 | AA100: 0.0186
C101: 44871 | D101: 4128.35 | E101: -0.0094 | G101: 18349.7 | H101: 0.0128 | V101: 44871 | W101: 2493.12 | X101: -0.0069 | Z101: 18349.7 | AA101: 0.0128
C102: 44878 | D102: 3910.6 | E102: -0.0527 | G102: 18307.65 | H102: -0.0023 | V102: 44878 | W102: 2473.85 | X102: -0.0077 | Z102: 18307.65 | AA102: -0.0023
C103: 44885 | D103: 3904.45 | E103: -0.0016 | G103: 18512.75 | H103: 0.0112 | V103: 44885 | W103: 2527.39 | X103: 0.0216 | Z103: 18512.75 | AA103: 0.0112
C104: 44892 | D104: 4005.75 | E104: 0.0259 | G104: 18696.1 | H104: 0.0099 | V104: 44892 | W104: 2604.73 | X104: 0.0306 | Z104: 18696.1 | AA104: 0.0099
C105: 44899 | D105: 4002.4 | E105: -0.0008 | G105: 18496.6 | H105: -0.0107 | V105: 44899 | W105: 2711.45 | X105: 0.041 | Z105: 18496.6 | AA105: -0.0107
... C116: 44976 | D116: 3499.2 | E116: -0.0129 | G116: 17465.8 | H116: -0.0267 | V116: 44976 | W116: 2474.35 | X116: -0.0124 | Z116: 17465.8 | AA116: -0.0267

Sheet Intrinsic Growth
B3: ="Intrinsic Growth - "&UPDATE -> Intrinsic Growth - Tata Motors
B4: Calculation of ROIC | C4: ='Asian Paints Data'!C2 -> 41699 | D4: ='Asian Paints Data'!D2 -> 42064 | E4: ='Asian Paints Data'!E2 -> 42430 | F4: ='Asian Paints Data'!F2 -> 42795 | G4: ='Asian Paints Data'!G2 -> 43160 | H4: ='Asian Paints Data'!H2 -> 43525 | I4: ='Asian Paints Data'!I2 -> 43891 | J4: ='Asian Paints Data'!J2 -> 44256 | ... N4: ='Asian Paints Data'!N2 -> 45717
B6: Current Assets
B7: Inventories | C7: ='Asian Paints Data'!C37 -> 2070 | D7: ='Asian Paints Data'!D37 -> 2259 | E7: ='Asian Paints Data'!E37 -> 1998 | F7: ='Asian Paints Data'!F37 -> 2627 | G7: ='Asian Paints Data'!G37 -> 2658 | H7: ='Asian Paints Data'!H37 -> 3150 | I7: ='Asian Paints Data'!I37 -> 3390 | J7: ='Asian Paints Data'!J37 -> 3799 | ... N7: ='Asian Paints Data'!N37 -> 6719
B8: Trade Receivables | C8: ='Asian Paints Data'!C38 -> 1110 | D8: ='Asian Paints Data'!D38 -> 1182 | E8: ='Asian Paints Data'!E38 -> 1187 | F8: ='Asian Paints Data'!F38 -> 1447 | G8: ='Asian Paints Data'!G38 -> 1731 | H8: ='Asian Paints Data'!H38 -> 1907 | I8: ='Asian Paints Data'!I38 -> 1795 | J8: ='Asian Paints Data'!J38 -> 2602 | ... N8: ='Asian Paints Data'!N38 -> 4314
B9: Loans and Advances | C9: ='Asian Paints Data'!C43 -> 7 | D9: ='Asian Paints Data'!D43 -> 8 | E9: ='Asian Paints Data'!E43 -> 9 | F9: ='Asian Paints Data'!F43 -> 14 | G9: ='Asian Paints Data'!G43 -> 13 | H9: ='Asian Paints Data'!H43 -> 16 | I9: ='Asian Paints Data'!I43 -> 12 | J9: ='Asian Paints Data'!J43 -> 11 | ... N9: ='Asian Paints Data'!N43 -> 22
B10: Other Asset Items | C10: ='Asian Paints Data'!C44 -> 603 | D10: ='Asian Paints Data'!D44 -> 817 | E10: ='Asian Paints Data'!E44 -> 705 | F10: ='Asian Paints Data'!F44 -> 1303 | G10: ='Asian Paints Data'!G44 -> 1678 | H10: ='Asian Paints Data'!H44 -> 1456 | I10: ='Asian Paints Data'!I44 -> 1727 | J10: ='Asian Paints Data'!J44 -> 2555 | ... N10: ='Asian Paints Data'!N44 -> 3319
B11: Total Current Assets | C11: =SUM(C7:C10) -> 3790 | D11: =SUM(D7:D10) -> 4266 | E11: =SUM(E7:E10) -> 3899 | F11: =SUM(F7:F10) -> 5391 | G11: =SUM(G7:G10) -> 6080 | H11: =SUM(H7:H10) -> 6529 | I11: =SUM(I7:I10) -> 6924 | J11: =SUM(J7:J10) -> 8967 | ... N11: =SUM(N7:N10) -> 14374
B13: Current Liabilites
B14: ='Asian Paints Data'!B13 -> Trade Payables | C14: ='Asian Paints Data'!C13 -> 1746 | D14: ='Asian Paints Data'!D13 -> 1549 | E14: ='Asian Paints Data'!E13 -> 1565 | F14: ='Asian Paints Data'!F13 -> 1923 | G14: ='Asian Paints Data'!G13 -> 2160 | H14: ='Asian Paints Data'!H13 -> 2394 | I14: ='Asian Paints Data'!I13 -> 2137 | ... N14: ='Asian Paints Data'!N13 -> 3848
B15: ='Asian Paints Data'!B14 -> Advance from Customers | C15: ='Asian Paints Data'!C14 -> 0 | D15: ='Asian Paints Data'!D14 -> 5 | E15: ='Asian Paints Data'!E14 -> 12 | F15: ='Asian Paints Data'!F14 -> 17 | G15: ='Asian Paints Data'!G14 -> 16 | H15: ='Asian Paints Data'!H14 -> 13 | I15: ='Asian Paints Data'!I14 -> 29 | ... N15: ='Asian Paints Data'!N14 -> 173
B16: ='Asian Paints Data'!B15 -> Other liability items | C16: ='Asian Paints Data'!C15 -> 1795 | D16: ='Asian Paints Data'!D15 -> 1937 | E16: ='Asian Paints Data'!E15 -> 1750 | F16: ='Asian Paints Data'!F15 -> 1925 | G16: ='Asian Paints Data'!G15 -> 2316 | H16: ='Asian Paints Data'!H15 -> 2690 | I16: ='Asian Paints Data'!I15 -> 2320 | ... N16: ='Asian Paints Data'!N15 -> 3985
B17: Total Current Liabilites | C17: =SUM(C14:C16) -> 3541 | D17: =SUM(D14:D16) -> 3491 | E17: =SUM(E14:E16) -> 3327 | F17: =SUM(F14:F16) -> 3865 | G17: =SUM(G14:G16) -> 4492 | H17: =SUM(H14:H16) -> 5097 | I17: =SUM(I14:I16) -> 4486 | J17: =SUM(J14:J16) -> 6033 | ... N17: =SUM(N14:N16) -> 8006
B19: Net Working Capital | C19: =C11-C17 -> 249 | D19: =D11-D17 -> 775 | E19: =E11-E17 -> 572 | F19: =F11-F17 -> 1526 | G19: =G11-G17 -> 1588 | H19: =H11-H17 -> 1432 | I19: =I11-I17 -> 2438 | J19: =J11-J17 -> 2934 | ... N19: =N11-N17 -> 6368
B21: Fixed Assets
B22: ='Asian Paints Data'!B20 -> Land | C22: ='Asian Paints Data'!C20 -> 247 | D22: ='Asian Paints Data'!D20 -> 251 | E22: ='Asian Paints Data'!E20 -> 429 | F22: ='Asian Paints Data'!F20 -> 408 | G22: ='Asian Paints Data'!G20 -> 586 | H22: ='Asian Paints Data'!H20 -> 605 | I22: ='Asian Paints Data'!I20 -> 640 | ... N22: ='Asian Paints Data'!N20 -> 1050
B23: ='Asian Paints Data'!B21 -> Building | C23: ='Asian Paints Data'!C21 -> 931 | D23: ='Asian Paints Data'!D21 -> 962 | E23: ='Asian Paints Data'!E21 -> 923 | F23: ='Asian Paints Data'!F21 -> 931 | G23: ='Asian Paints Data'!G21 -> 957 | H23: ='Asian Paints Data'!H21 -> 2402 | I23: ='Asian Paints Data'!I21 -> 2257 | ... N23: ='Asian Paints Data'!N21 -> 4136
B24: ='Asian Paints Data'!B22 -> Plant Machinery | C24: ='Asian Paints Data'!C22 -> 2054 | D24: ='Asian Paints Data'!D22 -> 2132 | E24: ='Asian Paints Data'!E22 -> 1793 | F24: ='Asian Paints Data'!F22 -> 1980 | G24: ='Asian Paints Data'!G22 -> 2157 | H24: ='Asian Paints Data'!H22 -> 4006 | I24: ='Asian Paints Data'!I22 -> 4208 | ... N24: ='Asian Paints Data'!N22 -> 7576
B25: ='Asian Paints Data'!B23 -> Equipments | C25: ='Asian Paints Data'!C23 -> 155 | D25: ='Asian Paints Data'!D23 -> 171 | E25: ='Asian Paints Data'!E23 -> 97 | F25: ='Asian Paints Data'!F23 -> 119 | G25: ='Asian Paints Data'!G23 -> 200 | H25: ='Asian Paints Data'!H23 -> 221 | I25: ='Asian Paints Data'!I23 -> 241 | ... N25: ='Asian Paints Data'!N23 -> 325
B26: ='Asian Paints Data'!B24 -> Furniture n fittings | C26: ='Asian Paints Data'!C24 -> 71 | D26: ='Asian Paints Data'!D24 -> 83 | E26: ='Asian Paints Data'!E24 -> 49 | F26: ='Asian Paints Data'!F24 -> 59 | G26: ='Asian Paints Data'!G24 -> 72 | H26: ='Asian Paints Data'!H24 -> 88 | I26: ='Asian Paints Data'!I24 -> 94 | ... N26: ='Asian Paints Data'!N24 -> 203
B27: ='Asian Paints Data'!B25 -> Vehicles | C27: ='Asian Paints Data'!C25 -> 14 | D27: ='Asian Paints Data'!D25 -> 18 | E27: ='Asian Paints Data'!E25 -> 11 | F27: ='Asian Paints Data'!F25 -> 14 | G27: ='Asian Paints Data'!G25 -> 27 | H27: ='Asian Paints Data'!H25 -> 47 | I27: ='Asian Paints Data'!I25 -> 43 | ... N27: ='Asian Paints Data'!N25 -> 39
B28: ='Asian Paints Data'!B26 -> Intangible Assets | C28: ='Asian Paints Data'!C26 -> 203 | D28: ='Asian Paints Data'!D26 -> 351 | E28: ='Asian Paints Data'!E26 -> 339 | F28: ='Asian Paints Data'!F26 -> 276 | G28: ='Asian Paints Data'!G26 -> 468 | H28: ='Asian Paints Data'!H26 -> 512 | I28: ='Asian Paints Data'!I26 -> 505 | ... N28: ='Asian Paints Data'!N26 -> 827
B29: ='Asian Paints Data'!B27 -> Other fixed assets | C29: ='Asian Paints Data'!C27 -> 128 | D29: ='Asian Paints Data'!D27 -> 145 | E29: ='Asian Paints Data'!E27 -> 103 | F29: ='Asian Paints Data'!F27 -> 128 | G29: ='Asian Paints Data'!G27 -> 238 | H29: ='Asian Paints Data'!H27 -> 261 | I29: ='Asian Paints Data'!I27 -> 293 | ... N29: ='Asian Paints Data'!N27 -> 328
B30: ='Asian Paints Data'!B28 -> Gross Block | C30: ='Asian Paints Data'!C28 -> 3804 | D30: ='Asian Paints Data'!D28 -> 4112 | E30: ='Asian Paints Data'!E28 -> 3744 | F30: ='Asian Paints Data'!F28 -> 3914 | G30: ='Asian Paints Data'!G28 -> 4705 | H30: ='Asian Paints Data'!H28 -> 8141 | I30: ='Asian Paints Data'!I28 -> 8282 | ... N30: ='Asian Paints Data'!N28 -> 14484
B31: ='Asian Paints Data'!B29 -> Accumulated Depreciation | C31: ='Asian Paints Data'!C29 -> -1242 | D31: ='Asian Paints Data'!D29 -> -1242 | E31: ='Asian Paints Data'!E29 -> -1242 | F31: ='Asian Paints Data'!F29 -> -1242 | G31: ='Asian Paints Data'!G29 -> -1242 | H31: ='Asian Paints Data'!H29 -> -1242 | I31: ='Asian Paints Data'!I29 -> -1242 | ... N31: ='Asian Paints Data'!N29 -> -1242
B32: ='Asian Paints Data'!B30 -> Net Block | C32: ='Asian Paints Data'!C30 -> 2562 | D32: ='Asian Paints Data'!D30 -> 2870 | E32: ='Asian Paints Data'!E30 -> 2502 | F32: ='Asian Paints Data'!F30 -> 2672 | G32: ='Asian Paints Data'!G30 -> 3463 | H32: ='Asian Paints Data'!H30 -> 6899 | I32: ='Asian Paints Data'!I30 -> 7040 | ... N32: ='Asian Paints Data'!N30 -> 13242
B34: Invested Capital | C34: =C32+C19 -> 2811 | D34: =D32+D19 -> 3645 | E34: =E32+E19 -> 3074 | F34: =F32+F19 -> 4198 | G34: =G32+G19 -> 5051 | H34: =H32+H19 -> 8331 | I34: =I32+I19 -> 9478 | J34: =J32+J19 -> 10084 | ... N34: =N32+N19 -> 19610
B35: EBIT | C35: ='Asian Paints Data'!C117 -> 1758 | D35: ='Asian Paints Data'!D117 -> 1977 | E35: ='Asian Paints Data'!E117 -> 2449 | F35: ='Asian Paints Data'!F117 -> 2659 | G35: ='Asian Paints Data'!G117 -> 2844 | H35: ='Asian Paints Data'!H117 -> 3143 | I35: ='Asian Paints Data'!I117 -> 3377 | J35: ='Asian Paints Data'!J117 -> 4065 | ... N35: ='Asian Paints Data'!N117 -> 4980
B37: ROIC (Return on Investment Capital) | C37: =C35/C34 -> 0.62540021 | D37: =D35/D34 -> 0.54238683 | E37: =E35/E34 -> 0.79668185 | F37: =F35/F34 -> 0.63339686 | G37: =G35/G34 -> 0.56305682 | H37: =H35/H34 -> 0.37726563 | I37: =I35/I34 -> 0.3562988 | J37: =J35/J34 -> 0.40311384 | ... N37: =N35/N34 -> 0.25395207
B39: Calculation of Reinvestment Rate
B41: Net Capex | C41: =-SUM('Asian Paints Data'!C79:C80) -> 235 | D41: =-SUM('Asian Paints Data'!D79:D80) -> 438 | E41: =-SUM('Asian Paints Data'!E79:E80) -> 802 | F41: =-SUM('Asian Paints Data'!F79:F80) -> 667 | G41: =-SUM('Asian Paints Data'!G79:G80) -> 1409 | H41: =-SUM('Asian Paints Data'!H79:H80) -> 1134 | I41: =-SUM('Asian Paints Data'!I79:I80) -> 367 | J41: =-SUM('Asian Paints Data'!J79:J80) -> 254 | ... N41: =-SUM('Asian Paints Data'!N79:N80) -> 1820
B42: Change in Working Capital | D42: =D19-C19 -> 526 | E42: =E19-D19 -> -203 | F42: =F19-E19 -> 954 | G42: =G19-F19 -> 62 | H42: =H19-G19 -> -156 | I42: =I19-H19 -> 1006 | J42: =J19-I19 -> 496 | K42: =K19-J19 -> 2795 | ... N42: =N19-M19 -> -14
B44: EBIT | C44: =C35 -> 1758 | D44: =D35 -> 1977 | E44: =E35 -> 2449 | F44: =F35 -> 2659 | G44: =G35 -> 2844 | H44: =H35 -> 3143 | I44: =I35 -> 3377 | J44: =J35 -> 4065 | ... N44: =N35 -> 4980
B45: Mariginal Tax Rate | C45: =25% -> 0.25 | D45: =25% -> 0.25 | E45: =25% -> 0.25 | F45: =25% -> 0.25 | G45: =25% -> 0.25 | H45: =25% -> 0.25 | I45: =25% -> 0.25 | J45: =25% -> 0.25 | ... N45: =25% -> 0.25
B46: EBIT(1-T) | C46: =C44*(1-C45) -> 1318.5 | D46: =D44*(1-D45) -> 1482.75 | E46: =E44*(1-E45) -> 1836.75 | F46: =F44*(1-F45) -> 1994.25 | G46: =G44*(1-G45) -> 2133 | H46: =H44*(1-H45) -> 2357.25 | I46: =I44*(1-I45) -> 2532.75 | J46: =J44*(1-J45) -> 3048.75 | ... N46: =N44*(1-N45) -> 3735
B48: Reinvestment | D48: =D41+D42 -> 964 | E48: =E41+E42 -> 599 | F48: =F41+F42 -> 1621 | G48: =G41+G42 -> 1471 | H48: =H41+H42 -> 978 | I48: =I41+I42 -> 1373 | J48: =J41+J42 -> 750 | K48: =K41+K42 -> 3306 | ... N48: =N41+N42 -> 1806
B49: Reinvestment Rate | D49: =D48/D46 -> 0.65014331 | E49: =E48/E46 -> 0.3261195 | F49: =F48/F46 -> 0.81283691 | G49: =G48/G46 -> 0.68963901 | H49: =H48/H46 -> 0.41489023 | I49: =I48/I46 -> 0.54209851 | J49: =J48/J46 -> 0.24600246 | K49: =K48/K46 -> 1.1053159 | ... N49: =N48/N46 -> 0.48353414
M51: 4 Year Avg | N51: =AVERAGE(K49:N49) -> 0.64971282
M52: 4 Year Median | N52: =MEDIAN(K49:N49) -> 0.51018617
B55: Calculation of Growth Rate
B57: ReinveStment Rate | D57: =D49 -> 0.65014331 | E57: =E49 -> 0.3261195 | F57: =F49 -> 0.81283691 | G57: =G49 -> 0.68963901 | H57: =H49 -> 0.41489023 | I57: =I49 -> 0.54209851 | J57: =J49 -> 0.24600246 | K57: =K49 -> 1.1053159 | ... N57: =N49 -> 0.48353414
B58: ROIC | D58: =D37 -> 0.54238683 | E58: =E37 -> 0.79668185 | F58: =F37 -> 0.63339686 | G58: =G37 -> 0.56305682 | H58: =H37 -> 0.37726563 | I58: =I37 -> 0.3562988 | J58: =J37 -> 0.40311384 | K58: =K37 -> 0.30618042 | ... N58: =N37 -> 0.25395207
B60: Intrinsic Growth | D60: =D57*D58 -> 0.35262917 | E60: =E57*E58 -> 0.25981349 | F60: =F57*F58 -> 0.51484834 | G60: =G57*G58 -> 0.38830595 | H60: =H57*H58 -> 0.15652383 | I60: =I57*I58 -> 0.19314905 | J60: =J57*J58 -> 0.099166997 | K60: =K57*K58 -> 0.3384261 | ... N60: =N57*N58 -> 0.12279449
M63: 4 Year Avg | N63: =AVERAGE(H60:K60) -> 0.19681649
M64: 4 Year Median | N64: =MEDIAN(H60:K60) -> 0.17483644

Sheet Common Size Statement
B2: ="Common Size Statment - "&UPDATE -> Common Size Statment - Tata Motors
B3: Particulars (P & L) | C3: ='Data Sheet'!B16 -> 42460 | D3: ='Data Sheet'!C16 -> 42825 | E3: ='Data Sheet'!D16 -> 43190 | F3: ='Data Sheet'!E16 -> 43555 | G3: ='Data Sheet'!F16 -> 43921 | H3: ='Data Sheet'!G16 -> 44286 | I3: ='Data Sheet'!H16 -> 44651 | J3: ='Data Sheet'!I16 -> 45016 | ... L3: ='Data Sheet'!K16 -> 45747
B5: ='Data Sheet'!A17 -> Sales | C5: ='Data Sheet'!B17/'Data Sheet'!B$17 -> 1 | D5: ='Data Sheet'!C17/'Data Sheet'!C$17 -> 1 | E5: ='Data Sheet'!D17/'Data Sheet'!D$17 -> 1 | F5: ='Data Sheet'!E17/'Data Sheet'!E$17 -> 1 | G5: ='Data Sheet'!F17/'Data Sheet'!F$17 -> 1 | H5: ='Data Sheet'!G17/'Data Sheet'!G$17 -> 1 | I5: ='Data Sheet'!H17/'Data Sheet'!H$17 -> 1 | J5: ='Data Sheet'!I17/'Data Sheet'!I$17 -> 1 | ... L5: ='Data Sheet'!K17/'Data Sheet'!K$17 -> 1
B6: ='Data Sheet'!A18 -> Raw Material Cost | C6: ='Data Sheet'!B18/'Data Sheet'!B$17 -> 0.60844786 | D6: ='Data Sheet'!C18/'Data Sheet'!C$17 -> 0.64256171 | E6: ='Data Sheet'!D18/'Data Sheet'!D$17 -> 0.64447357 | F6: ='Data Sheet'!E18/'Data Sheet'!E$17 -> 0.64340246 | G6: ='Data Sheet'!F18/'Data Sheet'!F$17 -> 0.63163559 | H6: ='Data Sheet'!G18/'Data Sheet'!G$17 -> 0.6149343 | I6: ='Data Sheet'!H18/'Data Sheet'!H$17 -> 0.64389657 | J6: ='Data Sheet'!I18/'Data Sheet'!I$17 -> 0.66842005 | ... L6: ='Data Sheet'!K18/'Data Sheet'!K$17 -> 0.611674
B7: ='Data Sheet'!A19 -> Change in Inventory | C7: ='Data Sheet'!B19/'Data Sheet'!B$17 -> 0.010075204 | D7: ='Data Sheet'!C19/'Data Sheet'!C$17 -> 0.027438359 | E7: ='Data Sheet'!D19/'Data Sheet'!D$17 -> 0.007019642 | F7: ='Data Sheet'!E19/'Data Sheet'!E$17 -> -0.0068003275 | G7: ='Data Sheet'!F19/'Data Sheet'!F$17 -> -0.008546395 | H7: ='Data Sheet'!G19/'Data Sheet'!G$17 -> -0.018752035 | I7: ='Data Sheet'!H19/'Data Sheet'!H$17 -> -0.0057118668 | J7: ='Data Sheet'!I19/'Data Sheet'!I$17 -> 0.01382103 | ... L7: ='Data Sheet'!K19/'Data Sheet'!K$17 -> -0.0064499255
B8: ='Data Sheet'!A20 -> Power and Fuel | C8: ='Data Sheet'!B20/'Data Sheet'!B$17 -> 0.0041884213 | D8: ='Data Sheet'!C20/'Data Sheet'!C$17 -> 0.0043005273 | E8: ='Data Sheet'!D20/'Data Sheet'!D$17 -> 0.004486633 | F8: ='Data Sheet'!E20/'Data Sheet'!E$17 -> 0.0052524952 | G8: ='Data Sheet'!F20/'Data Sheet'!F$17 -> 0.0048452899 | H8: ='Data Sheet'!G20/'Data Sheet'!G$17 -> 0.0044551377 | I8: ='Data Sheet'!H20/'Data Sheet'!H$17 -> 0.0078228109 | J8: ='Data Sheet'!I20/'Data Sheet'!I$17 -> 0.007264653 | ... L8: ='Data Sheet'!K20/'Data Sheet'!K$17 -> 0.0055561241
B9: ='Data Sheet'!A21 -> Other Mfr. Exp | C9: ='Data Sheet'!B21/'Data Sheet'!B$17 -> 0.044320546 | D9: ='Data Sheet'!C21/'Data Sheet'!C$17 -> 0.037329068 | E9: ='Data Sheet'!D21/'Data Sheet'!D$17 -> 0.037632111 | F9: ='Data Sheet'!E21/'Data Sheet'!E$17 -> 0.038731543 | G9: ='Data Sheet'!F21/'Data Sheet'!F$17 -> 0.044208832 | H9: ='Data Sheet'!G21/'Data Sheet'!G$17 -> 0.033119871 | I9: ='Data Sheet'!H21/'Data Sheet'!H$17 -> 0.033856195 | J9: ='Data Sheet'!I21/'Data Sheet'!I$17 -> 0.03400894 | ... L9: ='Data Sheet'!K21/'Data Sheet'!K$17 -> 0.042786477
B10: ='Data Sheet'!A22 -> Employee Cost | C10: ='Data Sheet'!B22/'Data Sheet'!B$17 -> 0.10577314 | D10: ='Data Sheet'!C22/'Data Sheet'!C$17 -> 0.10505627 | E10: ='Data Sheet'!D22/'Data Sheet'!D$17 -> 0.10392742 | F10: ='Data Sheet'!E22/'Data Sheet'!E$17 -> 0.1101015 | G10: ='Data Sheet'!F22/'Data Sheet'!F$17 -> 0.11659263 | H10: ='Data Sheet'!G22/'Data Sheet'!G$17 -> 0.11068479 | I10: ='Data Sheet'!H22/'Data Sheet'!H$17 -> 0.11064148 | J10: ='Data Sheet'!I22/'Data Sheet'!I$17 -> 0.097277205 | ... L10: ='Data Sheet'!K22/'Data Sheet'!K$17 -> 0.10863667
B11: ='Data Sheet'!A23 -> Selling and admin | C11: ='Data Sheet'!B23/'Data Sheet'!B$17 -> 0.080542957 | D11: ='Data Sheet'!C23/'Data Sheet'!C$17 -> 0.11138381 | E11: ='Data Sheet'!D23/'Data Sheet'!D$17 -> 0.10634378 | F11: ='Data Sheet'!E23/'Data Sheet'!E$17 -> 0.10836581 | G11: ='Data Sheet'!F23/'Data Sheet'!F$17 -> 0.11203335 | H11: ='Data Sheet'!G23/'Data Sheet'!G$17 -> 0.092138806 | I11: ='Data Sheet'!H23/'Data Sheet'!H$17 -> 0.10488425 | J11: ='Data Sheet'!I23/'Data Sheet'!I$17 -> 0.10070091 | ... L11: ='Data Sheet'!K23/'Data Sheet'!K$17 -> 0.10711743
B12: ='Data Sheet'!A24 -> Other Expenses | C12: ='Data Sheet'!B24/'Data Sheet'!B$17 -> 0.026183832 | D12: ='Data Sheet'!C24/'Data Sheet'!C$17 -> 0.017094283 | E12: ='Data Sheet'!D24/'Data Sheet'!D$17 -> 0.0022582367 | F12: ='Data Sheet'!E24/'Data Sheet'!E$17 -> 0.0056592338 | G12: ='Data Sheet'!F24/'Data Sheet'!F$17 -> 0.013239885 | H12: ='Data Sheet'!G24/'Data Sheet'!G$17 -> -0.0033407828 | I12: ='Data Sheet'!H24/'Data Sheet'!H$17 -> 0.0044105011 | J12: ='Data Sheet'!I24/'Data Sheet'!I$17 -> 0.014187308 | ... L12: ='Data Sheet'!K24/'Data Sheet'!K$17 -> -0.0077985877
B13: ='Data Sheet'!A26 -> Depreciation | C13: ='Data Sheet'!B26/'Data Sheet'!B$17 -> 0.061201426 | D13: ='Data Sheet'!C26/'Data Sheet'!C$17 -> 0.066390387 | E13: ='Data Sheet'!D26/'Data Sheet'!D$17 -> 0.073927472 | F13: ='Data Sheet'!E26/'Data Sheet'!E$17 -> 0.078130605 | G13: ='Data Sheet'!F26/'Data Sheet'!F$17 -> 0.082068398 | H13: ='Data Sheet'!G26/'Data Sheet'!G$17 -> 0.094264231 | I13: ='Data Sheet'!H26/'Data Sheet'!H$17 -> 0.089191478 | J13: ='Data Sheet'!I26/'Data Sheet'!I$17 -> 0.071857611 | ... L13: ='Data Sheet'!K26/'Data Sheet'!K$17 -> 0.052891209
B14: ='Data Sheet'!A27 -> Interest | C14: ='Data Sheet'!B27/'Data Sheet'!B$17 -> 0.017905727 | D14: ='Data Sheet'!C27/'Data Sheet'!C$17 -> 0.01571423 | E14: ='Data Sheet'!D27/'Data Sheet'!D$17 -> 0.016058248 | F14: ='Data Sheet'!E27/'Data Sheet'!E$17 -> 0.019072102 | G14: ='Data Sheet'!F27/'Data Sheet'!F$17 -> 0.027744997 | H14: ='Data Sheet'!G27/'Data Sheet'!G$17 -> 0.032415293 | I14: ='Data Sheet'!H27/'Data Sheet'!H$17 -> 0.033441332 | J14: ='Data Sheet'!I27/'Data Sheet'!I$17 -> 0.029556232 | ... L14: ='Data Sheet'!K27/'Data Sheet'!K$17 -> 0.011560286
B15: ='Data Sheet'!A28 -> Profit before tax | C15: ='Data Sheet'!B28/'Data Sheet'!B$17 -> 0.051734106 | D15: ='Data Sheet'!C28/'Data Sheet'!C$17 -> 0.034538557 | E15: ='Data Sheet'!D28/'Data Sheet'!D$17 -> 0.038261059 | F15: ='Data Sheet'!E28/'Data Sheet'!E$17 -> -0.10389917 | G15: ='Data Sheet'!F28/'Data Sheet'!F$17 -> -0.040525768 | H15: ='Data Sheet'!G28/'Data Sheet'!G$17 -> -0.041931546 | I15: ='Data Sheet'!H28/'Data Sheet'!H$17 -> -0.025151083 | J15: ='Data Sheet'!I28/'Data Sheet'!I$17 -> 0.0098099827 | ... L15: ='Data Sheet'!K28/'Data Sheet'!K$17 -> 0.087904115
B16: ='Data Sheet'!A29 -> Tax | C16: ='Data Sheet'!B29/'Data Sheet'!B$17 -> 0.011078919 | D16: ='Data Sheet'!C29/'Data Sheet'!C$17 -> 0.012055322 | E16: ='Data Sheet'!D29/'Data Sheet'!D$17 -> 0.01489255 | F16: ='Data Sheet'!E29/'Data Sheet'!E$17 -> -0.0080726731 | G16: ='Data Sheet'!F29/'Data Sheet'!F$17 -> 0.0015139735 | H16: ='Data Sheet'!G29/'Data Sheet'!G$17 -> 0.010175794 | I16: ='Data Sheet'!H29/'Data Sheet'!H$17 -> 0.015195672 | J16: ='Data Sheet'!I29/'Data Sheet'!I$17 -> 0.0020350498 | ... L16: ='Data Sheet'!K29/'Data Sheet'!K$17 -> 0.023884738
B17: ='Data Sheet'!A30 -> Net profit | C17: ='Data Sheet'!B30/'Data Sheet'!B$17 -> 0.042407971 | D17: ='Data Sheet'!C30/'Data Sheet'!C$17 -> 0.027640219 | E17: ='Data Sheet'!D30/'Data Sheet'!D$17 -> 0.030831402 | F17: ='Data Sheet'!E30/'Data Sheet'!E$17 -> -0.095470566 | G17: ='Data Sheet'!F30/'Data Sheet'!F$17 -> -0.046236426 | H17: ='Data Sheet'!G30/'Data Sheet'!G$17 -> -0.053849771 | I17: ='Data Sheet'!H30/'Data Sheet'!H$17 -> -0.04108932 | J17: ='Data Sheet'!I30/'Data Sheet'!I$17 -> 0.0069783829 | ... L17: ='Data Sheet'!K30/'Data Sheet'!K$17 -> 0.063293874
B18: ='Data Sheet'!A31 -> Dividend Amount | C18: ='Data Sheet'!B31/'Data Sheet'!B$17 -> 0.00024874966 | D18: ='Data Sheet'!C31/'Data Sheet'!C$17 -> 0 | E18: ='Data Sheet'!D31/'Data Sheet'!D$17 -> 0 | F18: ='Data Sheet'!E31/'Data Sheet'!E$17 -> 0 | G18: ='Data Sheet'!F31/'Data Sheet'!F$17 -> 0 | H18: ='Data Sheet'!G31/'Data Sheet'!G$17 -> 0 | I18: ='Data Sheet'!H31/'Data Sheet'!H$17 -> 0 | J18: ='Data Sheet'!I31/'Data Sheet'!I$17 -> 0.002214142 | ... L18: ='Data Sheet'!K31/'Data Sheet'!K$17 -> 0.0050216627
B22: ="Common Size Statment - "&UPDATE -> Common Size Statment - Tata Motors
B23: Particulars (Balance Sheet) | C23: ='Data Sheet'!B56 -> 42460 | D23: ='Data Sheet'!C56 -> 42825 | E23: ='Data Sheet'!D56 -> 43190 | F23: ='Data Sheet'!E56 -> 43555 | G23: ='Data Sheet'!F56 -> 43921 | H23: ='Data Sheet'!G56 -> 44286 | I23: ='Data Sheet'!H56 -> 44651 | J23: ='Data Sheet'!I56 -> 45016 | ... L23: ='Data Sheet'!K56 -> 45747
B25: Total Liabilites | C25: ='Data Sheet'!B61/'Data Sheet'!B$61 -> 1 | D25: ='Data Sheet'!C61/'Data Sheet'!C$61 -> 1 | E25: ='Data Sheet'!D61/'Data Sheet'!D$61 -> 1 | F25: ='Data Sheet'!E61/'Data Sheet'!E$61 -> 1 | G25: ='Data Sheet'!F61/'Data Sheet'!F$61 -> 1 | H25: ='Data Sheet'!G61/'Data Sheet'!G$61 -> 1 | I25: ='Data Sheet'!H61/'Data Sheet'!H$61 -> 1 | J25: ='Data Sheet'!I61/'Data Sheet'!I$61 -> 1 | ... L25: ='Data Sheet'!K61/'Data Sheet'!K$61 -> 1
B26: ='Data Sheet'!A57 -> Equity Share Capital | C26: ='Data Sheet'!B57/'Data Sheet'!B$61 -> 0.0025806268 | D26: ='Data Sheet'!C57/'Data Sheet'!C$61 -> 0.0024918156 | E26: ='Data Sheet'!D57/'Data Sheet'!D$61 -> 0.0020759077 | F26: ='Data Sheet'!E57/'Data Sheet'!E$61 -> 0.0022218261 | G26: ='Data Sheet'!F57/'Data Sheet'!F$61 -> 0.0022473027 | H26: ='Data Sheet'!G57/'Data Sheet'!G$61 -> 0.00224203 | I26: ='Data Sheet'!H57/'Data Sheet'!H$61 -> 0.0023274677 | J26: ='Data Sheet'!I57/'Data Sheet'!I$61 -> 0.0022888513 | ... L26: ='Data Sheet'!K57/'Data Sheet'!K$61 -> 0.0019523945
B27: ='Data Sheet'!A58 -> Reserves | C27: ='Data Sheet'!B58/'Data Sheet'!B$61 -> 0.29740864 | D27: ='Data Sheet'!C58/'Data Sheet'!C$61 -> 0.21051652 | E27: ='Data Sheet'!D58/'Data Sheet'!D$61 -> 0.28958148 | F27: ='Data Sheet'!E58/'Data Sheet'!E$61 -> 0.19463415 | G27: ='Data Sheet'!F58/'Data Sheet'!F$61 -> 0.19476266 | H27: ='Data Sheet'!G58/'Data Sheet'!G$61 -> 0.15950149 | I27: ='Data Sheet'!H58/'Data Sheet'!H$61 -> 0.13309172 | J27: ='Data Sheet'!I58/'Data Sheet'!I$61 -> 0.13313168 | ... L27: ='Data Sheet'!K58/'Data Sheet'!K$61 -> 0.30614394
B28: ='Data Sheet'!A59 -> Borrowings | C28: ='Data Sheet'!B59/'Data Sheet'!B$61 -> 0.26354158 | D28: ='Data Sheet'!C59/'Data Sheet'!C$61 -> 0.28836993 | E28: ='Data Sheet'!D59/'Data Sheet'!D$61 -> 0.27186032 | F28: ='Data Sheet'!E59/'Data Sheet'!E$61 -> 0.34731478 | G28: ='Data Sheet'!F59/'Data Sheet'!F$61 -> 0.38974289 | H28: ='Data Sheet'!G59/'Data Sheet'!G$61 -> 0.41610975 | I28: ='Data Sheet'!H59/'Data Sheet'!H$61 -> 0.44505065 | J28: ='Data Sheet'!I59/'Data Sheet'!I$61 -> 0.40072807 | ... L28: ='Data Sheet'!K59/'Data Sheet'!K$61 -> 0.18977486
B29: ='Data Sheet'!A60 -> Other Liabilities | C29: ='Data Sheet'!B60/'Data Sheet'!B$61 -> 0.43646915 | D29: ='Data Sheet'!C60/'Data Sheet'!C$61 -> 0.49862173 | E29: ='Data Sheet'!D60/'Data Sheet'!D$61 -> 0.43648229 | F29: ='Data Sheet'!E60/'Data Sheet'!E$61 -> 0.45582924 | G29: ='Data Sheet'!F60/'Data Sheet'!F$61 -> 0.41324715 | H29: ='Data Sheet'!G60/'Data Sheet'!G$61 -> 0.42214673 | I29: ='Data Sheet'!H60/'Data Sheet'!H$61 -> 0.41953016 | J29: ='Data Sheet'!I60/'Data Sheet'!I$61 -> 0.46385139 | ... L29: ='Data Sheet'!K60/'Data Sheet'!K$61 -> 0.5021288
B31: Total Assests | C31: ='Data Sheet'!B76/'Data Sheet'!B$76 -> 1 | D31: ='Data Sheet'!C76/'Data Sheet'!C$76 -> 1 | E31: ='Data Sheet'!D76/'Data Sheet'!D$76 -> 1 | F31: ='Data Sheet'!E76/'Data Sheet'!E$76 -> 1 | G31: ='Data Sheet'!F76/'Data Sheet'!F$76 -> 1 | H31: ='Data Sheet'!G76/'Data Sheet'!G$76 -> 1 | I31: ='Data Sheet'!H76/'Data Sheet'!H$76 -> 1 | J31: ='Data Sheet'!I76/'Data Sheet'!I$76 -> 1 | ... L31: ='Data Sheet'!K76/'Data Sheet'!K$76 -> 1
B32: ='Data Sheet'!A62 -> Net Block | C32: ='Data Sheet'!B62/'Data Sheet'!B$76 -> 0.40744008 | D32: ='Data Sheet'!C62/'Data Sheet'!C$76 -> 0.35198457 | E32: ='Data Sheet'!D62/'Data Sheet'!D$76 -> 0.37107854 | F32: ='Data Sheet'!E62/'Data Sheet'!E$76 -> 0.36386392 | G32: ='Data Sheet'!F62/'Data Sheet'!F$76 -> 0.39698726 | H32: ='Data Sheet'!G62/'Data Sheet'!G$76 -> 0.40608849 | I32: ='Data Sheet'!H62/'Data Sheet'!H$76 -> 0.42197417 | J32: ='Data Sheet'!I62/'Data Sheet'!I$76 -> 0.39465148 | ... L32: ='Data Sheet'!K62/'Data Sheet'!K$76 -> 0.30691057
B33: ='Data Sheet'!A63 -> Capital Work in Progress | C33: ='Data Sheet'!B63/'Data Sheet'!B$76 -> 0.098482158 | D33: ='Data Sheet'!C63/'Data Sheet'!C$76 -> 0.12362901 | E33: ='Data Sheet'!D63/'Data Sheet'!D$76 -> 0.12235484 | F33: ='Data Sheet'!E63/'Data Sheet'!E$76 -> 0.10429662 | G33: ='Data Sheet'!F63/'Data Sheet'!F$76 -> 0.11125729 | H33: ='Data Sheet'!G63/'Data Sheet'!G$76 -> 0.061375225 | I33: ='Data Sheet'!H63/'Data Sheet'!H$76 -> 0.031152506 | J33: ='Data Sheet'!I63/'Data Sheet'!I$76 -> 0.042651899 | ... L33: ='Data Sheet'!K63/'Data Sheet'!K$76 -> 0.17456423
B34: ='Data Sheet'!A64 -> Investments | C34: ='Data Sheet'!B64/'Data Sheet'!B$76 -> 0.090305676 | D34: ='Data Sheet'!C64/'Data Sheet'!C$76 -> 0.074612566 | E34: ='Data Sheet'!D64/'Data Sheet'!D$76 -> 0.063610241 | F34: ='Data Sheet'!E64/'Data Sheet'!E$76 -> 0.051588289 | G34: ='Data Sheet'!F64/'Data Sheet'!F$76 -> 0.050935446 | H34: ='Data Sheet'!G64/'Data Sheet'!G$76 -> 0.072079768 | I34: ='Data Sheet'!H64/'Data Sheet'!H$76 -> 0.089282796 | J34: ='Data Sheet'!I64/'Data Sheet'!I$76 -> 0.078820363 | ... L34: ='Data Sheet'!K64/'Data Sheet'!K$76 -> 0.094585023
B35: ='Data Sheet'!A65 -> Other Assets | C35: ='Data Sheet'!B65/'Data Sheet'!B$76 -> 0.40377208 | D35: ='Data Sheet'!C65/'Data Sheet'!C$76 -> 0.44977386 | E35: ='Data Sheet'!D65/'Data Sheet'!D$76 -> 0.44295638 | F35: ='Data Sheet'!E65/'Data Sheet'!E$76 -> 0.48025117 | G35: ='Data Sheet'!F65/'Data Sheet'!F$76 -> 0.44082 | H35: ='Data Sheet'!G65/'Data Sheet'!G$76 -> 0.46045651 | I35: ='Data Sheet'!H65/'Data Sheet'!H$76 -> 0.45759053 | J35: ='Data Sheet'!I65/'Data Sheet'!I$76 -> 0.48387626 | ... L35: ='Data Sheet'!K65/'Data Sheet'!K$76 -> 0.42394018
B36: ='Data Sheet'!A67 -> Receivables | C36: ='Data Sheet'!B67/'Data Sheet'!B$76 -> 0.051564319 | D36: ='Data Sheet'!C67/'Data Sheet'!C$76 -> 0.051638166 | E36: ='Data Sheet'!D67/'Data Sheet'!D$76 -> 0.060800116 | F36: ='Data Sheet'!E67/'Data Sheet'!E$76 -> 0.062139199 | G36: ='Data Sheet'!F67/'Data Sheet'!F$76 -> 0.034895094 | H36: ='Data Sheet'!G67/'Data Sheet'!G$76 -> 0.037120014 | I36: ='Data Sheet'!H67/'Data Sheet'!H$76 -> 0.037810927 | J36: ='Data Sheet'!I67/'Data Sheet'!I$76 -> 0.047024716 | ... L36: ='Data Sheet'!K67/'Data Sheet'!K$76 -> 0.0351431
B37: ='Data Sheet'!A68 -> Inventory | C37: ='Data Sheet'!B68/'Data Sheet'!B$76 -> 0.12407941 | D37: ='Data Sheet'!C68/'Data Sheet'!C$76 -> 0.12871547 | E37: ='Data Sheet'!D68/'Data Sheet'!D$76 -> 0.12878571 | F37: ='Data Sheet'!E68/'Data Sheet'!E$76 -> 0.12761951 | G37: ='Data Sheet'!F68/'Data Sheet'!F$76 -> 0.11698717 | H37: ='Data Sheet'!G68/'Data Sheet'!G$76 -> 0.10565506 | I37: ='Data Sheet'!H68/'Data Sheet'!H$76 -> 0.10709348 | J37: ='Data Sheet'!I68/'Data Sheet'!I$76 -> 0.12177623 | ... L37: ='Data Sheet'!K68/'Data Sheet'!K$76 -> 0.12539094
B38: ='Data Sheet'!A69 -> Cash & Bank | C38: ='Data Sheet'!B69/'Data Sheet'!B$76 -> 0.11573799 | D38: ='Data Sheet'!C69/'Data Sheet'!C$76 -> 0.13235686 | E38: ='Data Sheet'!D69/'Data Sheet'!D$76 -> 0.10579088 | F38: ='Data Sheet'!E69/'Data Sheet'!E$76 -> 0.10679898 | G38: ='Data Sheet'!F69/'Data Sheet'!F$76 -> 0.10533773 | H38: ='Data Sheet'!G69/'Data Sheet'!G$76 -> 0.13699234 | I38: ='Data Sheet'!H69/'Data Sheet'!H$76 -> 0.12359146 | J38: ='Data Sheet'!I69/'Data Sheet'!I$76 -> 0.1106017 | ... L38: ='Data Sheet'!K69/'Data Sheet'!K$76 -> 0.10832076

Sheet DCF
B3: Calculation of PV of FCFF | D3: ='Intrinsic Growth'!N4 -> 45717 | E3: =D3+366 -> 46083 | F3: =E3+365 -> 46448 | G3: =F3+365 -> 46813 | H3: =G3+365 -> 47178 | I3: =H3+365 -> 47543
B5: EBIT | D5: ='Asian Paints Data'!N117 -> 4980 | E5: =D5*(1+$D$15) -> 6013.35 | F5: =E5*(1+$D$15) -> 7261.1201 | G5: =F5*(1+$D$15) -> 8767.8026 | H5: =G5*(1+$D$15) -> 10587.122 | I5: =H5*(1+$D$15) -> 12783.949
B6: Tax Rate | D6: 0.25 | E6: 0.25 | F6: 0.25 | G6: 0.25 | H6: 0.25 | I6: 0.25
B7: EBIT(1-Tax) | D7: =D5*(1-D6) -> 3735 | E7: =E5*(1-E6) -> 4510.0125 | F7: =F5*(1-F6) -> 5445.8401 | G7: =G5*(1-G6) -> 6575.8519 | H7: =H5*(1-H6) -> 7940.3412 | I7: =I5*(1-I6) -> 9587.962
B8: Less: Reinvestment Rate | D8: ='Intrinsic Growth'!N52 -> 0.51018617 | E8: =D8+(($I$8-$D$8)/4) -> 0.50548963 | F8: =E8+(($I$8-$D$8)/4) -> 0.50079309 | G8: =F8+(($I$8-$D$8)/4) -> 0.49609654 | H8: =G8+(($I$8-$D$8)/4) -> 0.4914 | I8: 0.4914 | J8: Please Check the formula
B9: Free Cash Flow to Firm (FCFF) | D9: =D7*D8 -> 1905.5454 | E9: =E7*E8 -> 2279.7645 | F9: =F7*F8 -> 2727.2391 | G9: =G7*G8 -> 3262.2574 | H9: =H7*H8 -> 3901.8837 | I9: =I7*I8 -> 4711.5245
B10: Mid Year Convention | E10: 0.5 | F10: =E10+1 -> 1.5 | G10: =F10+1 -> 2.5 | H10: =G10+1 -> 3.5 | I10: =H10+1 -> 4.5
B11: Discounting Year | E11: =1/(1+$D$17)^E10 -> 0.90715556 | F11: =1/(1+$D$17)^F10 -> 0.74652662 | G11: =1/(1+$D$17)^G10 -> 0.61434006 | H11: =1/(1+$D$17)^H10 -> 0.50555961 | I11: =1/(1+$D$17)^I10 -> 0.41604078
B13: PV of FCFF | E13: =E9*E11 -> 2068.1011 | F13: =F9*F11 -> 2035.9566 | G13: =G9*G11 -> 2004.1354 | H13: =H9*H11 -> 1972.6348 | I13: =I9*I11 -> 1960.1863
B15: Expected Growth | D15: 0.2075
B16: Terminal Growth | D16: 0.0586
B17: WACC | D17: =WACC!M48 -> 0.2151684
B19: FCFF (n+1) | D19: =I9*(1+D15) -> 5689.1659
B20: WACC | D20: =D17 -> 0.2151684
B21: Terminal Growth | D21: =D16 -> 0.0586
B23: Terminal Value | D23: =D19/(D20-D21) -> 36336.617
B26: Calculation of Equity Value
B28: PV OF FCFF | D28: =SUM(E13:I13) -> 10041.014
B29: PV of Terminal Value | D29: =D23*I11 -> 15117.514
B30: Value of Operating Assets | D30: =SUM(D28:D29) -> 25158.529
B32: Add Cash: | D32: ='Asian Paints Data'!N42 -> 782
B33: Less Debt: | D33: =SUM('Asian Paints Data'!N7:N8) -> 864
B34: Value of Equity | D34: =D30+D32-D33 -> 25076.529
B35: No of Shares | D35: 95.92
B37: Equity Value Per Share | D37: =D34/D35 -> 261.4317
B39: Share Price | D39: =2348 -> 2348
B40: Discount Premium | D40: =D34/D39 -> 10.679953

Sheet Retailing Companies
A3: S No. | B3: Company | C3: CMP | D3: Mrkt Capitalisation | E3: Debt | F3: Debt/Equity
A4: 1 | B4: Eternal Ltd | C4: 328.45 | D4: 316965.77 | E4: 2045 | F4: 0.07
A5: 2 | B5: Avenue Super. | C5: 4418.4 | D5: 287519.9 | E5: 819.62 | F5: 0.04
A6: 3 | B6: Trent | C6: 4815.7 | D6: 171192.1 | E6: 2237.19 | F6: 0.41
A7: 4 | B7: Swiggy | C7: 413.85 | D7: 103199.58 | E7: 1702.95 | F7: 0.17
A8: 5 | B8: Info Edg.(India) | C8: 1333.9 | D8: 86492.82 | E8: 267.34 | F8: 0.01

Sheet Market Return
B2: Year | C2: Annual
B3: 2000 | C3: -0.1465
B4: 2001 | C4: -0.1618 | F4: Average Return | G4: =AVERAGE(C3:C27) -> 0.153348
B5: 2002 | C5: 0.0325 | F5: Dividend Yeild | G5: =(1.38)/100 -> 0.0138
B6: 2003 | C6: 0.719 | F6: Total Market Price | G6: =SUM(G4:G5) -> 0.167148
B7: 2004 | C7: 0.1068
B8: 2005 | C8: 0.3634
B9: 2006 | C9: 0.3983
B10: 2007 | C10: 0.5477
B11: 2008 | C11: -0.5179
B12: 2009 | C12: 0.7576
B13: 2010 | C13: 0.1795
B14: 2011 | C14: -0.2462
B15: 2012 | C15: 0.277
B16: 2013 | C16: 0.0676
B17: 2014 | C17: 0.3139
B18: 2015 | C18: -0.0406
... B27: 2024 | C27: 0.0875

Sheet Cash Flow Data
C2: 41699 | D2: 42064 | E2: 42430 | F2: 42795 | G2: 43160 | H2: 43525 | I2: 43891 | J2: 44256 | K2: 44621 | L2: 44986 | M2: 45352 | N2: 45717
B3: Cash from Operating Activity - | C3: 36151 | D3: 35531 | E3: 37900 | F3: 30199 | G3: 23857 | H3: 18891 | I3: 26633 | J3: 29001 | K3: 14283 | L3: 35388 | M3: 67915 | N3: 63102
B4: Profit from operations | C4: 36303 | D4: 43397 | E4: 38626 | F4: 28840 | G4: 33312 | H4: 28771 | I4: 23352 | J4: 31198 | K4: 26943 | L4: 41694 | M4: 65106 | N4: 58937
B5: Receivables | C5: 445 | D5: -3179 | E5: -2223 | F5: -4152 | G5: -10688 | H5: -9109 | I5: 9950 | J5: -5505 | K5: 185 | L5: -2213 | M5: -1876 | N5: 3573
B6: Inventory | C6: -2853 | D6: -3692 | E6: -5743 | F6: -6621 | G6: -3560 | H6: 2069 | I6: 2326 | J6: 3814 | K6: 472 | L6: -5665 | M6: -7265 | N6: 2127
B7: Payables | C7: 4694 | D7: 3598 | E7: 3947 | F7: 9301 | G7: 7320 | H7: -4692 | I7: -8085 | J7: 5748 | K7: -7012 | L7: 6945 | M7: 13706 | N7: 1303
B8: Loans Advances | C8: 0 | D8: 0 | E8: -520 | F8: 0 | G8: 0 | H8: 0 | I8: 0 | J8: 0 | K8: 0 | L8: 0 | M8: 0 | N8: 0
B9: Other WC items | C9: 1870 | D9: -398 | E9: 5852 | F9: 4727 | G9: 494 | H9: 4512 | I9: 875 | J9: -4150 | K9: -4396 | L9: -2194 | M9: 2760 | N9: 1153
B10: Working capital changes | C10: 4157 | D10: -3672 | E10: 1313 | F10: 3254 | G10: -6434 | H10: -7221 | I10: 5065 | J10: -93 | K10: -10750 | L10: -3127 | M10: 7325 | N10: 8156
B11: Direct taxes | C11: -4308 | D11: -4194 | E11: -2040 | F11: -1895 | G11: -3021 | H11: -2659 | I11: -1785 | J11: -2105 | K11: -1910 | L11: -3179 | M11: -4516 | N11: -3991
B12: Cash from Investing Activity - | C12: -27991 | D12: -36232 | E12: -36694 | F12: -39571 | G12: -25139 | H12: -20878 | I12: -33115 | J12: -25672 | K12: -4444 | L12: -15417 | M12: -22781 | N12: -49982
B13: Fixed assets purchased | C13: -26975 | D13: -31962 | E13: -31503 | F13: -16072 | G13: -35079 | H13: -35304 | I13: -29702 | J13: -20205 | K13: -15168 | L13: -19230 | M13: -31414 | N13: -38042
B14: Fixed assets sold | C14: 50 | D14: 74 | E14: 59 | F14: 53 | G14: 30 | H14: 67 | I14: 171 | J14: 351 | K14: 230 | L14: 285 | M14: 231 | N14: 974
... B33: Net Cash Flow | C33: 4277 | D33: 4500 | E33: -2589 | F33: -3167 | G33: 730 | H33: 6843 | I33: -3092 | J33: 13232 | K33: 6459 | L33: -6272 | M33: 8128 | N33: -5666

Sheet Data Sheet
A1: COMPANY NAME | B1: TATA MOTORS LTD | E1: Tata Motors
A2: LATEST VERSION | B2: 2.1 | E2: PLEASE DO NOT MAKE ANY CHANGES TO THIS SHEET
A3: CURRENT VERSION | B3: 2.1
A5: META
A6: Number of shares | B6: =IF(B9>0, B9/B8, 0) -> 368.22742
A7: Face Value | B7: 2
A8: Current Price | B8: 678.7
A9: Market Capitalization | B9: 249915.95
A15: PROFIT & LOSS
A16: Report Date | B16: 42460 | C16: 42825 | D16: 43190 | E16: 43555 | F16: 43921 | G16: 44286 | H16: 44651 | I16: 45016 | J16: 45382 | K16: 45747
A17: Sales | B17: 273045.6 | C17: 269692.51 | D17: 291550.48 | E17: 301938.4 | F17: 261067.97 | G17: 249794.75 | H17: 278453.62 | I17: 345966.97 | J17: 434016 | K17: 439695
A18: Raw Material Cost | B18: 166134.01 | C18: 173294.08 | D18: 187896.58 | E18: 194267.91 | F18: 164899.82 | G18: 153607.36 | H18: 179295.33 | I18: 231251.26 | J18: 274321 | K18: 268950
A19: Change in Inventory | B19: 2750.99 | C19: 7399.92 | D19: 2046.58 | E19: -2053.28 | F19: -2231.19 | G19: -4684.16 | H19: -1590.49 | I19: 4781.62 | J19: 1566 | K19: -2836
A20: Power and Fuel | B20: 1143.63 | C20: 1159.82 | D20: 1308.08 | E20: 1585.93 | F20: 1264.95 | G20: 1112.87 | H20: 2178.29 | I20: 2513.33 | J20: 2189 | K20: 2443
A21: Other Mfr. Exp | B21: 12101.53 | C21: 10067.37 | D21: 10971.66 | E21: 11694.54 | F21: 11541.51 | G21: 8273.17 | H21: 9427.38 | I21: 11765.97 | J21: 17446 | K21: 18813
A22: Employee Cost | B22: 28880.89 | C22: 28332.89 | D22: 30300.09 | E22: 33243.87 | F22: 30438.6 | G22: 27648.48 | H22: 30808.52 | I22: 33654.7 | J22: 41990 | K22: 47767
A23: Selling and admin | B23: 21991.9 | C23: 30039.38 | D23: 31004.58 | E23: 32719.8 | F23: 29248.32 | G23: 23015.79 | H23: 29205.4 | I23: 34839.19 | J23: 42765 | K23: 47099
A24: Other Expenses | B24: 7149.38 | C24: 4610.2 | D24: 658.39 | E24: 1708.74 | F24: 3456.51 | G24: -834.51 | H24: 1228.12 | I24: 4908.34 | J24: -953 | K24: -3429
A25: Other Income | B25: -2669.62 | C25: 1869.1 | D25: 5932.73 | E25: -26686.25 | F25: 101.71 | G25: -11117.83 | H25: 2424.05 | I25: 6663.97 | J25: 4792 | K25: 11774
A26: Depreciation | B26: 16710.78 | C26: 17904.99 | D26: 21553.59 | E26: 23590.63 | F26: 21425.43 | G26: 23546.71 | H26: 24835.69 | I26: 24860.36 | J26: 27239 | K26: 23256
A27: Interest | B27: 4889.08 | C27: 4238.01 | D27: 4681.79 | E27: 5758.6 | F27: 7243.33 | G27: 8097.17 | H27: 9311.86 | I27: 10225.48 | J27: 7594 | K27: 5083
... A30: Net profit | B30: 11579.31 | C30: 7454.36 | D30: 8988.91 | E30: -28826.23 | F30: -12070.85 | G30: -13451.39 | H30: -11441.47 | I30: 2414.29 | J30: 31399 | K30: 27830
A31: Dividend Amount | B31: 67.92 | I31: 766.02 | J31: 2301 | K31: 2208
A40: Quarters
A41: Report Date | B41: 45016 | C41: 45107 | D41: 45199 | E41: 45291 | F41: 45382 | G41: 45473 | H41: 45565 | I41: 45657 | J41: 45747 | K41: 45838
A42: Sales | B42: 105932.35 | C42: 102236 | D42: 105129 | E42: 110577 | F42: 119033 | G42: 107102 | H42: 101450 | I42: 112608 | J42: 119503 | K42: 104407
A43: Expenses | B43: 92817.95 | C43: 89019 | D43: 91362 | E43: 95159 | F43: 102348 | G43: 91854 | H43: 89291 | I43: 100185 | J43: 102685 | K43: 94183
A44: Other Income | B44: 1452.86 | C44: 895 | D44: 1557 | E44: 1604 | F44: 1412 | G44: 6553 | H44: 1647 | I44: 1700 | J44: 1057 | K44: 1595
A45: Depreciation | B45: 7050.2 | C45: 6633 | D45: 6637 | E45: 6850 | F45: 7143 | G45: 6565 | H45: 6005 | I45: 5399 | J45: 5295 | K45: 5320
A46: Interest | B46: 2641.67 | C46: 2615 | D46: 2652 | E46: 2485 | F46: 1645 | G46: 1471 | H46: 2034 | I46: 1119 | J46: 1076 | K46: 938
A47: Profit before tax | B47: 4875.39 | C47: 4864 | D47: 6035 | E47: 7687 | F47: 9309 | G47: 13765 | H47: 5767 | I47: 7605 | J47: 11504 | K47: 5561
A48: Tax | B48: -620.65 | C48: 1563 | D48: 2203 | E48: 542 | F48: -8219 | G48: 3178 | H48: 2317 | I48: 2120 | J48: 2948 | K48: 1558
A49: Net profit | B49: 5407.79 | C49: 3203 | D49: 3764 | E49: 7025 | F49: 17407 | G49: 10514 | H49: 3343 | I49: 5406 | J49: 8470 | K49: 3924
A50: Operating Profit | B50: 13114.4 | C50: 13217 | D50: 13767 | E50: 15418 | F50: 16685 | G50: 15248 | H50: 12159 | I50: 12423 | J50: 16818 | K50: 10224
A55: BALANCE SHEET
A56: Report Date | B56: 42460 | C56: 42825 | D56: 43190 | E56: 43555 | F56: 43921 | G56: 44286 | H56: 44651 | I56: 45016 | J56: 45382 | K56: 45747
A57: Equity Share Capital | B57: 679.18 | C57: 679.22 | D57: 679.22 | E57: 679.22 | F57: 719.54 | G57: 765.81 | H57: 765.88 | I57: 766.02 | J57: 767 | K57: 736
A58: Reserves | B58: 78273.23 | C58: 57382.67 | D58: 94748.69 | E58: 59500.34 | F58: 62358.99 | G58: 54480.91 | H58: 43795.36 | I58: 44555.77 | J58: 84151 | K58: 115408
A59: Borrowings | B59: 69359.96 | C59: 78603.98 | D59: 88950.47 | E59: 106175.34 | F59: 124787.64 | G59: 142130.57 | H59: 146449.03 | I59: 134113.44 | J59: 107264 | K59: 71540
A60: Other Liabilities | B60: 114871.75 | C60: 135914.49 | D60: 142813.43 | E60: 139348.59 | F60: 132313.22 | G60: 144192.62 | H60: 138051.22 | I60: 155239.2 | J60: 177339 | K60: 189289
A61: Total | B61: 263184.12 | C61: 272580.36 | D61: 327191.81 | E61: 305703.49 | F61: 320179.39 | G61: 341569.91 | H61: 329061.49 | I61: 334674.43 | J61: 369521 | K61: 376973
A62: Net Block | B62: 107231.76 | C62: 95944.08 | D62: 121413.86 | E62: 111234.47 | F62: 127107.14 | G62: 138707.61 | H62: 138855.45 | I62: 132079.76 | J62: 121285 | K62: 115697
A63: Capital Work in Progress | B63: 25918.94 | C63: 33698.84 | D63: 40033.5 | E63: 31883.84 | F63: 35622.29 | G63: 20963.93 | H63: 10251.09 | I63: 14274.5 | J63: 35698 | K63: 65806
A64: Investments | B64: 23767.02 | C64: 20337.92 | D64: 20812.75 | E64: 15770.72 | F64: 16308.48 | G64: 24620.28 | H64: 29379.53 | I64: 26379.16 | J64: 22971 | K64: 35656
A65: Other Assets | B65: 106266.4 | C65: 122599.52 | D65: 144931.7 | E65: 146814.46 | F65: 141141.48 | G65: 157278.09 | H65: 150575.42 | I65: 161941.01 | J65: 189567 | K65: 159814
A66: Total | B66: 263184.12 | C66: 272580.36 | D66: 327191.81 | E66: 305703.49 | F66: 320179.39 | G66: 341569.91 | H66: 329061.49 | I66: 334674.43 | J66: 369521 | K66: 376973
A67: Receivables | B67: 13570.91 | C67: 14075.55 | D67: 19893.3 | E67: 18996.17 | F67: 11172.69 | G67: 12679.08 | H67: 12442.12 | I67: 15737.97 | J67: 16952 | K67: 13248
... A70: No. of Equity Shares | B70: 3395930306 | C70: 3396100719 | D70: 3396100719 | E70: 3396100719 | F70: 3597726185 | G70: 3829060661 | H70: 3829414903 | I70: 3830097221 | J70: 3832491897 | K70: 3681348742
A71: New Bonus Shares
A72: Face value | B72: 2 | C72: 2 | D72: 2 | E72: 2 | F72: 2 | G72: 2 | H72: 2 | I72: 2 | J72: 2 | K72: 2
A75: Other Essests | B75: =B65-SUM(B67:B69) -> 29579.36 | C75: =C65-SUM(C67:C69) -> 37360.78 | D75: =D65-SUM(D67:D69) -> 48286.86 | E75: =E65-SUM(E67:E69) -> 56155.74 | F75: =F65-SUM(F67:F69) -> 58784.94 | G75: =G65-SUM(G67:G69) -> 61717.96 | H75: =H65-SUM(H67:H69) -> 62223.77 | I75: =I65-SUM(I67:I69) -> 68432.09 | ... K75: =K65-SUM(K67:K69) -> 58463
A76: Total Assets | B76: =SUM(B62:B64,B75,B67:B69) -> 263184.12 | C76: =SUM(C62:C64,C75,C67:C69) -> 272580.36 | D76: =SUM(D62:D64,D75,D67:D69) -> 327191.81 | E76: =SUM(E62:E64,E75,E67:E69) -> 305703.49 | F76: =SUM(F62:F64,F75,F67:F69) -> 320179.39 | G76: =SUM(G62:G64,G75,G67:G69) -> 341569.91 | H76: =SUM(H62:H64,H75,H67:H69) -> 329061.49 | I76: =SUM(I62:I64,I75,I67:I69) -> 334674.43 | ... K76: =SUM(K62:K64,K75,K67:K69) -> 376973
A80: CASH FLOW:
A81: Report Date | B81: 42460 | C81: 42825 | D81: 43190 | E81: 43555 | F81: 43921 | G81: 44286 | H81: 44651 | I81: 45016 | J81: 45382 | K81: 45747
A82: Cash from Operating Activity | B82: 37899.54 | C82: 30199.25 | D82: 23857.42 | E82: 18890.75 | F82: 26632.94 | G82: 29000.51 | H82: 14282.83 | I82: 35388.01 | J82: 67915 | K82: 63102
A83: Cash from Investing Activity | B83: -36693.9 | C83: -39571.4 | D83: -25139.14 | E83: -20878.07 | F83: -33114.55 | G83: -25672.5 | H83: -4443.66 | I83: -15417.17 | J83: -22781 | K83: -49982
A84: Cash from Financing Activity | B84: -3795.12 | C84: 6205.3 | D84: 2011.71 | E84: 8830.37 | F84: 3389.61 | G84: 9904.2 | H84: -3380.17 | I84: -26242.9 | J84: -37006 | K84: -18786
A85: Net Cash Flow | B85: -2589.48 | C85: -3166.85 | D85: 729.99 | E85: 6843.05 | F85: -3092 | G85: 13232.21 | H85: 6459 | I85: -6272.06 | J85: 8128 | K85: -5666
A90: PRICE: | B90: 386.6 | C90: 465.85 | D90: 326.85 | E90: 174.25 | F90: 71.05 | G90: 301.8 | H90: 433.75 | I90: 420.8 | J90: 992.8 | K90: 674.45
A92: DERIVED:
A93: Adjusted Equity Shares in Cr | B93: 288.72 | C93: 288.73 | D93: 288.73 | E93: 288.73 | F93: 308.9 | G93: 332.03 | H93: 332.07 | I93: 332.13 | J93: 332.37 | K93: 368.13

Sheet Asian Paints Data
B2: Particulars | C2: 41699 | D2: 42064 | E2: 42430 | F2: 42795 | G2: 43160 | H2: 43525 | I2: 43891 | J2: 44256 | K2: 44621 | L2: 44986 | M2: 45352 | N2: 45717
B4: Equity Capital | C4: 96 | D4: 96 | E4: 96 | F4: 96 | G4: 96 | H4: 96 | I4: 96 | J4: 96 | K4: 96 | L4: 96 | M4: 96 | N4: 96
B5: Reserves | C5: 3943 | D5: 4646 | E5: 6429 | F5: 7508 | G5: 8314 | H5: 9375 | I5: 10034 | J5: 12710 | K5: 13716 | L5: 15896 | M5: 18632 | N5: 19304
B6: Borrowings -
B7: Long term Borrowings | C7: 41 | D7: 78 | E7: 73 | F7: 41 | G7: 28 | H7: 19 | I7: 19 | J7: 15 | K7: 45 | L7: 76 | M7: 54 | N7: 260
B8: Short term Borrowings | C8: 199 | D8: 332 | E8: 231 | F8: 504 | G8: 492 | H8: 597 | I8: 321 | J8: 334 | K8: 731 | L8: 896 | M8: 1053 | N8: 604
B9: Lease Liabilities | C9: 0 | D9: 0 | E9: 0 | F9: 0 | G9: 0 | H9: 693 | I9: 764 | J9: 745 | K9: 811 | L9: 960 | M9: 1367 | N9: 1427
B10: Other Borrowings | C10: 9 | D10: 8 | E10: 20 | F10: 15 | G10: 13 | H10: 11 | I10: 15 | J10: 0 | K10: 0 | L10: 0 | M10: 0 | N10: 0
B11: Other Liabilities -
B12: Non controlling int | C12: 246 | D12: 264 | E12: 384 | F12: 375 | G12: 328 | H12: 361 | I12: 404 | J12: 423 | K12: 388 | L12: 454 | M12: 695 | N12: 659 | O12: It's not an current Liability
B13: Trade Payables | C13: 1746 | D13: 1549 | E13: 1565 | F13: 1923 | G13: 2160 | H13: 2394 | I13: 2137 | J13: 3379 | K13: 4164 | L13: 3635 | M13: 3831 | N13: 3848
B14: Advance from Customers | C14: 0 | D14: 5 | E14: 12 | F14: 17 | G14: 16 | H14: 13 | I14: 29 | J14: 41 | K14: 76 | L14: 108 | M14: 154 | N14: 173
B15: Other liability items | C15: 1795 | D15: 1937 | E15: 1750 | F15: 1925 | G15: 2316 | H15: 2690 | I15: 2320 | J15: 2613 | K15: 2932 | L15: 3657 | M15: 4017 | N15: 3985
B17: Total Liabilities | C17: 8075 | D17: 8914 | E17: 10559 | F17: 12405 | G17: 13763 | H17: 16249 | I17: 16138 | J17: 20355 | K17: 22958 | L17: 25779 | M17: 29901 | N17: 30355
B19: Fixed Assets -
B20: Land | C20: 247 | D20: 251 | E20: 429 | F20: 408 | G20: 586 | H20: 605 | I20: 640 | J20: 644 | K20: 644 | L20: 804 | M20: 1126 | N20: 1050
B21: Building | C21: 931 | D21: 962 | E21: 923 | F21: 931 | G21: 957 | H21: 2402 | I21: 2257 | J21: 2249 | K21: 2325 | L21: 2883 | M21: 3390 | N21: 4136
B22: Plant Machinery | C22: 2054 | D22: 2132 | E22: 1793 | F22: 1980 | G22: 2157 | H22: 4006 | I22: 4208 | J22: 4340 | K22: 4531 | L22: 4825 | M22: 5422 | N22: 7576
B23: Equipments | C23: 155 | D23: 171 | E23: 97 | F23: 119 | G23: 200 | H23: 221 | I23: 241 | J23: 243 | K23: 253 | L23: 270 | M23: 298 | N23: 325
B24: Furniture n fittings | C24: 71 | D24: 83 | E24: 49 | F24: 59 | G24: 72 | H24: 88 | I24: 94 | J24: 99 | K24: 113 | L24: 146 | M24: 175 | N24: 203
B25: Vehicles | C25: 14 | D25: 18 | E25: 11 | F25: 14 | G25: 27 | H25: 47 | I25: 43 | J25: 38 | K25: 32 | L25: 36 | M25: 40 | N25: 39
B26: Intangible Assets | C26: 203 | D26: 351 | E26: 339 | F26: 276 | G26: 468 | H26: 512 | I26: 505 | J26: 476 | K26: 345 | L26: 422 | M26: 850 | N26: 827
B27: Other fixed assets | C27: 128 | D27: 145 | E27: 103 | F27: 128 | G27: 238 | H27: 261 | I27: 293 | J27: 302 | K27: 294 | L27: 289 | M27: 321 | N27: 328
B28: Gross Block | C28: 3804 | D28: 4112 | E28: 3744 | F28: 3914 | G28: 4705 | H28: 8141 | I28: 8282 | J28: 8392 | K28: 8538 | L28: 9676 | M28: 11622 | N28: 14484
B29: Accumulated Depreciation | C29: -1242 | D29: -1242 | E29: -1242 | F29: -1242 | G29: -1242 | H29: -1242 | I29: -1242 | J29: -1242 | K29: -1242 | L29: -1242 | M29: -1242 | N29: -1242
B30: Net Block | C30: =SUM(C28:C29) -> 2562 | D30: =SUM(D28:D29) -> 2870 | E30: =SUM(E28:E29) -> 2502 | F30: =SUM(F28:F29) -> 2672 | G30: =SUM(G28:G29) -> 3463 | H30: =SUM(H28:H29) -> 6899 | I30: =SUM(I28:I29) -> 7040 | J30: =SUM(J28:J29) -> 7150 | ... N30: =SUM(N28:N29) -> 13242
B32: CWIP | C32: 72 | D32: 196 | E32: 107 | F32: 258 | G32: 1405 | H32: 210 | I32: 140 | J32: 183 | K32: 426 | L32: 1020 | M32: 2698 | N32: 1254
B33: Investments | C33: 1424 | D33: 1588 | E33: 2712 | F33: 2652 | G33: 2141 | H33: 2569 | I33: 2019 | J33: 4737 | K33: 3248 | L33: 4262 | M33: 4588 | N33: 4725
B36: Other Assets -
B37: Inventories | C37: 2070 | D37: 2259 | E37: 1998 | F37: 2627 | G37: 2658 | H37: 3150 | I37: 3390 | J37: 3799 | K37: 6153 | L37: 6211 | M37: 5923 | N37: 6719
B38: Trade receivables - | C38: 1110 | D38: 1182 | E38: 1187 | F38: 1447 | G38: 1731 | H38: 1907 | I38: 1795 | J38: 2602 | K38: 3871 | L38: 4637 | M38: 4889 | N38: 4314
B39: Receivables over 6m | C39: 51 | D39: 61 | E39: 0 | F39: 0 | G39: 0 | H39: 0 | I39: 0 | J39: 0 | K39: 279 | L39: 366 | M39: 588 | N39: 726
B40: Receivables under 6m | C40: 1110 | D40: 1180 | E40: 1253 | F40: 1526 | G40: 1820 | H40: 2028 | I40: 1950 | J40: 2787 | K40: 3834 | L40: 4576 | M40: 4723 | N40: 4250
B41: Prov for Doubtful | C41: -50 | D41: -59 | E41: -67 | F41: -79 | G41: -89 | H41: -121 | I41: -155 | J41: -185 | K41: -241 | L41: -305 | M41: -422 | N41: -663
B42: Cash Equivalents | C42: 229 | D42: 204 | E42: 424 | F42: 801 | G42: 405 | H42: 445 | I42: 783 | J42: 611 | K42: 864 | L42: 844 | M42: 1084 | N42: 782
B43: Loans n Advances | C43: 7 | D43: 8 | E43: 9 | F43: 14 | G43: 13 | H43: 16 | I43: 12 | J43: 11 | K43: 8 | L43: 12 | M43: 17 | N43: 22
B44: Other asset items | C44: 603 | D44: 817 | E44: 705 | F44: 1303 | G44: 1678 | H44: 1456 | I44: 1727 | J44: 2555 | K44: 2869 | L44: 3024 | M44: 3555 | N44: 3319
B45: Total Assets | C45: 8075 | D45: 8914 | E45: 10559 | F45: 12405 | G45: 13763 | H45: 16249 | I45: 16138 | J45: 20355 | K45: 22958 | L45: 25779 | M45: 29901 | N45: 30355
B49: P & L
C51: 44713 | D51: 44805 | E51: 44896 | F51: 44986 | G51: 45078 | H51: 45170 | I51: 45261 | J51: 45352 | K51: 45444 | L51: 45536 | M51: 45627 | N51: 45717 | O51: 45809
B52: Sales + | C52: 8607 | D52: 8458 | E52: 8637 | F52: 8787 | G52: 9182 | H52: 8479 | I52: 9103 | J52: 8731 | K52: 8970 | L52: 8028 | M52: 8549 | N52: 8359 | O52: 8939
B53: Expenses + | C53: 7051 | D53: 7230 | E53: 7025 | F53: 6923 | G53: 7061 | H53: 6762 | I53: 7047 | J53: 7039 | K53: 7276 | L53: 6788 | M53: 6913 | N53: 6923 | O53: 7314
B54: Operating Profit | C54: 1556 | D54: 1228 | E54: 1611 | F54: 1865 | G54: 2121 | H54: 1716 | I54: 2056 | J54: 1691 | K54: 1694 | L54: 1240 | M54: 1637 | N54: 1436 | O54: 1625
B55: OPM % | C55: 0.18 | D55: 0.15 | E55: 0.19 | F55: 0.21 | G55: 0.23 | H55: 0.2 | I55: 0.23 | J55: 0.19 | K55: 0.19 | L55: 0.15 | M55: 0.19 | N55: 0.17 | O55: 0.18
B56: Other Income + | C56: 88 | D56: 118 | E56: 122 | F56: 104 | G56: 228 | H56: 194 | I56: 186 | J56: 212 | K56: 193 | L56: 25 | M56: 193 | N56: -60 | O56: 229
B57: Interest | C57: 29 | D57: 35 | E57: 41 | F57: 39 | G57: 46 | H57: 51 | I57: 54 | J57: 54 | K57: 55 | L57: 63 | M57: 56 | N57: 53 | O57: 44
B58: Depreciation | C58: 208 | D58: 216 | E58: 214 | F58: 220 | G58: 198 | H58: 209 | I58: 220 | J58: 226 | K58: 228 | L58: 242 | M58: 256 | N58: 301 | O58: 301
B59: Profit before tax | C59: 1407 | D59: 1094 | E59: 1478 | F59: 1710 | G59: 2105 | H59: 1651 | I59: 1968 | J59: 1624 | K59: 1604 | L59: 959 | M59: 1518 | N59: 1022 | O59: 1509
B60: Tax % | C60: 0.26 | D60: 0.27 | E60: 0.26 | F60: 0.26 | G60: 0.25 | H60: 0.25 | I60: 0.25 | J60: 0.21 | K60: 0.26 | L60: 0.28 | M60: 0.26 | N60: 0.31 | O60: 0.26
B61: Net Profit + | C61: 1036 | D61: 804 | E61: 1097 | F61: 1258 | G61: 1575 | H61: 1232 | I61: 1475 | J61: 1275 | K61: 1187 | L61: 694 | M61: 1128 | N61: 701 | O61: 1117
B62: EPS in Rs | C62: 10.6 | D62: 8.16 | E62: 11.18 | F62: 12.87 | G62: 16.16 | H62: 12.57 | I62: 15.09 | J62: 13.1 | K62: 12.2 | L62: 7.24 | M62: 11.58 | N62: 7.22 | O62: 11.47
B64: EBIT | C64: =C54-C58 -> 1348 | D64: =D54-D58 -> 1012 | E64: =E54-E58 -> 1397 | F64: =F54-F58 -> 1645 | G64: =G54-G58 -> 1923 | H64: =H54-H58 -> 1507 | I64: =I54-I58 -> 1836 | J64: =J54-J58 -> 1465 | ... O64: =O54-O58 -> 1324
B67: Cash Flow Statements
C69: 41699 | D69: 42064 | E69: 42430 | F69: 42795 | G69: 43160 | H69: 43525 | I69: 43891 | J69: 44256 | K69: 44621 | L69: 44986 | M69: 45352 | N69: 45717
B70: Cash from Operating Activity - | C70: 1402 | D70: 1188 | E70: 2243 | F70: 1527 | G70: 2113 | H70: 2470 | I70: 3038 | J70: 3683 | K70: 986 | L70: 4193 | M70: 6104 | N70: 4424
B71: Profit from operations | C71: 2051 | D71: 2271 | E71: 2848 | F71: 3056 | G71: 3274 | H71: 3861 | I71: 4380 | J71: 4970 | K71: 4957 | L71: 6460 | M71: 7929 | N71: 6390
B72: Receivables | C72: -254 | D72: -155 | E72: -146 | F72: -475 | G72: -483 | H72: -205 | I72: 160 | J72: -849 | K72: -1326 | L72: -834 | M72: -362 | N72: 282
B73: Inventory | C73: -231 | D73: -144 | E73: 202 | F73: -629 | G73: -39 | H73: -492 | I73: -251 | J73: -409 | K73: -2354 | L73: -56 | M73: 315 | N73: -805
B74: Payables | C74: 317 | D74: -151 | E74: 142 | F74: 501 | G74: 442 | H74: 287 | I74: -241 | J74: 1143 | K74: 644 | L74: -539 | M74: 269 | N74: -160
B75: Other WC items | C75: 0 | D75: 0 | E75: 0 | F75: 0 | G75: 0 | H75: 0 | I75: 0 | J75: -92 | K75: 242 | L75: 657 | M75: -212 | N75: 114
B76: Working capital changes | C76: -168 | D76: -450 | E76: 198 | F76: -603 | G76: -80 | H76: -410 | I76: -331 | J76: -206 | K76: -2795 | L76: -772 | M76: 10 | N76: -570
B77: Direct taxes | C77: -480 | D77: -633 | E77: -802 | F77: -925 | G77: -1081 | H77: -982 | I77: -1011 | J77: -1080 | K77: -1176 | L77: -1494 | M77: -1835 | N77: -1396
B78: Cash from Investing Activity - | C78: -586 | D78: -465 | E78: -866 | F78: -681 | G78: -1556 | H78: -918 | I78: -518 | J78: -541 | K78: -317 | L78: -1282 | M78: -2548 | N78: -941
B79: Fixed assets purchased | C79: -251 | D79: -454 | E79: -817 | F79: -684 | G79: -1426 | H79: -1151 | I79: -404 | J79: -282 | K79: -551 | L79: -1446 | M79: -2496 | N79: -1830
B80: Fixed assets sold | C80: 16 | D80: 16 | E80: 15 | F80: 17 | G80: 17 | H80: 17 | I80: 37 | J80: 28 | K80: 40 | L80: 26 | M80: 5 | N80: 10
B81: Investments purchased | C81: -872 | D81: -243 | E81: -282 | F81: -153 | G81: -320 | H81: -573 | I81: -25 | J81: -140 | K81: 0 | L81: -146 | M81: -212 | N81: -1
... B97: Net Cash Flow | C97: 190 | D97: 147 | E97: 528 | F97: 90 | G97: -822 | H97: 434 | I97: -351 | J97: 2492 | K97: -1138 | L97: 771 | M97: 573 | N97: -270
C102: 41699 | D102: 42064 | E102: 42430 | F102: 42795 | G102: 43160 | H102: 43525 | I102: 43891 | J102: 44256 | K102: 44621 | L102: 44986 | M102: 45352 | N102: 45717
B103: Sales + | C103: 12220 | D103: 13615 | E103: 14271 | F103: 15062 | G103: 16825 | H103: 19240 | I103: 20211 | J103: 21713 | K103: 29101 | L103: 34489 | M103: 35495 | N103: 33906
B104: Expenses + | C104: 10217 | D104: 11372 | E104: 11546 | F104: 12068 | G104: 13621 | H104: 15475 | I104: 16054 | J104: 16857 | K104: 24298 | L104: 28229 | M104: 27910 | N104: 27899
B105: Operating Profit | C105: 2004 | D105: 2243 | E105: 2725 | F105: 2994 | G105: 3204 | H105: 3765 | I105: 4157 | J105: 4856 | K105: 4804 | L105: 6260 | M105: 7585 | N105: 6006
B106: OPM % | C106: 0.16 | D106: 0.16 | E106: 0.19 | F106: 0.2 | G106: 0.19 | H106: 0.2 | I106: 0.21 | J106: 0.22 | K106: 0.17 | L106: 0.18 | M106: 0.21 | N106: 0.18
B107: Other Income + | C107: 124 | D107: 142 | E107: 213 | F107: 338 | G107: 336 | H107: 274 | I107: 355 | J107: 332 | K107: 296 | L107: 431 | M107: 821 | N107: 350
B108: Interest | C108: 48 | D108: 42 | E108: 49 | F108: 37 | G108: 41 | H108: 110 | I108: 102 | J108: 92 | K108: 95 | L108: 144 | M108: 205 | N108: 227
B109: Depreciation | C109: 246 | D109: 266 | E109: 276 | F109: 335 | G109: 360 | H109: 622 | I109: 780 | J109: 791 | K109: 816 | L109: 858 | M109: 853 | N109: 1026
B110: Profit before tax | C110: 1834 | D110: 2077 | E110: 2614 | F110: 2960 | G110: 3138 | H110: 3306 | I110: 3629 | J110: 4304 | K110: 4188 | L110: 5689 | M110: 7348 | N110: 5103
B111: Tax % | C111: 0.31 | D111: 0.31 | E111: 0.32 | F111: 0.32 | G111: 0.33 | H111: 0.33 | I111: 0.24 | J111: 0.26 | K111: 0.26 | L111: 0.26 | M111: 0.24 | N111: 0.27
B112: Tax \ | C112: =C110*(1-C111) -> 1265.46 | D112: =D110*(1-D111) -> 1433.13 | E112: =E110*(1-E111) -> 1777.52 | F112: =F110*(1-F111) -> 2012.8 | G112: =G110*(1-G111) -> 2102.46 | H112: =H110*(1-H111) -> 2215.02 | I112: =I110*(1-I111) -> 2758.04 | J112: =J110*(1-J111) -> 3184.96 | ... N112: =N110*(1-N111) -> 3725.19
B113: Net Profit + | C113: 1263 | D113: 1427 | E113: 1803 | F113: 2016 | G113: 2098 | H113: 2208 | I113: 2774 | J113: 3207 | K113: 3085 | L113: 4195 | M113: 5558 | N113: 3710
B114: EPS in Rs | C114: 12.71 | D114: 14.54 | E114: 18.19 | F114: 20.22 | G114: 21.26 | H114: 22.48 | I114: 28.2 | J114: 32.73 | K114: 31.59 | L114: 42.81 | M114: 56.92 | N114: 38.23
B115: Dividend Payout % | C115: 0.42 | D115: 0.42 | E115: 0.41 | F115: 0.51 | G115: 0.41 | H115: 0.47 | I115: 0.43 | J115: 0.55 | K115: 0.61 | L115: 0.6 | M115: 0.58 | N115: 0.65
B117: EBIT | C117: =C105-C109 -> 1758 | D117: =D105-D109 -> 1977 | E117: =E105-E109 -> 2449 | F117: =F105-F109 -> 2659 | G117: =G105-G109 -> 2844 | H117: =H105-H109 -> 3143 | I117: =I105-I109 -> 3377 | J117: =J105-J109 -> 4065 | ... N117: =N105-N109 -> 4980
C119: =C113+C112+C109+C108 -> 2822.46 | D119: =D113+D112+D109+D108 -> 3168.13 | E119: =E113+E112+E109+E108 -> 3905.52 | F119: =F113+F112+F109+F108 -> 4400.8 | G119: =G113+G112+G109+G108 -> 4601.46 | H119: =H113+H112+H109+H108 -> 5155.02 | I119: =I113+I112+I109+I108 -> 6414.04 | J119: =J113+J112+J109+J108 -> 7274.96 | ... N119: =N113+N112+N109+N108 -> 8688.19
