Workbook
Name UPDATE: 'Data Sheet'!$E$1

Sheet Income Statement
B6: ="Historical Data of " &'Data Sheet'!B1 -> Historical Data of BERGER PAINTS INDIA LTD
B7: Years | D7: ='Data Sheet'!B16 -> 42460 | E7: ='Data Sheet'!C16 -> 42825 | F7: ='Data Sheet'!D16 -> 43190 | G7: ='Data Sheet'!E16 -> 43555 | H7: ='Data Sheet'!F16 -> 43921 | I7: ='Data Sheet'!G16 -> 44286 | J7: ='Data Sheet'!H16 -> 44651 | K7: ='Data Sheet'!I16 -> 45016 | ... M7: ='Data Sheet'!K16 -> 45747 | N7: LTM
B8: Income Statement
B10: Sales | D10: ='Data Sheet'!B17 -> 4223.1 | E10: ='Data Sheet'!C17 -> 4552.25 | F10: ='Data Sheet'!D17 -> 5165.73 | G10: ='Data Sheet'!E17 -> 6061.86 | H10: ='Data Sheet'!F17 -> 6365.82 | I10: ='Data Sheet'!G17 -> 6817.59 | J10: ='Data Sheet'!H17 -> 8761.78 | K10: ='Data Sheet'!I17 -> 10567.84 | ... M10: ='Data Sheet'!K17 -> 11544.71 | N10: =IFERROR(SUM('Data Sheet'!H42:K42), "-") -> 11654.46
B11: Sales Growth | E11: =E10/D10-1 -> 0.077940376 | F11: =F10/E10-1 -> 0.13476413 | G11: =G10/F10-1 -> 0.17347597 | H11: =H10/G10-1 -> 0.050143025 | I11: =I10/H10-1 -> 0.070968076 | J11: =J10/I10-1 -> 0.28517262 | K11: =K10/J10-1 -> 0.20612935 | L11: =L10/K10-1 -> 0.059717028 | ... N11: =N10/M10-1 -> 0.0095065186
B13: COGS | D13: =SUM('Data Sheet'!B18,'Data Sheet'!B20,'Data Sheet'!B21) - 1 *'Data Sheet'!B19 -> 2851.32 | E13: =SUM('Data Sheet'!C18,'Data Sheet'!C20,'Data Sheet'!C21) - 1 *'Data Sheet'!C19 -> 3009.76 | F13: =SUM('Data Sheet'!D18,'Data Sheet'!D20,'Data Sheet'!D21) - 1 *'Data Sheet'!D19 -> 3443.09 | G13: =SUM('Data Sheet'!E18,'Data Sheet'!E20,'Data Sheet'!E21) - 1 *'Data Sheet'!E19 -> 4208.1 | H13: =SUM('Data Sheet'!F18,'Data Sheet'!F20,'Data Sheet'!F21) - 1 *'Data Sheet'!F19 -> 4330.45 | I13: =SUM('Data Sheet'!G18,'Data Sheet'!G20,'Data Sheet'!G21) - 1 *'Data Sheet'!G19 -> 4538.84 | J13: =SUM('Data Sheet'!H18,'Data Sheet'!H20,'Data Sheet'!H21) - 1 *'Data Sheet'!H19 -> 6272 | K13: =SUM('Data Sheet'!I18,'Data Sheet'!I20,'Data Sheet'!I21) - 1 *'Data Sheet'!I19 -> 7716.11 | ... M13: =SUM('Data Sheet'!K18,'Data Sheet'!K20,'Data Sheet'!K21) - 1 *'Data Sheet'!K19 -> 7756.5 | N13: =IFERROR(SUM('Data Sheet'!H43:K43), "-") -> 9792.37
B14: COGS as % of Revenue | D14: =D13/D10 -> 0.67517227 | E14: =E13/E10 -> 0.66115877 | F14: =F13/F10 -> 0.66652535 | G14: =G13/G10 -> 0.69419287 | H14: =H13/H10 -> 0.68026586 | I14: =I13/I10 -> 0.66575432 | J14: =J13/J10 -> 0.71583628 | K14: =K13/K10 -> 0.73015015 | ... N14: =N13/N10 -> 0.84022512
B16: Gross Profit | D16: =D10-D13 -> 1371.78 | E16: =E10-E13 -> 1542.49 | F16: =F10-F13 -> 1722.64 | G16: =G10-G13 -> 1853.76 | H16: =H10-H13 -> 2035.37 | I16: =I10-I13 -> 2278.75 | J16: =J10-J13 -> 2489.78 | K16: =K10-K13 -> 2851.73 | ... N16: =N10-N13 -> 1862.09
B17: Gross Margin | D17: =D16/D10 -> 0.32482773 | E17: =E16/E10 -> 0.33884123 | F17: =F16/F10 -> 0.33347465 | G17: =G16/G10 -> 0.30580713 | H17: =H16/H10 -> 0.31973414 | I17: =I16/I10 -> 0.33424568 | J17: =J16/J10 -> 0.28416372 | K17: =K16/K10 -> 0.26984985 | ... N17: =N16/N10 -> 0.15977488
B19: Selling & general expenses | D19: =SUM('Data Sheet'!B23:B24) -> 453.08 | E19: =SUM('Data Sheet'!C23:C24) -> 516.42 | F19: =SUM('Data Sheet'!D23:D24) -> 558.59 | G19: =SUM('Data Sheet'!E23:E24) -> 510.16 | H19: =SUM('Data Sheet'!F23:F24) -> 529.57 | I19: =SUM('Data Sheet'!G23:G24) -> 610.67 | J19: =SUM('Data Sheet'!H23:H24) -> 615.02 | K19: =SUM('Data Sheet'!I23:I24) -> 764.18 | ... M19: =SUM('Data Sheet'!K23:K24) -> 1114.75
B20: S & G % | D20: =D19/D10 -> 0.10728612 | E20: =E19/E10 -> 0.1134428 | F20: =F19/F10 -> 0.1081338 | G20: =G19/G10 -> 0.084158988 | H20: =H19/H10 -> 0.083189597 | I20: =I19/I10 -> 0.089572708 | J20: =J19/J10 -> 0.070193499 | K20: =K19/K10 -> 0.072311844 | ... N20: =N19/N10 -> 0
B22: EBITDA | D22: =D16-D19 -> 918.7 | E22: =E16-E19 -> 1026.07 | F22: =F16-F19 -> 1164.05 | G22: =G16-G19 -> 1343.6 | H22: =H16-H19 -> 1505.8 | I22: =I16-I19 -> 1668.08 | J22: =J16-J19 -> 1874.76 | K22: =K16-K19 -> 2087.55 | ... N22: =N16-N19 -> 1862.09
B23: EBITDA Margins | D23: =D22/D10 -> 0.21754162 | E23: =E22/E10 -> 0.22539843 | F23: =F22/F10 -> 0.22534085 | G23: =G22/G10 -> 0.22164814 | H23: =H22/H10 -> 0.23654455 | I23: =I22/I10 -> 0.24467297 | J23: =J22/J10 -> 0.21397022 | K23: =K22/K10 -> 0.197538 | ... N23: =N22/N10 -> 0.15977488
B25: Depreciation | D25: ='Data Sheet'!B26 -> 98.65 | E25: ='Data Sheet'!C26 -> 108.05 | F25: ='Data Sheet'!D26 -> 124.21 | G25: ='Data Sheet'!E26 -> 182.27 | H25: ='Data Sheet'!F26 -> 191.01 | I25: ='Data Sheet'!G26 -> 211.14 | J25: ='Data Sheet'!H26 -> 226.51 | K25: ='Data Sheet'!I26 -> 264.03 | ... M25: ='Data Sheet'!K26 -> 354.19 | N25: =SUM('Data Sheet'!H45:K45) -> 360.96
B26: Depreciation | D26: =D25/D10 -> 0.023359617 | E26: =E25/E10 -> 0.023735515 | F26: =F25/F10 -> 0.024045004 | G26: =G25/G10 -> 0.030068329 | H26: =H25/H10 -> 0.030005561 | I26: =I25/I10 -> 0.030969888 | J26: =J25/J10 -> 0.025852053 | K26: =K25/K10 -> 0.024984292 | ... N26: =N25/N10 -> 0.030971834
B28: EBIT | D28: =D22-D25 -> 820.05 | E28: =E22-E25 -> 918.02 | F28: =F22-F25 -> 1039.84 | G28: =G22-G25 -> 1161.33 | H28: =H22-H25 -> 1314.79 | I28: =I22-I25 -> 1456.94 | J28: =J22-J25 -> 1648.25 | K28: =K22-K25 -> 1823.52 | ... N28: =N22-N25 -> 1501.13
B29: EBIT% | D29: =D28/D10 -> 0.194182 | E29: =E28/E10 -> 0.20166291 | F29: =F28/F10 -> 0.20129585 | G29: =G28/G10 -> 0.19157981 | H29: =H28/H10 -> 0.20653898 | I29: =I28/I10 -> 0.21370308 | J29: =J28/J10 -> 0.18811817 | K29: =K28/K10 -> 0.17255371 | ... N29: =N28/N10 -> 0.12880305
B31: Interest | D31: ='Data Sheet'!B27 -> 27.28 | E31: ='Data Sheet'!C27 -> 16.22 | F31: ='Data Sheet'!D27 -> 24.55 | G31: ='Data Sheet'!E27 -> 47.24 | H31: ='Data Sheet'!F27 -> 47.04 | I31: ='Data Sheet'!G27 -> 44.1 | J31: ='Data Sheet'!H27 -> 50.72 | K31: ='Data Sheet'!I27 -> 99.23 | ... M31: ='Data Sheet'!K27 -> 63.27 | N31: =SUM('Data Sheet'!H46:K46) -> 62.58
B32: Interest Rate% | D32: =D31/D10 -> 0.0064597097 | E32: =E31/E10 -> 0.0035630732 | F32: =F31/F10 -> 0.0047524745 | G32: =G31/G10 -> 0.0077929876 | H32: =H31/H10 -> 0.0073894644 | I32: =I31/I10 -> 0.0064685615 | J32: =J31/J10 -> 0.0057887781 | K32: =K31/K10 -> 0.0093898091 | ... N32: =N31/N10 -> 0.0053696182
B34: EBT | D34: =D28-D31 -> 792.77 | E34: =E28-E31 -> 901.8 | F34: =F28-F31 -> 1015.29 | G34: =G28-G31 -> 1114.09 | H34: =H28-H31 -> 1267.75 | I34: =I28-I31 -> 1412.84 | J34: =J28-J31 -> 1597.53 | K34: =K28-K31 -> 1724.29 | ... N34: =N28-N31 -> 1438.55
B35: EBT% | D35: =D34/D10 -> 0.18772229 | E35: =E34/E10 -> 0.19809984 | F35: =F34/F10 -> 0.19654337 | G35: =G34/G10 -> 0.18378682 | H35: =H34/H10 -> 0.19914952 | I35: =I34/I10 -> 0.20723452 | J35: =J34/J10 -> 0.18232939 | K35: =K34/K10 -> 0.1631639 | ... N35: =N34/N10 -> 0.12343343
B37: Tax rate | D37: ='Data Sheet'!B29 -> 188.62 | E37: ='Data Sheet'!C29 -> 229.42 | F37: ='Data Sheet'!D29 -> 243.91 | G37: ='Data Sheet'!E29 -> 271.27 | H37: ='Data Sheet'!F29 -> 227.06 | I37: ='Data Sheet'!G29 -> 258.9 | J37: ='Data Sheet'!H29 -> 289.34 | K37: ='Data Sheet'!I29 -> 301.94 | ... M37: ='Data Sheet'!K29 -> 385.66 | N37: =SUM('Data Sheet'!H48:K48) -> 381.44
B38: Tax% | D38: =D37/D34 -> 0.23792525 | E38: =E37/E28 -> 0.24990741 | F38: =F37/F28 -> 0.23456493 | G38: =G37/G28 -> 0.23358563 | H38: =H37/H28 -> 0.17269678 | I38: =I37/I28 -> 0.17770121 | J38: =J37/J28 -> 0.17554376 | K38: =K37/K28 -> 0.16558085 | L38: =L37/L28 -> 0.17248263 | ... N38: =N37/N28 -> 0.25410191
B40: EAT/Net Profit | D40: =D34-D37 -> 604.15 | E40: =E34-E37 -> 672.38 | F40: =F34-F37 -> 771.38 | G40: =G34-G37 -> 842.82 | H40: =H34-H37 -> 1040.69 | I40: =I34-I37 -> 1153.94 | J40: =J34-J37 -> 1308.19 | K40: =K34-K37 -> 1422.35 | ... N40: =N34-N37 -> 1057.11
B41: Profit Margin | D41: =D40/D10 -> 0.14305842 | E41: =E40/E10 -> 0.14770278 | F41: =F40/F10 -> 0.14932643 | G41: =G40/G10 -> 0.13903653 | H41: =H40/H10 -> 0.1634809 | I41: =I40/I10 -> 0.16925923 | J41: =J40/J10 -> 0.14930642 | K41: =K40/K10 -> 0.13459231 | ... N41: =N40/N10 -> 0.090704331
B44: No. of Shares | D44: ='Data Sheet'!B124 -> 116.51 | E44: ='Data Sheet'!C124 -> 116.52 | F44: ='Data Sheet'!D124 -> 116.52 | G44: ='Data Sheet'!E124 -> 116.54 | H44: ='Data Sheet'!F124 -> 116.55 | I44: ='Data Sheet'!G124 -> 116.56 | J44: ='Data Sheet'!H124 -> 116.56 | K44: ='Data Sheet'!I124 -> 116.57 | ... M44: ='Data Sheet'!K124 -> 116.59
B45: Earning Per Share | D45: =D40/D44 -> 5.1853918 | E45: =E40/E44 -> 5.7705115 | F45: =F40/F44 -> 6.620151 | G45: =G40/G44 -> 7.2320233 | H45: =H40/H44 -> 8.9291291 | I45: =I40/I44 -> 9.8999657 | J45: =J40/J44 -> 11.223318 | K45: =K40/K44 -> 12.201681 | ... M45: =M40/M44 -> 16.042028
B46: Dividend | D46: ='Data Sheet'!B31/D44 -> 0.98214746 | E46: ='Data Sheet'!C31/E44 -> 1.4582904 | F46: ='Data Sheet'!D31/F44 -> 1.5 | G46: ='Data Sheet'!E31/G44 -> 1.5832332 | H46: ='Data Sheet'!F31/H44 -> 1.8332046 | I46: ='Data Sheet'!G31/I44 -> 2.3332189 | J46: ='Data Sheet'!H31/J44 -> 2.5832189 | K46: ='Data Sheet'!I31/K44 -> 2.6666381 | ... M46: ='Data Sheet'!K31/M44 -> 3.7999828
B47: Divided Payout Ratio | D47: =D46/D45 -> 0.1894066 | E47: =E46/E45 -> 0.25271424 | F47: =F46/F45 -> 0.22658093 | G47: =G46/G45 -> 0.21891982 | H47: =H46/H45 -> 0.20530609 | I47: =I46/I45 -> 0.2356795 | J47: =J46/J45 -> 0.23016534 | K47: =K46/K45 -> 0.21854677 | ... M47: =M46/M45 -> 0.23687672
B48: Retained Earnings | D48: =1 -D47 -> 0.8105934 | E48: =1 -E47 -> 0.74728576 | F48: =1 -F47 -> 0.77341907 | G48: =1 -G47 -> 0.78108018 | H48: =1 -H47 -> 0.79469391 | I48: =1 -I47 -> 0.7643205 | J48: =1 -J47 -> 0.76983466 | K48: =1 -K47 -> 0.78145323 | ... M48: =1 -M47 -> 0.76312328

Sheet Balance Sheet
B6: ="Historical Balance S " &'Data Sheet'!B1 -> Historical Balance S BERGER PAINTS INDIA LTD
B7: Years | D7: ='Data Sheet'!B16 -> 42460 | E7: ='Data Sheet'!C16 -> 42825 | F7: ='Data Sheet'!D16 -> 43190 | G7: ='Data Sheet'!E16 -> 43555 | H7: ='Data Sheet'!F16 -> 43921 | I7: ='Data Sheet'!G16 -> 44286 | J7: ='Data Sheet'!H16 -> 44651 | K7: ='Data Sheet'!I16 -> 45016 | ... M7: ='Data Sheet'!K16 -> 45747
B8: Balance Sheet
B10: ='Data Sheet'!A57 -> Equity Share Capital | D10: ='Data Sheet'!B57 -> 69.35 | E10: ='Data Sheet'!C57 -> 97.1 | F10: ='Data Sheet'!D57 -> 97.1 | G10: ='Data Sheet'!E57 -> 97.11 | H10: ='Data Sheet'!F57 -> 97.12 | I10: ='Data Sheet'!G57 -> 97.13 | J10: ='Data Sheet'!H57 -> 97.13 | K10: ='Data Sheet'!I57 -> 97.14 | ... M10: ='Data Sheet'!K57 -> 116.59
B11: ='Data Sheet'!A58 -> Reserves | D11: ='Data Sheet'!B58 -> 1492.74 | E11: ='Data Sheet'!C58 -> 1804.46 | F11: ='Data Sheet'!D58 -> 2097.41 | G11: ='Data Sheet'!E58 -> 2346.7 | H11: ='Data Sheet'!F58 -> 2563.01 | I11: ='Data Sheet'!G58 -> 3279.74 | J11: ='Data Sheet'!H58 -> 3829.86 | K11: ='Data Sheet'!I58 -> 4396.98 | ... M11: ='Data Sheet'!K58 -> 6037.51
B12: ='Data Sheet'!A59 -> Borrowings | D12: ='Data Sheet'!B59 -> 354.41 | E12: ='Data Sheet'!C59 -> 406.21 | F12: ='Data Sheet'!D59 -> 422.17 | G12: ='Data Sheet'!E59 -> 752.94 | H12: ='Data Sheet'!F59 -> 766.9 | I12: ='Data Sheet'!G59 -> 633.76 | J12: ='Data Sheet'!H59 -> 1013.53 | K12: ='Data Sheet'!I59 -> 1188.97 | ... M12: ='Data Sheet'!K59 -> 670.27
B13: ='Data Sheet'!A60 -> Other Liabilities | D13: ='Data Sheet'!B60 -> 960.29 | E13: ='Data Sheet'!C60 -> 1131.8 | F13: ='Data Sheet'!D60 -> 1325.97 | G13: ='Data Sheet'!E60 -> 1359.92 | H13: ='Data Sheet'!F60 -> 1472.47 | I13: ='Data Sheet'!G60 -> 1907.01 | J13: ='Data Sheet'!H60 -> 2270.97 | K13: ='Data Sheet'!I60 -> 2283.32 | ... M13: ='Data Sheet'!K60 -> 2300.45
B14: Total Liabilities | D14: =SUM(D10:D13) -> 2876.79 | E14: =SUM(E10:E13) -> 3439.57 | F14: =SUM(F10:F13) -> 3942.65 | G14: =SUM(G10:G13) -> 4556.67 | H14: =SUM(H10:H13) -> 4899.5 | I14: =SUM(I10:I13) -> 5917.64 | J14: =SUM(J10:J13) -> 7211.49 | K14: =SUM(K10:K13) -> 7966.41 | ... M14: =SUM(M10:M13) -> 9124.82
B16: ="Fixed " &'Data Sheet'!A62 -> Fixed Net Block | D16: ='Data Sheet'!B62 -> 962.92 | E16: ='Data Sheet'!C62 -> 1135.96 | F16: ='Data Sheet'!D62 -> 1267.17 | G16: ='Data Sheet'!E62 -> 1582.65 | H16: ='Data Sheet'!F62 -> 1915.57 | I16: ='Data Sheet'!G62 -> 2044.22 | J16: ='Data Sheet'!H62 -> 2186.81 | K16: ='Data Sheet'!I62 -> 3331.57 | ... M16: ='Data Sheet'!K62 -> 3676.99
B17: ='Data Sheet'!A63 -> Capital Work in Progress | D17: ='Data Sheet'!B63 -> 51.06 | E17: ='Data Sheet'!C63 -> 62.21 | F17: ='Data Sheet'!D63 -> 97.16 | G17: ='Data Sheet'!E63 -> 169.89 | H17: ='Data Sheet'!F63 -> 178.49 | I17: ='Data Sheet'!G63 -> 106.75 | J17: ='Data Sheet'!H63 -> 605.51 | K17: ='Data Sheet'!I63 -> 110.54 | ... M17: ='Data Sheet'!K63 -> 125.32
B18: ='Data Sheet'!A64 -> Investments | D18: ='Data Sheet'!B64 -> 347.54 | E18: ='Data Sheet'!C64 -> 472.13 | F18: ='Data Sheet'!D64 -> 333.13 | G18: ='Data Sheet'!E64 -> 394.92 | H18: ='Data Sheet'!F64 -> 315.17 | I18: ='Data Sheet'!G64 -> 355.67 | J18: ='Data Sheet'!H64 -> 234.33 | K18: ='Data Sheet'!I64 -> 183.11 | ... M18: ='Data Sheet'!K64 -> 532.63
B19: ='Data Sheet'!A65 -> Other Assets | D19: ='Data Sheet'!B65-SUM(D22:D24) -> 131.31 | E19: ='Data Sheet'!C65-SUM(E22:E24) -> 153.21 | F19: ='Data Sheet'!D65-SUM(F22:F24) -> 340.48 | G19: ='Data Sheet'!E65-SUM(G22:G24) -> 265.72 | H19: ='Data Sheet'!F65-SUM(H22:H24) -> 277.77 | I19: ='Data Sheet'!G65-SUM(I22:I24) -> 335.54 | J19: ='Data Sheet'!H65-SUM(J22:J24) -> 502.38 | K19: ='Data Sheet'!I65-SUM(K22:K24) -> 534.26 | ... M19: ='Data Sheet'!K65-SUM(M22:M24) -> 387.59
B20: Total Non Current Assets | D20: =SUM(D16:D19) -> 1492.83 | E20: =SUM(E16:E19) -> 1823.51 | F20: =SUM(F16:F19) -> 2037.94 | G20: =SUM(G16:G19) -> 2413.18 | H20: =SUM(H16:H19) -> 2687 | I20: =SUM(I16:I19) -> 2842.18 | J20: =SUM(J16:J19) -> 3529.03 | K20: =SUM(K16:K19) -> 4159.48 | ... M20: =SUM(M16:M19) -> 4722.53
B22: ='Data Sheet'!A67 -> Receivables | D22: ='Data Sheet'!B67 -> 545.4 | E22: ='Data Sheet'!C67 -> 578.14 | F22: ='Data Sheet'!D67 -> 692.4 | G22: ='Data Sheet'!E67 -> 671.48 | H22: ='Data Sheet'!F67 -> 714.11 | I22: ='Data Sheet'!G67 -> 1019.72 | J22: ='Data Sheet'!H67 -> 1053.68 | K22: ='Data Sheet'!I67 -> 1243.12 | ... M22: ='Data Sheet'!K67 -> 1535.67
B23: ='Data Sheet'!A68 -> Inventory | D23: ='Data Sheet'!B68 -> 733.23 | E23: ='Data Sheet'!C68 -> 935.47 | F23: ='Data Sheet'!D68 -> 1007.34 | G23: ='Data Sheet'!E68 -> 1233.53 | H23: ='Data Sheet'!F68 -> 1278.46 | I23: ='Data Sheet'!G68 -> 1616.13 | J23: ='Data Sheet'!H68 -> 2315.83 | K23: ='Data Sheet'!I68 -> 2319.12 | ... M23: ='Data Sheet'!K68 -> 2366.14
B24: ='Data Sheet'!A69 -> Cash & Bank | D24: ='Data Sheet'!B69 -> 105.33 | E24: ='Data Sheet'!C69 -> 102.45 | F24: ='Data Sheet'!D69 -> 204.97 | G24: ='Data Sheet'!E69 -> 238.48 | H24: ='Data Sheet'!F69 -> 219.93 | I24: ='Data Sheet'!G69 -> 439.61 | J24: ='Data Sheet'!H69 -> 312.95 | K24: ='Data Sheet'!I69 -> 244.69 | ... M24: ='Data Sheet'!K69 -> 500.48
B25: Total Current Assets | D25: =SUM(D22:D24) -> 1383.96 | E25: =SUM(E22:E24) -> 1616.06 | F25: =SUM(F22:F24) -> 1904.71 | G25: =SUM(G22:G24) -> 2143.49 | H25: =SUM(H22:H24) -> 2212.5 | I25: =SUM(I22:I24) -> 3075.46 | J25: =SUM(J22:J24) -> 3682.46 | K25: =SUM(K22:K24) -> 3806.93 | ... M25: =SUM(M22:M24) -> 4402.29
B27: Total Assets | D27: =D20+D25 -> 2876.79 | E27: =E20+E25 -> 3439.57 | F27: =F20+F25 -> 3942.65 | G27: =G20+G25 -> 4556.67 | H27: =H20+H25 -> 4899.5 | I27: =I20+I25 -> 5917.64 | J27: =J20+J25 -> 7211.49 | K27: =K20+K25 -> 7966.41 | ... M27: =M20+M25 -> 9124.82
B29: Balance | D29: =D14=D27 -> TRUE | E29: =E14=E27 -> TRUE | F29: =F14=F27 -> TRUE | G29: =G14=G27 -> TRUE | H29: =H14=H27 -> TRUE | I29: =I14=I27 -> TRUE | J29: =J14=J27 -> TRUE | K29: =K14=K27 -> TRUE | ... M29: =M14=M27 -> TRUE

Sheet Cash Flow Statement
B6: ="Historical Data of " &'Data Sheet'!B1 -> Historical Data of BERGER PAINTS INDIA LTD
B7: Years | C7: ='Data Sheet'!B16 -> 42460 | D7: ='Data Sheet'!C16 -> 42825 | E7: ='Data Sheet'!D16 -> 43190 | F7: ='Data Sheet'!E16 -> 43555 | G7: ='Data Sheet'!F16 -> 43921 | H7: ='Data Sheet'!G16 -> 44286 | I7: ='Data Sheet'!H16 -> 44651 | J7: ='Data Sheet'!I16 -> 45016 | ... L7: ='Data Sheet'!K16 -> 45747
B9: Operating Activies
B10: ='Data Sheet'!A89 -> Profit from operations | C10: ='Data Sheet'!B89 -> 438 | D10: ='Data Sheet'!C89 -> 524 | E10: ='Data Sheet'!D89 -> 659 | F10: ='Data Sheet'!E89 -> 742 | G10: ='Data Sheet'!F89 -> 827 | H10: ='Data Sheet'!G89 -> 946 | I10: ='Data Sheet'!H89 -> 1087 | ... L10: ='Data Sheet'!K89 -> 1543
B11: ='Data Sheet'!A90 -> Receivables | C11: ='Data Sheet'!B90 -> -101 | D11: ='Data Sheet'!C90 -> -49 | E11: ='Data Sheet'!D90 -> -44 | F11: ='Data Sheet'!E90 -> -34 | G11: ='Data Sheet'!F90 -> -114 | H11: ='Data Sheet'!G90 -> 21 | I11: ='Data Sheet'!H90 -> -43 | ... L11: ='Data Sheet'!K90 -> -212
B12: ='Data Sheet'!A91 -> Inventory | C12: ='Data Sheet'!B91 -> -60 | D12: ='Data Sheet'!C91 -> -24 | E12: ='Data Sheet'!D91 -> -39 | F12: ='Data Sheet'!E91 -> -203 | G12: ='Data Sheet'!F91 -> -72 | H12: ='Data Sheet'!G91 -> -226 | I12: ='Data Sheet'!H91 -> -45 | ... L12: ='Data Sheet'!K91 -> -3
B13: ='Data Sheet'!A92 -> Payables | C13: ='Data Sheet'!B92 -> 136 | D13: ='Data Sheet'!C92 -> 15 | E13: ='Data Sheet'!D92 -> 132 | F13: ='Data Sheet'!E92 -> 92 | G13: ='Data Sheet'!F92 -> 194 | H13: ='Data Sheet'!G92 -> 46 | I13: ='Data Sheet'!H92 -> 63 | ... L13: ='Data Sheet'!K92 -> -37
B14: ='Data Sheet'!A93 -> Loans Advances | C14: ='Data Sheet'!B93 -> 0 | D14: ='Data Sheet'!C93 -> 53 | E14: ='Data Sheet'!D93 -> 0 | F14: ='Data Sheet'!E93 -> 2 | G14: ='Data Sheet'!F93 -> 4 | H14: ='Data Sheet'!G93 -> -1 | I14: ='Data Sheet'!H93 -> -5 | ... L14: ='Data Sheet'!K93 -> -41
B15: ='Data Sheet'!A94 -> Other WC items | C15: ='Data Sheet'!B94 -> 0 | D15: ='Data Sheet'!C94 -> 16 | E15: ='Data Sheet'!D94 -> 65 | F15: ='Data Sheet'!E94 -> 16 | G15: ='Data Sheet'!F94 -> -140 | H15: ='Data Sheet'!G94 -> 69 | I15: ='Data Sheet'!H94 -> -71 | ... L15: ='Data Sheet'!K94 -> 35
B16: ='Data Sheet'!A95 -> Working capital changes | C16: ='Data Sheet'!B95 -> -26 | D16: ='Data Sheet'!C95 -> 12 | E16: ='Data Sheet'!D95 -> 114 | F16: ='Data Sheet'!E95 -> -128 | G16: ='Data Sheet'!F95 -> -128 | H16: ='Data Sheet'!G95 -> -92 | I16: ='Data Sheet'!H95 -> -100 | ... L16: ='Data Sheet'!K95 -> -259
B17: ='Data Sheet'!A96 -> Direct taxes | C17: ='Data Sheet'!B96 -> -102 | D17: ='Data Sheet'!C96 -> -122 | E17: ='Data Sheet'!D96 -> -178 | F17: ='Data Sheet'!E96 -> -220 | G17: ='Data Sheet'!F96 -> -277 | H17: ='Data Sheet'!G96 -> -243 | I17: ='Data Sheet'!H96 -> -263 | ... L17: ='Data Sheet'!K96 -> -308
B18: Total Operating Cash | C18: =SUM(C10:C17) -> 285 | D18: =SUM(D10:D17) -> 425 | E18: =SUM(E10:E17) -> 709 | F18: =SUM(F10:F17) -> 267 | G18: =SUM(G10:G17) -> 294 | H18: =SUM(H10:H17) -> 520 | I18: =SUM(I10:I17) -> 623 | J18: =SUM(J10:J17) -> 627 | ... L18: =SUM(L10:L17) -> 718
B20: Investing Activities
B21: ='Data Sheet'!A98 -> Fixed assets purchased | C21: ='Data Sheet'!B98 -> -243 | D21: ='Data Sheet'!C98 -> -162 | E21: ='Data Sheet'!D98 -> -122 | F21: ='Data Sheet'!E98 -> -269 | G21: ='Data Sheet'!F98 -> -293 | H21: ='Data Sheet'!G98 -> -293 | I21: ='Data Sheet'!H98 -> -435 | ... L21: ='Data Sheet'!K98 -> -748
B22: ='Data Sheet'!A99 -> Fixed assets sold | C22: ='Data Sheet'!B99 -> 1 | D22: ='Data Sheet'!C99 -> 1 | E22: ='Data Sheet'!D99 -> 4 | F22: ='Data Sheet'!E99 -> 4 | G22: ='Data Sheet'!F99 -> 3 | H22: ='Data Sheet'!G99 -> 2 | I22: ='Data Sheet'!H99 -> 4 | ... L22: ='Data Sheet'!K99 -> 4
B23: ='Data Sheet'!A100 -> Investments purchased | C23: ='Data Sheet'!B100 -> -90 | D23: ='Data Sheet'!C100 -> -758 | E23: ='Data Sheet'!D100 -> -148 | F23: ='Data Sheet'!E100 -> -4094 | G23: ='Data Sheet'!F100 -> -1988 | H23: ='Data Sheet'!G100 -> -2130 | I23: ='Data Sheet'!H100 -> -3208 | ... L23: ='Data Sheet'!K100 -> -751
B24: ='Data Sheet'!A101 -> Investments sold | C24: ='Data Sheet'!B101 -> 11 | D24: ='Data Sheet'!C101 -> 720 | E24: ='Data Sheet'!D101 -> 0 | F24: ='Data Sheet'!E101 -> 4056 | G24: ='Data Sheet'!F101 -> 2150 | H24: ='Data Sheet'!G101 -> 2126 | I24: ='Data Sheet'!H101 -> 3297 | ... L24: ='Data Sheet'!K101 -> 788
B25: ='Data Sheet'!A102 -> Interest received | C25: ='Data Sheet'!B102 -> 21 | D25: ='Data Sheet'!C102 -> 15 | E25: ='Data Sheet'!D102 -> 12 | F25: ='Data Sheet'!E102 -> 5 | G25: ='Data Sheet'!F102 -> 6 | H25: ='Data Sheet'!G102 -> 18 | I25: ='Data Sheet'!H102 -> 17 | ... L25: ='Data Sheet'!K102 -> 13
B26: ='Data Sheet'!A103 -> Dividends received | C26: ='Data Sheet'!B103 -> 0 | D26: ='Data Sheet'!C103 -> 0 | E26: ='Data Sheet'!D103 -> 0 | F26: ='Data Sheet'!E103 -> 0 | G26: ='Data Sheet'!F103 -> 0 | H26: ='Data Sheet'!G103 -> 0 | I26: ='Data Sheet'!H103 -> 0 | ... L26: ='Data Sheet'!K103 -> 4
B27: ='Data Sheet'!A104 -> Invest in subsidiaries | C27: ='Data Sheet'!B104 -> -1 | D27: ='Data Sheet'!C104 -> 0 | E27: ='Data Sheet'!D104 -> 0 | F27: ='Data Sheet'!E104 -> 0 | G27: ='Data Sheet'!F104 -> 0 | H27: ='Data Sheet'!G104 -> 0 | I27: ='Data Sheet'!H104 -> 0 | ... L27: ='Data Sheet'!K104 -> 0
B28: ='Data Sheet'!A105 -> Investment in group cos | C28: ='Data Sheet'!B105 -> 0 | D28: ='Data Sheet'!C105 -> 0 | E28: ='Data Sheet'!D105 -> -6 | F28: ='Data Sheet'!E105 -> -57 | G28: ='Data Sheet'!F105 -> 0 | H28: ='Data Sheet'!G105 -> 0 | I28: ='Data Sheet'!H105 -> 0 | ... L28: ='Data Sheet'!K105 -> 0
B29: ='Data Sheet'!A106 -> Redemp n Canc of Shares | C29: ='Data Sheet'!B106 -> 0 | D29: ='Data Sheet'!C106 -> 0 | E29: ='Data Sheet'!D106 -> 0 | F29: ='Data Sheet'!E106 -> 0 | G29: ='Data Sheet'!F106 -> 2 | H29: ='Data Sheet'!G106 -> 0 | I29: ='Data Sheet'!H106 -> 0 | ... L29: ='Data Sheet'!K106 -> 0
B30: ='Data Sheet'!A107 -> Acquisition of companies | C30: ='Data Sheet'!B107 -> 0 | D30: ='Data Sheet'!C107 -> 0 | E30: ='Data Sheet'!D107 -> 0 | F30: ='Data Sheet'!E107 -> 0 | G30: ='Data Sheet'!F107 -> 0 | H30: ='Data Sheet'!G107 -> -41 | I30: ='Data Sheet'!H107 -> 0 | ... L30: ='Data Sheet'!K107 -> 0
B31: ='Data Sheet'!A108 -> Other investing items | C31: ='Data Sheet'!B108 -> 0 | D31: ='Data Sheet'!C108 -> 0 | E31: ='Data Sheet'!D108 -> 0 | F31: ='Data Sheet'!E108 -> 46 | G31: ='Data Sheet'!F108 -> -63 | H31: ='Data Sheet'!G108 -> -61 | I31: ='Data Sheet'!H108 -> 102 | ... L31: ='Data Sheet'!K108 -> 90
B32: Total Investing Cash | C32: =SUM(C21:C31) -> -301 | D32: =SUM(D21:D31) -> -184 | E32: =SUM(E21:E31) -> -260 | F32: =SUM(F21:F31) -> -309 | G32: =SUM(G21:G31) -> -183 | H32: =SUM(H21:H31) -> -379 | I32: =SUM(I21:I31) -> -223 | J32: =SUM(J21:J31) -> -458 | ... L32: =SUM(L21:L31) -> -600
B34: Financing Activities
B35: ='Data Sheet'!A110 -> Proceeds from shares | C35: ='Data Sheet'!B110 -> 0 | D35: ='Data Sheet'!C110 -> 0 | E35: ='Data Sheet'!D110 -> 0 | F35: ='Data Sheet'!E110 -> 0 | G35: ='Data Sheet'!F110 -> 0 | H35: ='Data Sheet'!G110 -> 0 | I35: ='Data Sheet'!H110 -> 0 | ... L35: ='Data Sheet'!K110 -> 0
B36: ='Data Sheet'!A111 -> Proceeds from borrowings | C36: ='Data Sheet'!B111 -> 96 | D36: ='Data Sheet'!C111 -> 10 | E36: ='Data Sheet'!D111 -> 0 | F36: ='Data Sheet'!E111 -> 1131 | G36: ='Data Sheet'!F111 -> 2578 | H36: ='Data Sheet'!G111 -> 3242 | I36: ='Data Sheet'!H111 -> 3538 | ... L36: ='Data Sheet'!K111 -> 8414
B37: ='Data Sheet'!A112 -> Repayment of borrowings | C37: ='Data Sheet'!B112 -> -43 | D37: ='Data Sheet'!C112 -> -24 | E37: ='Data Sheet'!D112 -> -232 | F37: ='Data Sheet'!E112 -> -1053 | G37: ='Data Sheet'!F112 -> -2659 | H37: ='Data Sheet'!G112 -> -3123 | I37: ='Data Sheet'!H112 -> -3437 | ... L37: ='Data Sheet'!K112 -> -8314
B38: ='Data Sheet'!A113 -> Interest paid fin | C38: ='Data Sheet'!B113 -> -42 | D38: ='Data Sheet'!C113 -> -45 | E38: ='Data Sheet'!D113 -> -27 | F38: ='Data Sheet'!E113 -> -16 | G38: ='Data Sheet'!F113 -> -25 | H38: ='Data Sheet'!G113 -> -30 | I38: ='Data Sheet'!H113 -> -31 | ... L38: ='Data Sheet'!K113 -> -61
B39: ='Data Sheet'!A114 -> Dividends paid | C39: ='Data Sheet'!B114 -> -62 | D39: ='Data Sheet'!C114 -> -138 | E39: ='Data Sheet'!D114 -> -108 | F39: ='Data Sheet'!E114 -> -117 | G39: ='Data Sheet'!F114 -> -205 | H39: ='Data Sheet'!G114 -> -211 | I39: ='Data Sheet'!H114 -> -382 | ... L39: ='Data Sheet'!K114 -> -301
B40: ='Data Sheet'!A115 -> Financial liabilities | C40: ='Data Sheet'!B115 -> 0 | D40: ='Data Sheet'!C115 -> 0 | E40: ='Data Sheet'!D115 -> 0 | F40: ='Data Sheet'!E115 -> 0 | G40: ='Data Sheet'!F115 -> 0 | H40: ='Data Sheet'!G115 -> -80 | I40: ='Data Sheet'!H115 -> -118 | ... L40: ='Data Sheet'!K115 -> -100
B41: ='Data Sheet'!A116 -> Other financing items | C41: ='Data Sheet'!B116 -> 0 | D41: ='Data Sheet'!C116 -> 0 | E41: ='Data Sheet'!D116 -> 0 | F41: ='Data Sheet'!E116 -> -27 | G41: ='Data Sheet'!F116 -> 110 | H41: ='Data Sheet'!G116 -> -57 | I41: ='Data Sheet'!H116 -> -49 | ... L41: ='Data Sheet'!K116 -> 0
B42: Total Financing Cash | C42: =SUM(C35:C41) -> -51 | D42: =SUM(D35:D41) -> -197 | E42: =SUM(E35:E41) -> -367 | F42: =SUM(F35:F41) -> -82 | G42: =SUM(G35:G41) -> -201 | H42: =SUM(H35:H41) -> -259 | I42: =SUM(I35:I41) -> -479 | J42: =SUM(J35:J41) -> -280 | ... L42: =SUM(L35:L41) -> -362
B44: Net Cash Flow | C44: =SUM(C18,C32,C42) -> -67 | D44: =SUM(D18,D32,D42) -> 44 | E44: =SUM(E18,E32,E42) -> 82 | F44: =SUM(F18,F32,F42) -> -124 | G44: =SUM(G18,G32,G42) -> -90 | H44: =SUM(H18,H32,H42) -> -118 | I44: =SUM(I18,I32,I42) -> -79 | J44: =SUM(J18,J32,J42) -> -111 | ... L44: =SUM(L18,L32,L42) -> -244

Sheet Ratio Analysis
B6: ="Historical Data of " &'Data Sheet'!$B$1 -> Historical Data of BERGER PAINTS INDIA LTD
B7: Years | C7: ='Data Sheet'!B16 -> 42460 | D7: ='Data Sheet'!C16 -> 42825 | E7: ='Data Sheet'!D16 -> 43190 | F7: ='Data Sheet'!E16 -> 43555 | G7: ='Data Sheet'!F16 -> 43921 | H7: ='Data Sheet'!G16 -> 44286 | I7: ='Data Sheet'!H16 -> 44651 | J7: ='Data Sheet'!I16 -> 45016 | ... L7: ='Data Sheet'!K16 -> 45747 | M7: Trend | N7: Mean | O7: Median
B9: Sales Growth | C9: ='Income Statement'!D11 -> 0 | D9: ='Income Statement'!E11 -> 0.077940376 | E9: ='Income Statement'!F11 -> 0.13476413 | F9: ='Income Statement'!G11 -> 0.17347597 | G9: ='Income Statement'!H11 -> 0.050143025 | H9: ='Income Statement'!I11 -> 0.070968076 | I9: ='Income Statement'!J11 -> 0.28517262 | J9: ='Income Statement'!K11 -> 0.20612935 | ... L9: ='Income Statement'!M11 -> 0.030877085 | N9: =IFERROR(AVERAGE(D9:L9), "") -> 0.12102085 | O9: =MEDIAN(D9:L9) -> 0.077940376
B10: EBITDA Growth | C10: =IFERROR('Income Statement'!D22/'Income Statement'!B22-1, "-") -> - | D10: ='Income Statement'!E22/'Income Statement'!D22-1 -> 0.11687167 | E10: ='Income Statement'!F22/'Income Statement'!E22-1 -> 0.13447426 | F10: ='Income Statement'!G22/'Income Statement'!F22-1 -> 0.15424595 | G10: ='Income Statement'!H22/'Income Statement'!G22-1 -> 0.12072045 | H10: ='Income Statement'!I22/'Income Statement'!H22-1 -> 0.10776996 | I10: ='Income Statement'!J22/'Income Statement'!I22-1 -> 0.12390293 | J10: ='Income Statement'!K22/'Income Statement'!J22-1 -> 0.11350253 | K10: ='Income Statement'!L22/'Income Statement'!K22-1 -> 0.2334986 | L10: ='Income Statement'!M22/'Income Statement'!L22-1 -> 0.038240925 | N10: =IFERROR(AVERAGE(D10:L10), "") -> 0.12702525 | O10: =MEDIAN(D10:L10) -> 0.12072045
B11: EBIT Growth | C11: =IFERROR('Income Statement'!D23/'Income Statement'!B23-1, "-") -> - | D11: ='Income Statement'!E28/'Income Statement'!D28 - 1 -> 0.11946833 | E11: ='Income Statement'!F28/'Income Statement'!E28 - 1 -> 0.13269863 | F11: ='Income Statement'!G28/'Income Statement'!F28 - 1 -> 0.11683528 | G11: ='Income Statement'!H28/'Income Statement'!G28 - 1 -> 0.1321416 | H11: ='Income Statement'!I28/'Income Statement'!H28 - 1 -> 0.10811613 | I11: ='Income Statement'!J28/'Income Statement'!I28 - 1 -> 0.13130946 | J11: ='Income Statement'!K28/'Income Statement'!J28 - 1 -> 0.10633702 | K11: ='Income Statement'!L28/'Income Statement'!K28 - 1 -> 0.23064732 | L11: ='Income Statement'!M28/'Income Statement'!L28 - 1 -> 0.033492119 | N11: =IFERROR(AVERAGE(D11:L11), "") -> 0.12344954 | O11: =MEDIAN(D11:L11) -> 0.11946833
B12: Net Profit | C12: =IFERROR('Income Statement'!D24/'Income Statement'!B24-1, "-") -> - | D12: ='Income Statement'!E40/'Income Statement'!D40 - 1 -> 0.11293553 | E12: ='Income Statement'!F40/'Income Statement'!E40 - 1 -> 0.14723817 | F12: ='Income Statement'!G40/'Income Statement'!F40 - 1 -> 0.092613239 | G12: ='Income Statement'!H40/'Income Statement'!G40 - 1 -> 0.23477136 | H12: ='Income Statement'!I40/'Income Statement'!H40 - 1 -> 0.10882203 | I12: ='Income Statement'!J40/'Income Statement'!I40 - 1 -> 0.13367246 | J12: ='Income Statement'!K40/'Income Statement'!J40 - 1 -> 0.087265611 | K12: ='Income Statement'!L40/'Income Statement'!K40 - 1 -> 0.25059936 | L12: ='Income Statement'!M40/'Income Statement'!L40 - 1 -> 0.051467571 | N12: =IFERROR(AVERAGE(D12:L12), "") -> 0.13548726 | O12: =MEDIAN(D12:L12) -> 0.11293553
B13: Dividend Growth | C13: =IFERROR('Income Statement'!D25/'Income Statement'!B25-1, "-") -> - | D13: ='Income Statement'!E46/'Income Statement'!D46 - 1 -> 0.48479784 | E13: ='Income Statement'!F46/'Income Statement'!E46 - 1 -> 0.028601695 | F13: ='Income Statement'!G46/'Income Statement'!F46 - 1 -> 0.055488816 | G13: ='Income Statement'!H46/'Income Statement'!G46 - 1 -> 0.15788666 | H13: ='Income Statement'!I46/'Income Statement'!H46 - 1 -> 0.27275423 | I13: ='Income Statement'!J46/'Income Statement'!I46 - 1 -> 0.10714811 | J13: ='Income Statement'!K46/'Income Statement'!J46 - 1 -> 0.032292705 | K13: ='Income Statement'!L46/'Income Statement'!K46 - 1 -> 0.31251407 | L13: ='Income Statement'!M46/'Income Statement'!L46 - 1 -> 0.085709385 | N13: =IFERROR(AVERAGE(D13:L13), "") -> 0.17079928 | O13: =MEDIAN(D13:L13) -> 0.10714811
N14: =IFERROR(AVERAGE(D14:L14), "")
B15: Gross Margin | C15: ='Income Statement'!D17 -> 0.32482773 | D15: ='Income Statement'!E17 -> 0.33884123 | E15: ='Income Statement'!F17 -> 0.33347465 | F15: ='Income Statement'!G17 -> 0.30580713 | G15: ='Income Statement'!H17 -> 0.31973414 | H15: ='Income Statement'!I17 -> 0.33424568 | I15: ='Income Statement'!J17 -> 0.28416372 | J15: ='Income Statement'!K17 -> 0.26984985 | ... L15: ='Income Statement'!M17 -> 0.32813384 | N15: =IFERROR(AVERAGE(D15:L15), "") -> 0.31424585 | O15: =IFERROR(MEDIAN(C15:L15), "") -> 0.32228094
B16: EBITDA Margin | C16: ='Income Statement'!D23 -> 0.21754162 | D16: ='Income Statement'!E23 -> 0.22539843 | E16: ='Income Statement'!F23 -> 0.22534085 | F16: ='Income Statement'!G23 -> 0.22164814 | G16: ='Income Statement'!H23 -> 0.23654455 | H16: ='Income Statement'!I23 -> 0.24467297 | I16: ='Income Statement'!J23 -> 0.21397022 | J16: ='Income Statement'!K23 -> 0.197538 | ... L16: ='Income Statement'!M23 -> 0.23157446 | N16: =IFERROR(AVERAGE(D16:L16), "") -> 0.22517996 | O16: =IFERROR(MEDIAN(C16:L16), "") -> 0.22536964
B17: EBIT Margin | C17: ='Income Statement'!D29 -> 0.194182 | D17: ='Income Statement'!E29 -> 0.20166291 | E17: ='Income Statement'!F29 -> 0.20129585 | F17: ='Income Statement'!G29 -> 0.19157981 | G17: ='Income Statement'!H29 -> 0.20653898 | H17: ='Income Statement'!I29 -> 0.21370308 | I17: ='Income Statement'!J29 -> 0.18811817 | J17: ='Income Statement'!K29 -> 0.17255371 | ... L17: ='Income Statement'!M29 -> 0.20089461 | N17: =IFERROR(AVERAGE(D17:L17), "") -> 0.19741482 | O17: =IFERROR(MEDIAN(C17:L17), "") -> 0.20064045
B18: EBT Margin | C18: ='Income Statement'!D35 -> 0.18772229 | D18: ='Income Statement'!E35 -> 0.19809984 | E18: ='Income Statement'!F35 -> 0.19654337 | F18: ='Income Statement'!G35 -> 0.18378682 | G18: ='Income Statement'!H35 -> 0.19914952 | H18: ='Income Statement'!I35 -> 0.20723452 | I18: ='Income Statement'!J35 -> 0.18232939 | J18: ='Income Statement'!K35 -> 0.1631639 | ... L18: ='Income Statement'!M35 -> 0.19541418 | N18: =IFERROR(AVERAGE(D18:L18), "") -> 0.19101339 | O18: =IFERROR(MEDIAN(C18:L18), "") -> 0.19440659
B19: Net Profit Margin | C19: ='Income Statement'!D41 -> 0.14305842 | D19: ='Income Statement'!E41 -> 0.14770278 | E19: ='Income Statement'!F41 -> 0.14932643 | F19: ='Income Statement'!G41 -> 0.13903653 | G19: ='Income Statement'!H41 -> 0.1634809 | H19: ='Income Statement'!I41 -> 0.16925923 | I19: ='Income Statement'!J41 -> 0.14930642 | J19: ='Income Statement'!K41 -> 0.13459231 | ... L19: ='Income Statement'!M41 -> 0.1620084 | N19: =IFERROR(AVERAGE(D19:L19), "") -> 0.15261654 | O19: =IFERROR(MEDIAN(C19:L19), "") -> 0.14931642
N20: =IFERROR(AVERAGE(D20:L20), "") | O20: =IFERROR(MEDIAN(C20:L20), "")
B21: Sales Expenses% of Sales | C21: ='Income Statement'!D14 -> 0.67517227 | D21: ='Income Statement'!E14 -> 0.66115877 | E21: ='Income Statement'!F14 -> 0.66652535 | F21: ='Income Statement'!G14 -> 0.69419287 | G21: ='Income Statement'!H14 -> 0.68026586 | H21: ='Income Statement'!I14 -> 0.66575432 | I21: ='Income Statement'!J14 -> 0.71583628 | J21: ='Income Statement'!K14 -> 0.73015015 | ... L21: ='Income Statement'!M14 -> 0.67186616 | N21: =IFERROR(AVERAGE(D21:L21), "") -> 0.68575415 | O21: =IFERROR(MEDIAN(C21:L21), "") -> 0.67771906
B22: Depriciation as % of Sales | C22: ='Income Statement'!D26 -> 0.023359617 | D22: ='Income Statement'!E26 -> 0.023735515 | E22: ='Income Statement'!F26 -> 0.024045004 | F22: ='Income Statement'!G26 -> 0.030068329 | G22: ='Income Statement'!H26 -> 0.030005561 | H22: ='Income Statement'!I26 -> 0.030969888 | I22: ='Income Statement'!J26 -> 0.025852053 | J22: ='Income Statement'!K26 -> 0.024984292 | ... L22: ='Income Statement'!M26 -> 0.030679853 | N22: =IFERROR(AVERAGE(D22:L22), "") -> 0.027765133 | O22: =IFERROR(MEDIAN(C22:L22), "") -> 0.02769888
B23: Operating Income as a % of Sales | C23: ='Income Statement'!D29 -> 0.194182 | D23: ='Income Statement'!E29 -> 0.20166291 | E23: ='Income Statement'!F29 -> 0.20129585 | F23: ='Income Statement'!G29 -> 0.19157981 | G23: ='Income Statement'!H29 -> 0.20653898 | H23: ='Income Statement'!I29 -> 0.21370308 | I23: ='Income Statement'!J29 -> 0.18811817 | J23: ='Income Statement'!K29 -> 0.17255371 | ... L23: ='Income Statement'!M29 -> 0.20089461 | N23: =IFERROR(AVERAGE(D23:L23), "") -> 0.19741482 | O23: =IFERROR(MEDIAN(C23:L23), "") -> 0.20064045
N24: =IFERROR(AVERAGE(D24:L24), "") | O24: =IFERROR(MEDIAN(C24:L24), "")
B25: Return on Capital Employed | C25: ='Income Statement'!D28/SUM('Balance Sheet'!D10:D12) -> 0.42788938 | D25: ='Income Statement'!E28/SUM('Balance Sheet'!E10:E12) -> 0.39779527 | E25: ='Income Statement'!F28/SUM('Balance Sheet'!F10:F12) -> 0.39738906 | F25: ='Income Statement'!G28/SUM('Balance Sheet'!G10:G12) -> 0.36328459 | G25: ='Income Statement'!H28/SUM('Balance Sheet'!H10:H12) -> 0.3836529 | H25: ='Income Statement'!I28/SUM('Balance Sheet'!I10:I12) -> 0.36326961 | I25: ='Income Statement'!J28/SUM('Balance Sheet'!J10:J12) -> 0.33361873 | J25: ='Income Statement'!K28/SUM('Balance Sheet'!K10:K12) -> 0.3208677 | ... L25: ='Income Statement'!M28/SUM('Balance Sheet'!M10:M12) -> 0.33985115 | N25: =IFERROR(AVERAGE(D25:L25), "") -> 0.36285339 | O25: =IFERROR(MEDIAN(C25:L25), "") -> 0.36461806
B26: Retained Earnings% | C26: ='Income Statement'!D48 -> 0.8105934 | D26: ='Income Statement'!E48 -> 0.74728576 | E26: ='Income Statement'!F48 -> 0.77341907 | F26: ='Income Statement'!G48 -> 0.78108018 | G26: ='Income Statement'!H48 -> 0.79469391 | H26: ='Income Statement'!I48 -> 0.7643205 | I26: ='Income Statement'!J48 -> 0.76983466 | J26: ='Income Statement'!K48 -> 0.78145323 | ... L26: ='Income Statement'!M48 -> 0.76312328 | N26: =IFERROR(AVERAGE(D26:L26), "") -> 0.77175826 | O26: =IFERROR(MEDIAN(C26:L26), "") -> 0.7720164
B27: Return on Equity% | C27: ='Income Statement'!D40/SUM('Balance Sheet'!D10:D11) -> 0.38675749 | D27: ='Income Statement'!E40/SUM('Balance Sheet'!E10:E11) -> 0.35359389 | E27: ='Income Statement'!F40/SUM('Balance Sheet'!F10:F11) -> 0.35150444 | F27: ='Income Statement'!G40/SUM('Balance Sheet'!G10:G11) -> 0.34487951 | G27: ='Income Statement'!H40/SUM('Balance Sheet'!H10:H11) -> 0.39121772 | H27: ='Income Statement'!I40/SUM('Balance Sheet'!I10:I11) -> 0.34171881 | I27: ='Income Statement'!J40/SUM('Balance Sheet'!J10:J11) -> 0.33312792 | J27: ='Income Statement'!K40/SUM('Balance Sheet'!K10:K11) -> 0.31649133 | ... L27: ='Income Statement'!M40/SUM('Balance Sheet'!M10:M11) -> 0.30391771 | N27: =IFERROR(AVERAGE(D27:L27), "") -> 0.34079386 | O27: =IFERROR(MEDIAN(C27:L27), "") -> 0.34329916
B28: Self Sustain Growth Rate | C28: =C26*C27 -> 0.31350306 | D28: =D26*D27 -> 0.26423568 | E28: =E26*E27 -> 0.27186023 | F28: =F26*F27 -> 0.26937855 | G28: =G26*G27 -> 0.31089834 | H28: =H26*H27 -> 0.26118269 | I28: =I26*I27 -> 0.25645342 | J28: =J26*J27 -> 0.24732317 | ... L28: =L26*L27 -> 0.23192668 | N28: =IFERROR(AVERAGE(D28:L28), "") -> 0.26312174 | O28: =IFERROR(MEDIAN(C28:L28), "") -> 0.26270919
B29: Interest Covering Ratio | C29: ='Income Statement'!D28/'Income Statement'!D31 -> 30.060484 | D29: ='Income Statement'!E28/'Income Statement'!E31 -> 56.598027 | E29: ='Income Statement'!F28/'Income Statement'!F31 -> 42.356008 | F29: ='Income Statement'!G28/'Income Statement'!G31 -> 24.583616 | G29: ='Income Statement'!H28/'Income Statement'!H31 -> 27.950468 | H29: ='Income Statement'!I28/'Income Statement'!I31 -> 33.037188 | I29: ='Income Statement'!J28/'Income Statement'!J31 -> 32.497043 | J29: ='Income Statement'!K28/'Income Statement'!K31 -> 18.376701 | ... L29: ='Income Statement'!M28/'Income Statement'!M31 -> 36.656709 | N29: =IFERROR(AVERAGE(D29:L29), "") -> 33.414942 | O29: =IFERROR(MEDIAN(C29:L29), "") -> 31.278763
B31: Debtor Turnover Ratio | C31: ='Income Statement'!D10/'Balance Sheet'!D22 -> 7.7431243 | D31: ='Income Statement'!E10/'Balance Sheet'!E22 -> 7.8739579 | E31: ='Income Statement'!F10/'Balance Sheet'!F22 -> 7.4606153 | F31: ='Income Statement'!G10/'Balance Sheet'!G22 -> 9.0276107 | G31: ='Income Statement'!H10/'Balance Sheet'!H22 -> 8.9143409 | H31: ='Income Statement'!I10/'Balance Sheet'!I22 -> 6.6857471 | I31: ='Income Statement'!J10/'Balance Sheet'!J22 -> 8.3154089 | J31: ='Income Statement'!K10/'Balance Sheet'!K22 -> 8.5010618 | ... L31: ='Income Statement'!M10/'Balance Sheet'!M22 -> 7.5177024 | N31: =IFERROR(AVERAGE(D31:L31), "") -> 8.0997371 | O31: =IFERROR(MEDIAN(C31:L31), "") -> 8.0946834
B32: Creditor Turnover Ratio | C32: ='Income Statement'!D10/'Balance Sheet'!D13 -> 4.397734 | D32: ='Income Statement'!E10/'Balance Sheet'!E13 -> 4.0221329 | E32: ='Income Statement'!F10/'Balance Sheet'!F13 -> 3.8958121 | F32: ='Income Statement'!G10/'Balance Sheet'!G13 -> 4.4575122 | G32: ='Income Statement'!H10/'Balance Sheet'!H13 -> 4.3232256 | H32: ='Income Statement'!I10/'Balance Sheet'!I13 -> 3.5750153 | I32: ='Income Statement'!J10/'Balance Sheet'!J13 -> 3.8581663 | J32: ='Income Statement'!K10/'Balance Sheet'!K13 -> 4.6282781 | ... L32: ='Income Statement'!M10/'Balance Sheet'!M13 -> 5.0184573 | N32: =IFERROR(AVERAGE(D32:L32), "") -> 4.309788 | O32: =IFERROR(MEDIAN(C32:L32), "") -> 4.3604798
B33: Inventory Turnover Ratio | C33: ='Income Statement'!D10/'Balance Sheet'!D23 -> 5.7595843 | D33: ='Income Statement'!E10/'Balance Sheet'!E23 -> 4.8662704 | E33: ='Income Statement'!F10/'Balance Sheet'!F23 -> 5.1280898 | F33: ='Income Statement'!G10/'Balance Sheet'!G23 -> 4.914238 | G33: ='Income Statement'!H10/'Balance Sheet'!H23 -> 4.9792876 | H33: ='Income Statement'!I10/'Balance Sheet'!I23 -> 4.2184663 | I33: ='Income Statement'!J10/'Balance Sheet'!J23 -> 3.7834297 | J33: ='Income Statement'!K10/'Balance Sheet'!K23 -> 4.5568319 | ... L33: ='Income Statement'!M10/'Balance Sheet'!M23 -> 4.8791323 | N33: =IFERROR(AVERAGE(D33:L33), "") -> 4.7181799 | O33: =IFERROR(MEDIAN(C33:L33), "") -> 4.8966851
B34: Fixed Assets Turnover Ratio | C34: ='Income Statement'!D10/'Balance Sheet'!D16 -> 4.3857226 | D34: ='Income Statement'!E10/'Balance Sheet'!E16 -> 4.0074034 | E34: ='Income Statement'!F10/'Balance Sheet'!F16 -> 4.076588 | F34: ='Income Statement'!G10/'Balance Sheet'!G16 -> 3.8301962 | G34: ='Income Statement'!H10/'Balance Sheet'!H16 -> 3.3231988 | H34: ='Income Statement'!I10/'Balance Sheet'!I16 -> 3.3350569 | I34: ='Income Statement'!J10/'Balance Sheet'!J16 -> 4.006649 | J34: ='Income Statement'!K10/'Balance Sheet'!K16 -> 3.17203 | ... L34: ='Income Statement'!M10/'Balance Sheet'!M16 -> 3.1397175 | N34: =IFERROR(AVERAGE(D34:L34), "") -> 3.565643 | O34: =IFERROR(MEDIAN(C34:L34), "") -> 3.5826265
B35: Capital Turnover Ratio | C35: ='Income Statement'!D10/SUM('Balance Sheet'!D10:D11) -> 2.7034934 | D35: ='Income Statement'!E10/SUM('Balance Sheet'!E10:E11) -> 2.3939555 | E35: ='Income Statement'!F10/SUM('Balance Sheet'!F10:F11) -> 2.3539332 | F35: ='Income Statement'!G10/SUM('Balance Sheet'!G10:G11) -> 2.4804956 | G35: ='Income Statement'!H10/SUM('Balance Sheet'!H10:H11) -> 2.3930485 | H35: ='Income Statement'!I10/SUM('Balance Sheet'!I10:I11) -> 2.018908 | I35: ='Income Statement'!J10/SUM('Balance Sheet'!J10:J11) -> 2.2311694 | J35: ='Income Statement'!K10/SUM('Balance Sheet'!K10:K11) -> 2.3514815 | ... L35: ='Income Statement'!M10/SUM('Balance Sheet'!M10:M11) -> 1.875938 | N35: =IFERROR(AVERAGE(D35:L35), "") -> 2.2423236 | O35: =IFERROR(MEDIAN(C35:L35), "") -> 2.3527074
N36: =IFERROR(AVERAGE(D36:L36), "") | O36: =IFERROR(MEDIAN(C36:L36), "")
B37: Debtor Days | C37: =365/C31 -> 47.138595 | D37: =365/D31 -> 46.355341 | E37: =365/E31 -> 48.923579 | F37: =365/F31 -> 40.431518 | G37: =365/G31 -> 40.945259 | H37: =365/H31 -> 54.593749 | I37: =365/I31 -> 43.894414 | J37: =365/J31 -> 42.935813 | ... L37: =365/L31 -> 48.552068 | N37: =IFERROR(AVERAGE(D37:L37), "") -> 45.451971 | O37: =IFERROR(MEDIAN(C37:L37), "") -> 45.124877
B38: Creditor Days | C38: =365/C32 -> 82.997289 | D38: =365/D32 -> 90.747872 | E38: =365/E32 -> 93.69035 | F38: =365/F32 -> 81.88424 | G38: =365/G32 -> 84.427701 | H38: =365/H32 -> 102.09746 | I38: =365/I32 -> 94.604527 | J38: =365/J32 -> 78.863022 | ... L38: =365/L32 -> 72.731515 | N38: =IFERROR(AVERAGE(D38:L38), "") -> 85.767597 | O38: =IFERROR(MEDIAN(C38:L38), "") -> 83.712495
B39: Inventory Days | C39: =365/C33 -> 63.372629 | D39: =365/D33 -> 75.006107 | E39: =365/E33 -> 71.1766 | F39: =365/F33 -> 74.273977 | G39: =365/G33 -> 73.303659 | H39: =365/H33 -> 86.524336 | I39: =365/I33 -> 96.473314 | J39: =365/J33 -> 80.099509 | ... L39: =365/L33 -> 74.808384 | N39: =IFERROR(AVERAGE(D39:L39), "") -> 78.07855 | O39: =IFERROR(MEDIAN(C39:L39), "") -> 74.541181
B40: Cash Conversion Cycle | C40: =(C37+C39)-C38 -> 27.513935 | D40: =(D37+D39)-D38 -> 30.613576 | E40: =(E37+E39)-E38 -> 26.40983 | F40: =(F37+F39)-F38 -> 32.821255 | G40: =(G37+G39)-G38 -> 29.821217 | H40: =(H37+H39)-H38 -> 39.020622 | I40: =(I37+I39)-I38 -> 45.763201 | J40: =(J37+J39)-J38 -> 44.1723 | ... L40: =(L37+L39)-L38 -> 50.628937 | N40: =IFERROR(AVERAGE(D40:L40), "") -> 37.762924 | O40: =IFERROR(MEDIAN(C40:L40), "") -> 35.920938
N41: =IFERROR(AVERAGE(D41:L41), "") | O41: =IFERROR(MEDIAN(C41:L41), "")
B42: CFO/Sales | C42: ='Cash Flow Statement'!$C$18/'Income Statement'!D10 -> 0.06748597 | D42: ='Cash Flow Statement'!$C$18/'Income Statement'!E10 -> 0.062606403 | E42: ='Cash Flow Statement'!$C$18/'Income Statement'!F10 -> 0.055171292 | F42: ='Cash Flow Statement'!$C$18/'Income Statement'!G10 -> 0.047015273 | G42: ='Cash Flow Statement'!$C$18/'Income Statement'!H10 -> 0.044770352 | H42: ='Cash Flow Statement'!$C$18/'Income Statement'!I10 -> 0.041803629 | I42: ='Cash Flow Statement'!$C$18/'Income Statement'!J10 -> 0.032527637 | J42: ='Cash Flow Statement'!$C$18/'Income Statement'!K10 -> 0.026968614 | ... L42: ='Cash Flow Statement'!$C$18/'Income Statement'!M10 -> 0.024686631 | N42: =IFERROR(AVERAGE(D42:L42), "") -> 0.040110968 | O42: =IFERROR(MEDIAN(C42:L42), "") -> 0.04328699
B43: CFO/Total Assests | C43: ='Cash Flow Statement'!$C$18/'Balance Sheet'!D27 -> 0.099068754 | D43: ='Cash Flow Statement'!$C$18/'Balance Sheet'!E27 -> 0.082859195 | E43: ='Cash Flow Statement'!$C$18/'Balance Sheet'!F27 -> 0.072286406 | F43: ='Cash Flow Statement'!$C$18/'Balance Sheet'!G27 -> 0.062545675 | G43: ='Cash Flow Statement'!$C$18/'Balance Sheet'!H27 -> 0.058169201 | H43: ='Cash Flow Statement'!$C$18/'Balance Sheet'!I27 -> 0.048161091 | I43: ='Cash Flow Statement'!$C$18/'Balance Sheet'!J27 -> 0.039520266 | J43: ='Cash Flow Statement'!$C$18/'Balance Sheet'!K27 -> 0.035775211 | ... L43: ='Cash Flow Statement'!$C$18/'Balance Sheet'!M27 -> 0.031233493 | N43: =IFERROR(AVERAGE(D43:L43), "") -> 0.051623297 | O43: =IFERROR(MEDIAN(C43:L43), "") -> 0.053165146
B44: CFO/Total Debt | C44: ='Cash Flow Statement'!$C$18/'Balance Sheet'!D12 -> 0.80415338 | D44: ='Cash Flow Statement'!$C$18/'Balance Sheet'!E12 -> 0.70160754 | E44: ='Cash Flow Statement'!$C$18/'Balance Sheet'!F12 -> 0.6750835 | F44: ='Cash Flow Statement'!$C$18/'Balance Sheet'!G12 -> 0.37851622 | G44: ='Cash Flow Statement'!$C$18/'Balance Sheet'!H12 -> 0.37162603 | H44: ='Cash Flow Statement'!$C$18/'Balance Sheet'!I12 -> 0.44969705 | I44: ='Cash Flow Statement'!$C$18/'Balance Sheet'!J12 -> 0.28119543 | J44: ='Cash Flow Statement'!$C$18/'Balance Sheet'!K12 -> 0.23970327 | ... L44: ='Cash Flow Statement'!$C$18/'Balance Sheet'!M12 -> 0.42520178 | N44: =IFERROR(AVERAGE(D44:L44), "") -> 0.43344124 | O44: =IFERROR(MEDIAN(C44:L44), "") -> 0.401859
O45: =IFERROR(MEDIAN(C45:L45), "")

Sheet Forecasting
B2: Weight | C2: Years | D2: Sales | E2: Growth
B3: 1 | C3: 42460 | D3: 4223.1 | E3: -
B4: 2 | C4: 42825 | D4: 4552.25 | E4: =D4/D3-1 -> 0.077940376
B5: 3 | C5: 43190 | D5: 5165.73 | E5: =D5/D4-1 -> 0.13476413
B6: 4 | C6: 43555 | D6: 6061.86 | E6: =D6/D5-1 -> 0.17347597
B7: 5 | C7: 43921 | D7: 6365.82 | E7: =D7/D6-1 -> 0.050143025
B8: 6 | C8: 44286 | D8: 6817.59 | E8: =D8/D7-1 -> 0.070968076
B9: 7 | C9: 44651 | D9: 8761.78 | E9: =D9/D8-1 -> 0.28517262
B10: 8 | C10: 45016 | D10: 10567.84 | E10: =D10/D9-1 -> 0.20612935
B11: 9 | C11: 45382 | D11: 11198.92 | E11: =D11/D10-1 -> 0.059717028
B12: 10 | C12: 45747 | D12: 11544.71 | E12: =D12/D11-1 -> 0.030877085
B13: 11 | C13: 2026 | D13: =FORECAST(B13,$D$3:$D$12,$B$3:$B$12) -> 12458.735 | E13: =D13/D12-1 -> 0.079172654
B14: 12 | C14: =C13+1 -> 2027 | D14: =FORECAST(B14,$D$3:$D$12,$B$3:$B$12) -> 13355.604 | E14: =D14/D13-1 -> 0.071987101
B15: 13 | C15: =C14+1 -> 2028 | D15: =FORECAST(B15,$D$3:$D$12,$B$3:$B$12) -> 14252.472 | E15: =D15/D14-1 -> 0.067152955
B16: 14 | C16: =C15+1 -> 2029 | D16: =FORECAST(B16,$D$3:$D$12,$B$3:$B$12) -> 15149.34 | E16: =D16/D15-1 -> 0.062927207
B17: 15 | C17: =C16+1 -> 2030 | D17: =FORECAST(B17,$D$3:$D$12,$B$3:$B$12) -> 16046.208 | E17: =D17/D16-1 -> 0.059201803
G20: SUMMARY OUTPUT
B21: 1st Method Average | C21: =AVERAGE(E4:E12) -> 0.12102085
B22: 2nd Method Geo Mean | C22: =_xlfn.RRI(B12,D3,D12) -> 0.10579639 | G22: Regression Statistics
B23: Another Way | C23: =(D12/D3)^(1/B12)-1 -> 0.10579639 | G23: Multiple R | H23: 0.97550595
B24: 3rd Method Regression | G24: R Square | H24: 0.95161186
B25: 11 | C25: 2026 | D25: 12458.735 | E25: 0.079172654 | G25: Adjusted R Square | H25: 0.94556335
B26: 12 | C26: 2027 | D26: 13355.604 | E26: 0.071987101 | G26: Standard Error | H26: 649.45662
B27: 13 | C27: 2028 | D27: 14252.472 | E27: 0.067152955 | G27: Observations | H27: 10
B28: 14 | C28: 2029 | D28: 15149.34 | E28: 0.062927207
B29: 15 | C29: 2030 | D29: 16046.208 | E29: 0.059201803 | G29: ANOVA
H30: df | I30: SS | J30: MS | K30: F | L30: Significance F
G31: Regression | H31: 1 | I31: 66360743 | J31: 66360743 | K31: 157.32978 | L31: 1.5289648e-06
G32: Residual | H32: 8 | I32: 3374351.3 | J32: 421793.91
G33: Total | H33: 9 | I33: 69735094
H35: Coefficients | I35: Standard Error | J35: t Stat | K35: P-value | L35: Lower 95% | M35: Upper 95% | N35: Lower 95.0% | O35: Upper 95.0%
G36: Intercept | H36: 2593.1847 | I36: 443.66334 | J36: 5.8449379 | K36: 0.00038498093 | L36: 1570.0952 | M36: 3616.2742 | N36: 1570.0952 | O36: 3616.2742
G37: Weight | H37: 896.86824 | I37: 71.502821 | J37: 12.543117 | K37: 1.5289648e-06 | L37: 731.98244 | M37: 1061.754 | N37: 731.98244 | O37: 1061.754

Sheet WACC
F6: Beta = “how jumpy” the stock is
B7: Weighted Average Cost of Capital
B9: All Figures are in INR unless Stated otherwise
B11: Peer Comps
J12: Debt/ | K12: Debt/ | L12: Levered/ | M12: Unlevered/
B13: Name of the Comp | F13: Country | G13: Total Debt | H13: Total Equity | I13: Tax Rate 1 | J13: Equity | K13: Capital | L13: Beta 2 | M13: Beta 3
B15: Asian Paints | F15: India | G15: ='Peer Companies'!F5 -> 2290.29 | H15: ='Peer Companies'!E5 -> 223119.01 | I15: 0.3 | J15: =G15/H15 -> 0.010264881 | K15: =G15/(H15+G15) -> 0.010160583 | L15: 0.52 | M15: =L15/(1+(1-I15)*J15) -> 0.51629024 | N15: LB/(1+(1 - Tax)* Debt/Equity)
B16: Berger Paints | F16: India | G16: ='Peer Companies'!F6 -> 670.27 | H16: ='Peer Companies'!E6 -> 62282.09 | I16: 0.3 | J16: =G16/H16 -> 0.010761842 | K16: =G16/(H16+G16) -> 0.010647258 | L16: ='Beta Calculation'!N10 -> 0.89971614 | M16: =L16/(1+(1-I16)*J16) -> 0.892989
B17: Kansai Nerolac | F17: India | G17: ='Peer Companies'!F7 -> 296.39 | H17: ='Peer Companies'!E7 -> 19800.51 | I17: 0.3 | J17: =G17/H17 -> 0.014968806 | K17: =G17/(H17+G17) -> 0.014748046 | L17: 0.77 | M17: =L17/(1+(1-I17)*J17) -> 0.76201548
B18: Akzo Nobel | F18: India | G18: ='Peer Companies'!F8 -> 62.1 | H18: ='Peer Companies'!E8 -> 15141.96 | I18: 0.3 | J18: =G18/H18 -> 0.0041011864 | K18: =G18/(H18+G18) -> 0.0040844353 | L18: 0.32 | M18: =L18/(1+(1-I18)*J18) -> 0.31908396
B19: Indigo Paints | F19: India | G19: ='Peer Companies'!F9 -> 19.7 | H19: ='Peer Companies'!E9 -> 4893.42 | I19: 0.3 | J19: =G19/H19 -> 0.0040258143 | K19: =G19/(H19+G19) -> 0.0040096721 | L19: 0.9 | M19: =L19/(1+(1-I19)*J19) -> 0.89747086
H21: Average | I21: =AVERAGE(I15:I19) -> 0.3 | J21: =AVERAGE(J15:J19) -> 0.0088245059 | K21: =AVERAGE(K15:K19) -> 0.0087299989 | L21: =AVERAGE(L15:L19) -> 0.68194323 | M21: =AVERAGE(M15:M19) -> 0.67756991
H22: Median | I22: =MEDIAN(I15:I19) -> 0.3 | J22: =MEDIAN(J15:J19) -> 0.010264881 | K22: =MEDIAN(K15:K19) -> 0.010160583 | L22: =MEDIAN(L15:L19) -> 0.77 | M22: =MEDIAN(M15:M19) -> 0.76201548
B25: Cost of Debt | I25: Cost of Equity
B26: Pre-Tax Cost of Debt | G26: =63/670 -> 0.094029851 | I26: Risk Free Rate | M26: 0.06514
B27: Tax Rate | G27: 0.3 | I27: Equity Risk Premium | M27: ='Market Returns'!F5-WACC!M26 -> 0.11450167
B28: After-Tax Cost of Debt | G28: =G26*G27 -> 0.028208955 | I28: Levered Beta 4 | M28: =L22 -> 0.77
I29: Cost of Equity | M29: =M26+M27*M28 -> 0.15330628
B32: Capital Structure | I32: Levered Beta
D34: Current | E34: Target | I34: Comps Median Unlevered Beta | M34: =M22 -> 0.76201548
B35: Total Debt | C35: =G16 -> 670.27 | D35: =C35/C37 -> 0.010647258 | E35: =K22 -> 0.010160583 | I35: Target Debt/Equity | M35: =E39 -> 0.010264881
B36: Market Capitalization | C36: =H16 -> 62282.09 | D36: =C36/C37 -> 0.98935274 | E36: =E37-E35 -> 0.98983942 | I36: Tax Rate | M36: =I19 -> 0.3
B37: Total Capital | C37: =SUM(C35:C36) -> 62952.36 | D37: =SUM(D35:D36) -> 1 | E37: 1 | I37: Levered Beta | M37: =M34*(1+(1-M36)*M35) -> 0.76749088
B39: Debt/Equity | E39: =E35/E36 -> 0.010264881
I40: Weighted Average Cost of Capital
I42: Total Equity | M42: =M29 -> 0.15330628
I43: Equity Weight | M43: =E36 -> 0.98983942
I45: Total Debt | M45: =G28 -> 0.028208955
I46: Debt Weight | M46: =E35 -> 0.010160583
I48: WACC | M48: =(M42*M43)+(M45*M46) -> 0.15203522

Sheet Beta Calculation
B3: Bergre Paints Stock Price of Two Years | F3: Nifty Stocks Price | J3: Beta Calculation | M3: Beta Drifting
B5: Date | C5: Price | D5: Change % | F5: Price | G5: Change % | J5: Beta 1 | K5: =SLOPE(D7:D110,G7:G110) -> 0.8503226 | M5: Levered Beta | N5: =K7 -> 0.8503226
B6: 44969 | C6: 474.13 | F6: 17944.2 | J6: Beta 2 | K6: =_xlfn.COVARIANCE.S(G7:G110,D7:D110)/_xlfn.VAR.S(G7:G110) -> 0.8503226 | M6: LB Weight | N6: 0.67
B7: 44976 | C7: 465.04 | D7: -0.0192 | F7: 17465.8 | G7: -0.0267 | J7: Beta 3 | K7: =K29 -> 0.8503226
B8: 44983 | C8: 483.96 | D8: 0.0407 | F8: 17594.35 | G8: 0.0074 | M8: Market Beta | N8: 1
B9: 44990 | C9: 490.92 | D9: 0.0144 | F9: 17412.9 | G9: -0.0103 | M9: Market Weight | N9: 0.33
B10: 44997 | C10: 494.54 | D10: 0.0074 | F10: 17100.05 | G10: -0.018 | M10: Adjusted Beta | N10: =(N5*N6)+(N8*N9) -> 0.89971614
B11: 45004 | C11: 478.08 | D11: -0.0333 | F11: 16945.05 | G11: -0.0091
B12: 45011 | C12: 484.75 | D12: 0.0139 | F12: 17359.75 | G12: 0.0245 | J12: SUMMARY OUTPUT
B13: 45018 | C13: 497.67 | D13: 0.0266 | F13: 17599.15 | G13: 0.0138
B14: 45025 | C14: 482.17 | D14: -0.0311 | F14: 17828 | G14: 0.013 | J14: Regression Statistics
B15: 45032 | C15: 487.17 | D15: 0.0104 | F15: 17624.05 | G15: -0.0114 | J15: Multiple R | K15: 0.3896426
B16: 45039 | C16: 508.63 | D16: 0.044 | F16: 18065 | G16: 0.025 | J16: R Square | K16: 0.15182135
B17: 45046 | C17: 514.38 | D17: 0.0113 | F17: 18069 | G17: 0.0002 | J17: Adjusted R Square | K17: 0.14350588
B18: 45053 | C18: 528.04 | D18: 0.0266 | F18: 18314.8 | G18: 0.0136 | J18: Standard Error | K18: 0.03200923
B19: 45060 | C19: 521.04 | D19: -0.0133 | F19: 18203.4 | G19: -0.0061 | J19: Observations | K19: 104
B20: 45067 | C20: 539.25 | D20: 0.0349 | F20: 18499.35 | G20: 0.0163
B21: 45074 | C21: 543.71 | D21: 0.0083 | F21: 18534.1 | G21: 0.0019 | J21: ANOVA
B22: 45081 | C22: 539.75 | D22: -0.0073 | F22: 18563.4 | G22: 0.0016 | K22: df | L22: SS | M22: MS | N22: F | O22: Significance F
B23: 45088 | C23: 561.29 | D23: 0.0399 | F23: 18826 | G23: 0.0141 | J23: Regression | K23: 1 | L23: 0.018706655 | M23: 0.018706655 | N23: 18.257684 | O23: 4.344244e-05
B24: 45095 | C24: 563.04 | D24: 0.0031 | F24: 18665.5 | G24: -0.0085 | J24: Residual | K24: 102 | L24: 0.10450826 | M24: 0.0010245908
B25: 45102 | C25: 565.08 | D25: 0.0036 | F25: 19189.05 | G25: 0.028 | J25: Total | K25: 103 | L25: 0.12321492
B26: 45109 | C26: 560.71 | D26: -0.0077 | F26: 19331.8 | G26: 0.0074
B27: 45116 | C27: 556.75 | D27: -0.0071 | F27: 19564.5 | G27: 0.012 | K27: Coefficients | L27: Standard Error | M27: t Stat | N27: P-value | O27: Lower 95% | P27: Upper 95% | Q27: Lower 95.0% | R27: Upper 95.0%
B28: 45123 | C28: 575.96 | D28: 0.0345 | F28: 19745 | G28: 0.0092 | J28: Intercept | K28: -0.0014176762 | L28: 0.0031774398 | M28: -0.44616935 | N28: 0.65642064 | O28: -0.007720113 | P28: 0.0048847605 | Q28: -0.007720113 | R28: 0.0048847605
B29: 45130 | C29: 566.38 | D29: -0.0166 | F29: 19646.05 | G29: -0.005 | J29: X Variable 1 | K29: 0.8503226 | L29: 0.19900357 | M29: 4.2729011 | N29: 4.344244e-05 | O29: 0.45559995 | P29: 1.2450452 | Q29: 0.45559995 | R29: 1.2450452
B30: 45137 | C30: 587.21 | D30: 0.0368 | F30: 19517 | G30: -0.0066
B31: 45144 | C31: 583.92 | D31: -0.0056 | F31: 19428.3 | G31: -0.0045
B32: 45151 | C32: 587.71 | D32: 0.0065 | F32: 19310.15 | G32: -0.0061
B33: 45158 | C33: 586.96 | D33: -0.0013 | F33: 19265.8 | G33: -0.0023
B34: 45165 | C34: 599.88 | D34: 0.022 | F34: 19435.3 | G34: 0.0088
B35: 45172 | C35: 597.42 | D35: -0.0041 | F35: 19819.95 | G35: 0.0198
B36: 45179 | C36: 599.75 | D36: 0.0039 | F36: 20192.35 | G36: 0.0188
B37: 45186 | C37: 669.3 | D37: 0.116 | F37: 19674.25 | G37: -0.0257
B38: 45193 | C38: 568.85 | D38: -0.1501 | F38: 19638.3 | G38: -0.0018
B39: 45200 | C39: 565.35 | D39: -0.0062 | F39: 19653.5 | G39: 0.0008
B40: 45207 | C40: 568.25 | D40: 0.0051 | F40: 19751.05 | G40: 0.005
B41: 45214 | C41: 584.25 | D41: 0.0282 | F41: 19542.65 | G41: -0.0106
... B110: 45697 | C110: 478.3 | D110: -0.0022 | F110: 22929.25 | G110: -0.0268

Sheet Market Returns
B2: Year | C2: Annual
B3: 2000 | E3: Average Return | F3: =AVERAGE(C4:C27) -> 0.16584167
B4: 2001 | C4: -0.1618 | E4: Dividend Yeild | F4: 0.0138
B5: 2002 | C5: 0.0325 | E5: Total Market Return | F5: =F3+F4 -> 0.17964167
B6: 2003 | C6: 0.719
B7: 2004 | C7: 0.1068
B8: 2005 | C8: 0.3634
B9: 2006 | C9: 0.3983
B10: 2007 | C10: 0.5477
B11: 2008 | C11: -0.5179
B12: 2009 | C12: 0.7576
B13: 2010 | C13: 0.1795
B14: 2011 | C14: -0.2462
B15: 2012 | C15: 0.277
B16: 2013 | C16: 0.0676
B17: 2014 | C17: 0.3139
... B27: 2024 | C27: 0.0875

Sheet Peer Companies
B4: Sno. | C4: Name | D4: CMP Rs. | E4: Mar Cap Rs.Cr. | F4: Debt Rs.Cr.
B5: 1 | C5: Asian Paints | D5: 2326.1 | E5: 223119.01 | F5: 2290.29
B6: 2 | C6: Berger Paints | D6: 534.2 | E6: 62282.09 | F6: 670.27
B7: 3 | C7: Kansai Nerolac | D7: 244.9 | E7: 19800.51 | F7: 296.39
B8: 4 | C8: Akzo Nobel | D8: 3324.95 | E8: 15141.96 | F8: 62.1
B9: 5 | C9: Indigo Paints | D9: 1026.4 | E9: 4893.42 | F9: 19.7

Sheet Intrinsic Growth
B3: ="Intrinsic Growth of " &'Data Sheet'!$B$1 -> Intrinsic Growth of BERGER PAINTS INDIA LTD
B4: Years | C4: ='Data Sheet'!B16 -> 42460 | D4: ='Data Sheet'!C16 -> 42825 | E4: ='Data Sheet'!D16 -> 43190 | F4: ='Data Sheet'!E16 -> 43555 | G4: ='Data Sheet'!F16 -> 43921 | H4: ='Data Sheet'!G16 -> 44286 | I4: ='Data Sheet'!H16 -> 44651 | J4: ='Data Sheet'!I16 -> 45016 | ... L4: ='Data Sheet'!K16 -> 45747
B6: Current Assests
B7: ='Data Sheet'!A153 -> Inventories | C7: ='Data Sheet'!B153 -> 696 | D7: ='Data Sheet'!C153 -> 719 | E7: ='Data Sheet'!D153 -> 733 | F7: ='Data Sheet'!E153 -> 935 | G7: ='Data Sheet'!F153 -> 1007 | H7: ='Data Sheet'!G153 -> 1234 | I7: ='Data Sheet'!H153 -> 1278 | ... L7: ='Data Sheet'!K153 -> 2319
B8: ='Data Sheet'!A154 -> Trade receivables + | C8: ='Data Sheet'!B154 -> 486 | D8: ='Data Sheet'!C154 -> 535 | E8: ='Data Sheet'!D154 -> 545 | F8: ='Data Sheet'!E154 -> 578 | G8: ='Data Sheet'!F154 -> 692 | H8: ='Data Sheet'!G154 -> 671 | I8: ='Data Sheet'!H154 -> 714 | ... L8: ='Data Sheet'!K154 -> 1243
B9: ='Data Sheet'!A155 -> Cash Equivalents | C9: ='Data Sheet'!B155 -> 184 | D9: ='Data Sheet'!C155 -> 170 | E9: ='Data Sheet'!D155 -> 105 | F9: ='Data Sheet'!E155 -> 102 | G9: ='Data Sheet'!F155 -> 205 | H9: ='Data Sheet'!G155 -> 238 | I9: ='Data Sheet'!H155 -> 220 | ... L9: ='Data Sheet'!K155 -> 245
B10: ='Data Sheet'!A156 -> Loans n Advances | C10: ='Data Sheet'!B156 -> 0 | D10: ='Data Sheet'!C156 -> 0 | E10: ='Data Sheet'!D156 -> 8 | F10: ='Data Sheet'!E156 -> 11 | G10: ='Data Sheet'!F156 -> 9 | H10: ='Data Sheet'!G156 -> 11 | I10: ='Data Sheet'!H156 -> 12 | ... L10: ='Data Sheet'!K156 -> 26
B11: ='Data Sheet'!A157 -> Other asset items | C11: ='Data Sheet'!B157 -> 142 | D11: ='Data Sheet'!C157 -> 126 | E11: ='Data Sheet'!D157 -> 123 | F11: ='Data Sheet'!E157 -> 142 | G11: ='Data Sheet'!F157 -> 331 | H11: ='Data Sheet'!G157 -> 255 | I11: ='Data Sheet'!H157 -> 266 | ... L11: ='Data Sheet'!K157 -> 509
B12: Total Current Assets | C12: =SUM(C7:C11) -> 1508 | D12: =SUM(D7:D11) -> 1550 | E12: =SUM(E7:E11) -> 1514 | F12: =SUM(F7:F11) -> 1768 | G12: =SUM(G7:G11) -> 2244 | H12: =SUM(H7:H11) -> 2409 | I12: =SUM(I7:I11) -> 2490 | J12: =SUM(J7:J11) -> 3412 | ... L12: =SUM(L7:L11) -> 4342
B14: Current Liabilities
B15: ='Data Sheet'!A135 -> Trade Payables | C15: ='Data Sheet'!B135 -> 544 | D15: ='Data Sheet'!C135 -> 560 | E15: ='Data Sheet'!D135 -> 670 | F15: ='Data Sheet'!E135 -> 761 | G15: ='Data Sheet'!F135 -> 955 | H15: ='Data Sheet'!G135 -> 999 | I15: ='Data Sheet'!H135 -> 1066 | ... L15: ='Data Sheet'!K135 -> 1766
B16: ='Data Sheet'!A136 -> Advance from Customers | C16: ='Data Sheet'!B136 -> 9 | D16: ='Data Sheet'!C136 -> 10 | E16: ='Data Sheet'!D136 -> 11 | F16: ='Data Sheet'!E136 -> 13 | G16: ='Data Sheet'!F136 -> 19 | H16: ='Data Sheet'!G136 -> 19 | I16: ='Data Sheet'!H136 -> 17 | ... L16: ='Data Sheet'!K136 -> 25
B17: ='Data Sheet'!A137 -> Other liability items | C17: ='Data Sheet'!B137 -> 298 | D17: ='Data Sheet'!C137 -> 276 | E17: ='Data Sheet'!D137 -> 280 | F17: ='Data Sheet'!E137 -> 358 | G17: ='Data Sheet'!F137 -> 351 | H17: ='Data Sheet'!G137 -> 338 | I17: ='Data Sheet'!H137 -> 383 | ... L17: ='Data Sheet'!K137 -> 485
B18: Total Current Liabilities | C18: =SUM(C14:C17) -> 851 | D18: =SUM(D14:D17) -> 846 | E18: =SUM(E15:E17) -> 961 | F18: =SUM(F15:F17) -> 1132 | G18: =SUM(G15:G17) -> 1325 | H18: =SUM(H15:H17) -> 1356 | I18: =SUM(I15:I17) -> 1466 | J18: =SUM(J15:J17) -> 1900 | K18: =SUM(K15:K17) -> 2264 | L18: =SUM(L15:L17) -> 2276
B20: Net Woking Capital | C20: =C12-C18 -> 657 | D20: =D12-D18 -> 704 | E20: =E12-E18 -> 553 | F20: =F12-F18 -> 636 | G20: =G12-G18 -> 919 | H20: =H12-H18 -> 1053 | I20: =I12-I18 -> 1024 | J20: =J12-J18 -> 1512 | ... L20: =L12-L18 -> 2066
B22: Fixed Assets
B23: ='Data Sheet'!A140 -> Land | C23: ='Data Sheet'!B140 -> 21 | D23: ='Data Sheet'!C140 -> 23 | E23: ='Data Sheet'!D140 -> 20 | F23: ='Data Sheet'!E140 -> 21 | G23: ='Data Sheet'!F140 -> 22 | H23: ='Data Sheet'!G140 -> 61 | I23: ='Data Sheet'!H140 -> 159 | ... L23: ='Data Sheet'!K140 -> 183
B24: ='Data Sheet'!A141 -> Building | C24: ='Data Sheet'!B141 -> 289 | D24: ='Data Sheet'!C141 -> 344 | E24: ='Data Sheet'!D141 -> 325 | F24: ='Data Sheet'!E141 -> 405 | G24: ='Data Sheet'!F141 -> 426 | H24: ='Data Sheet'!G141 -> 656 | I24: ='Data Sheet'!H141 -> 832 | ... L24: ='Data Sheet'!K141 -> 1626
B25: ='Data Sheet'!A142 -> Plant Machinery | C25: ='Data Sheet'!B142 -> 610 | D25: ='Data Sheet'!C142 -> 709 | E25: ='Data Sheet'!D142 -> 436 | F25: ='Data Sheet'!E142 -> 607 | G25: ='Data Sheet'!F142 -> 729 | H25: ='Data Sheet'!G142 -> 835 | I25: ='Data Sheet'!H142 -> 1011 | ... L25: ='Data Sheet'!K142 -> 2023
B26: ='Data Sheet'!A143 -> Equipments | C26: ='Data Sheet'!B143 -> 74 | D26: ='Data Sheet'!C143 -> 9 | E26: ='Data Sheet'!D143 -> 7 | F26: ='Data Sheet'!E143 -> 9 | G26: ='Data Sheet'!F143 -> 11 | H26: ='Data Sheet'!G143 -> 15 | I26: ='Data Sheet'!H143 -> 19 | ... L26: ='Data Sheet'!K143 -> 37
B27: ='Data Sheet'!A144 -> Computers | C27: ='Data Sheet'!B144 -> 0 | D27: ='Data Sheet'!C144 -> 69 | E27: ='Data Sheet'!D144 -> 25 | F27: ='Data Sheet'!E144 -> 36 | G27: ='Data Sheet'!F144 -> 47 | H27: ='Data Sheet'!G144 -> 49 | I27: ='Data Sheet'!H144 -> 56 | ... L27: ='Data Sheet'!K144 -> 61
B28: ='Data Sheet'!A145 -> Furniture n fittings | C28: ='Data Sheet'!B145 -> 33 | D28: ='Data Sheet'!C145 -> 36 | E28: ='Data Sheet'!D145 -> 22 | F28: ='Data Sheet'!E145 -> 26 | G28: ='Data Sheet'!F145 -> 37 | H28: ='Data Sheet'!G145 -> 40 | I28: ='Data Sheet'!H145 -> 44 | ... L28: ='Data Sheet'!K145 -> 55
B29: ='Data Sheet'!A146 -> Vehicles | C29: ='Data Sheet'!B146 -> 24 | D29: ='Data Sheet'!C146 -> 25 | E29: ='Data Sheet'!D146 -> 13 | F29: ='Data Sheet'!E146 -> 14 | G29: ='Data Sheet'!F146 -> 19 | H29: ='Data Sheet'!G146 -> 24 | I29: ='Data Sheet'!H146 -> 27 | ... L29: ='Data Sheet'!K146 -> 20
B30: ='Data Sheet'!A147 -> Intangible Assets | C30: ='Data Sheet'!B147 -> 224 | D30: ='Data Sheet'!C147 -> 198 | E30: ='Data Sheet'!D147 -> 186 | F30: ='Data Sheet'!E147 -> 179 | G30: ='Data Sheet'!F147 -> 265 | H30: ='Data Sheet'!G147 -> 269 | I30: ='Data Sheet'!H147 -> 279 | ... L30: ='Data Sheet'!K147 -> 282
B31: ='Data Sheet'!A148 -> Other fixed assets | C31: ='Data Sheet'!B148 -> 47 | D31: ='Data Sheet'!C148 -> 48 | E31: ='Data Sheet'!D148 -> 14 | F31: ='Data Sheet'!E148 -> 12 | G31: ='Data Sheet'!F148 -> 16 | H31: ='Data Sheet'!G148 -> 23 | I31: ='Data Sheet'!H148 -> 25 | ... L31: ='Data Sheet'!K148 -> 36
B32: ='Data Sheet'!A149 -> Gross Block | C32: ='Data Sheet'!B149 -> 1322 | D32: ='Data Sheet'!C149 -> 1461 | E32: ='Data Sheet'!D149 -> 1048 | F32: ='Data Sheet'!E149 -> 1310 | G32: ='Data Sheet'!F149 -> 1571 | H32: ='Data Sheet'!G149 -> 1971 | I32: ='Data Sheet'!H149 -> 2452 | ... L32: ='Data Sheet'!K149 -> 4324
B33: Accumulated Depriciation | C33: =-('Data Sheet'!B150) -> -458 | D33: =-('Data Sheet'!C150) -> -531 | E33: =-('Data Sheet'!D150) -> -85 | F33: =-('Data Sheet'!E150) -> -174 | G33: =-('Data Sheet'!F150) -> -304 | H33: =-('Data Sheet'!G150) -> -388 | I33: =-('Data Sheet'!H150) -> -536 | J33: =-('Data Sheet'!I150) -> -690 | ... L33: =-('Data Sheet'!K150) -> -992
B34: Net Block | C34: =SUM(C32:C33) -> 864 | D34: =SUM(D32:D33) -> 930 | E34: =SUM(E32:E33) -> 963 | F34: =SUM(F32:F33) -> 1136 | G34: =SUM(G32:G33) -> 1267 | H34: =SUM(H32:H33) -> 1583 | I34: =SUM(I32:I33) -> 1916 | J34: =SUM(J32:J33) -> 2044 | ... L34: =SUM(L32:L33) -> 3332
B36: Investment Capital | C36: =C34+C20 -> 1521 | D36: =D34+D20 -> 1634 | E36: =E34+E20 -> 1516 | F36: =F34+F20 -> 1772 | G36: =G34+G20 -> 2186 | H36: =H34+H20 -> 2636 | I36: =I34+I20 -> 2940 | J36: =J34+J20 -> 3556 | ... L36: =L34+L20 -> 5398
B37: EBIT | C37: ='Income Statement'!D28 -> 820.05 | D37: ='Income Statement'!E28 -> 918.02 | E37: ='Income Statement'!F28 -> 1039.84 | F37: ='Income Statement'!G28 -> 1161.33 | G37: ='Income Statement'!H28 -> 1314.79 | H37: ='Income Statement'!I28 -> 1456.94 | I37: ='Income Statement'!J28 -> 1648.25 | J37: ='Income Statement'!K28 -> 1823.52 | ... L37: ='Income Statement'!M28 -> 2319.27
B39: ROIC (Return on Investment Capital) | C39: =C37/C36 -> 0.53915187 | D39: =D37/D36 -> 0.56182375 | E39: =E37/E36 -> 0.68591029 | F39: =F37/F36 -> 0.6553781 | G39: =G37/G36 -> 0.60145929 | H39: =H37/H36 -> 0.55270865 | I39: =I37/I36 -> 0.56062925 | J39: =J37/J36 -> 0.5128009 | ... L39: =L37/L36 -> 0.42965358
B41: Calculation of Reinvestment Rate
B43: Net Capex | C43: =-SUM('Data Sheet'!B98:B99) -> 242 | D43: =-SUM('Data Sheet'!C98:C99) -> 161 | E43: =-SUM('Data Sheet'!D98:D99) -> 118 | F43: =-SUM('Data Sheet'!E98:E99) -> 265 | G43: =-SUM('Data Sheet'!F98:F99) -> 290 | H43: =-SUM('Data Sheet'!G98:G99) -> 291 | I43: =-SUM('Data Sheet'!H98:H99) -> 431 | J43: =-SUM('Data Sheet'!I98:I99) -> 185 | ... L43: =-SUM('Data Sheet'!K98:K99) -> 744
B44: Change in Working Capital | D44: =D20-C20 -> 47 | E44: =E20-D20 -> -151 | F44: =F20-E20 -> 83 | G44: =G20-F20 -> 283 | H44: =H20-G20 -> 134 | I44: =I20-H20 -> -29 | J44: =J20-I20 -> 488 | K44: =K20-J20 -> 409 | L44: =L20-K20 -> 145
B46: EBIT | C46: =C37 -> 820.05 | D46: =D37 -> 918.02 | E46: =E37 -> 1039.84 | F46: =F37 -> 1161.33 | G46: =G37 -> 1314.79 | H46: =H37 -> 1456.94 | I46: =I37 -> 1648.25 | J46: =J37 -> 1823.52 | ... L46: =L37 -> 2319.27
B47: Tax Rate | C47: 0.25 | D47: 0.25 | E47: 0.25 | F47: 0.25 | G47: 0.25 | H47: 0.25 | I47: 0.25 | J47: 0.25 | K47: 0.25 | L47: 0.25
B48: EBIT(1 - Tax) | C48: =C46*(1 - C47) -> 615.0375 | D48: =D46*(1 - D47) -> 688.515 | E48: =E46*(1 - E47) -> 779.88 | F48: =F46*(1 - F47) -> 870.9975 | G48: =G46*(1 - G47) -> 986.0925 | H48: =H46*(1 - H47) -> 1092.705 | I48: =I46*(1 - I47) -> 1236.1875 | J48: =J46*(1 - J47) -> 1367.64 | ... L48: =L46*(1 - L47) -> 1739.4525
B50: Reinvestement | C50: =SUM(C43:C44) -> 242 | D50: =SUM(D43:D44) -> 208 | E50: =SUM(E43:E44) -> -33 | F50: =SUM(F43:F44) -> 348 | G50: =SUM(G43:G44) -> 573 | H50: =SUM(H43:H44) -> 425 | I50: =SUM(I43:I44) -> 402 | J50: =SUM(J43:J44) -> 673 | ... L50: =SUM(L43:L44) -> 889
B51: Reinvestement Rate | C51: =C50/C48 -> 0.39347194 | D51: =D50/D48 -> 0.30209945 | E51: =E50/E48 -> -0.042314202 | F51: =F50/F48 -> 0.3995419 | G51: =G50/G48 -> 0.58108139 | H51: =H50/H48 -> 0.38894304 | I51: =I50/I48 -> 0.32519339 | J51: =J50/J48 -> 0.49208856 | ... L51: =L50/L48 -> 0.51108035
B53: Calculation of Intrinsic Growth
B55: Reinvestement Rate | C55: =C51 -> 0.39347194 | D55: =D51 -> 0.30209945 | E55: =E51 -> -0.042314202 | F55: =F51 -> 0.3995419 | G55: =G51 -> 0.58108139 | H55: =H51 -> 0.38894304 | I55: =I51 -> 0.32519339 | J55: =J51 -> 0.49208856 | ... L55: =L51 -> 0.51108035
B56: ROIC | C56: =C39 -> 0.53915187 | D56: =D39 -> 0.56182375 | E56: =E39 -> 0.68591029 | F56: =F39 -> 0.6553781 | G56: =G39 -> 0.60145929 | H56: =H39 -> 0.55270865 | I56: =I39 -> 0.56062925 | J56: =J39 -> 0.5128009 | ... L56: =L39 -> 0.42965358
B58: Intrinsic Growth | C58: =C56*C55 -> 0.21214114 | D58: =D56*D55 -> 0.16972664 | E58: =E56*E55 -> -0.029023747 | F58: =F56*F55 -> 0.26185102 | G58: =G56*G55 -> 0.3494968 | H58: =H56*H55 -> 0.21497218 | I58: =I56*I55 -> 0.18231293 | J58: =J56*J55 -> 0.25234346 | ... L58: =L56*L55 -> 0.2195875

Sheet Data Sheet
A1: COMPANY NAME | B1: BERGER PAINTS INDIA LTD | E1: =IF(B2<>B3, "A NEW VERSION OF THE WORKSHEET IS AVAILABLE", "")
A2: LATEST VERSION | B2: 2.1 | E2: PLEASE DO NOT MAKE ANY CHANGES TO THIS SHEET
A3: CURRENT VERSION | B3: 2.1
A5: META
A6: Number of shares | B6: =IF(B9>0, B9/B8, 0) -> 116.58948
A7: Face Value | B7: 1
A8: Current Price | B8: 535.15
A9: Market Capitalization | B9: 62392.86
A15: PROFIT & LOSS
A16: Report Date | B16: 42460 | C16: 42825 | D16: 43190 | E16: 43555 | F16: 43921 | G16: 44286 | H16: 44651 | I16: 45016 | J16: 45382 | K16: 45747
A17: Sales | B17: 4223.1 | C17: 4552.25 | D17: 5165.73 | E17: 6061.86 | F17: 6365.82 | G17: 6817.59 | H17: 8761.78 | I17: 10567.84 | J17: 11198.92 | K17: 11544.71
A18: Raw Material Cost | B18: 2489.81 | C18: 2357.66 | D18: 2730.63 | E18: 3426.09 | F18: 3306.65 | G18: 3579.29 | H18: 5124.6 | I18: 6065.6 | J18: 5804.34 | K18: 6155.9
A19: Change in Inventory | B19: 19.62 | C19: 125.09 | D19: 99.97 | E19: 173.95 | F19: 18.8 | G19: 186.65 | H19: 381.49 | I19: 93.24 | J19: -124.75 | K19: 134.41
A20: Power and Fuel | B20: 42.15 | C20: 43.79 | D20: 48.27 | E20: 59.13 | F20: 58.54 | G20: 56.47 | H20: 68.13 | I20: 83.27 | J20: 88.32 | K20: 91.86
A21: Other Mfr. Exp | B21: 338.98 | C21: 733.4 | D21: 764.16 | E21: 896.83 | F21: 984.06 | G21: 1089.73 | H21: 1460.76 | I21: 1660.48 | J21: 1665.47 | K21: 1643.15
A22: Employee Cost | B22: 273.92 | C22: 307.16 | D22: 357.05 | E22: 408.96 | F22: 453.11 | G22: 485.71 | H22: 543.69 | I22: 609.76 | J22: 713.67 | K22: 817
A23: Selling and admin | B23: 311.1 | C23: 366 | D23: 367.81 | E23: 273.45 | F23: 430.17 | G23: 483.04 | H23: 501.2 | I23: 606.38 | J23: 793.7 | K23: 960.31
A24: Other Expenses | B24: 141.98 | C24: 150.42 | D24: 190.78 | E24: 236.71 | F24: 99.4 | G24: 127.63 | H24: 113.82 | I24: 157.8 | J24: 147.35 | K24: 154.44
A25: Other Income | B25: 40.33 | C25: 108.44 | D25: 46.5 | E25: 60.03 | F25: 68.52 | G25: 51.49 | H25: 68.45 | I25: 47.81 | J25: 104.7 | K25: 129.47
A26: Depreciation | B26: 98.65 | C26: 108.05 | D26: 124.21 | E26: 182.27 | F26: 191.01 | G26: 211.14 | H26: 226.51 | I26: 264.03 | J26: 330.88 | K26: 354.19
A27: Interest | B27: 27.28 | C27: 16.22 | D27: 24.55 | E27: 47.24 | F27: 47.04 | G27: 44.1 | H27: 50.72 | I27: 99.23 | J27: 78.25 | K27: 63.27
... A31: Dividend Amount | B31: 114.43 | C31: 169.92 | D31: 174.78 | E31: 184.51 | F31: 213.66 | G31: 271.96 | H31: 301.1 | I31: 310.85 | J31: 408.03 | K31: 443.04
A40: Quarters
A41: Report Date | B41: 45016 | C41: 45107 | D41: 45199 | E41: 45291 | F41: 45382 | G41: 45473 | H41: 45565 | I41: 45657 | J41: 45747 | K41: 45838
A42: Sales | B42: 2443.63 | C42: 3029.51 | D42: 2767.3 | E42: 2881.83 | F42: 2520.28 | G42: 3091.01 | H42: 2774.61 | I42: 2975.06 | J42: 2704.03 | K42: 3200.76
A43: Expenses | B43: 2097.06 | C43: 2472.76 | D43: 2293.65 | E43: 2401.79 | F43: 2169.4 | G43: 2568.6 | H43: 2340.43 | I43: 2503.33 | J43: 2276.26 | K43: 2672.35
A44: Other Income | B44: 15.07 | C44: 17.35 | D44: 19.11 | E44: 20.34 | F44: 47.9 | G44: 45.95 | H44: 29.96 | I44: 27.48 | J44: 26.45 | K44: 2.82
A45: Depreciation | B45: 74.41 | C45: 78.21 | D45: 82.87 | E45: 82.91 | F45: 86.89 | G45: 87.21 | H45: 88.98 | I45: 88.81 | J45: 89.19 | K45: 93.98
A46: Interest | B46: 29.3 | C46: 19.71 | D46: 21.08 | E46: 19.62 | F46: 17.84 | G46: 15.17 | H46: 17.01 | I46: 15.99 | J46: 15.1 | K46: 14.48
A47: Profit before tax | B47: 257.93 | C47: 476.18 | D47: 388.81 | E47: 397.85 | F47: 294.05 | G47: 465.98 | H47: 358.15 | I47: 394.41 | J47: 349.93 | K47: 422.77
A48: Tax | B48: 71.92 | C48: 121.27 | D48: 96.68 | E48: 97.69 | F48: 71.43 | G48: 111.95 | H48: 88.25 | I48: 98.44 | J48: 87.02 | K48: 107.73
A49: Net profit | B49: 185.69 | C49: 354.35 | D49: 291.64 | E49: 299.65 | F49: 222.1 | G49: 353.56 | H49: 269.66 | I49: 295.13 | J49: 262.05 | K49: 314.63
A50: Operating Profit | B50: 346.57 | C50: 556.75 | D50: 473.65 | E50: 480.04 | F50: 350.88 | G50: 522.41 | H50: 434.18 | I50: 471.73 | J50: 427.77 | K50: 528.41
A55: BALANCE SHEET
A56: Report Date | B56: 42460 | C56: 42825 | D56: 43190 | E56: 43555 | F56: 43921 | G56: 44286 | H56: 44651 | I56: 45016 | J56: 45382 | K56: 45747
A57: Equity Share Capital | B57: 69.35 | C57: 97.1 | D57: 97.1 | E57: 97.11 | F57: 97.12 | G57: 97.13 | H57: 97.13 | I57: 97.14 | J57: 116.58 | K57: 116.59
A58: Reserves | B58: 1492.74 | C58: 1804.46 | D58: 2097.41 | E58: 2346.7 | F58: 2563.01 | G58: 3279.74 | H58: 3829.86 | I58: 4396.98 | J58: 5262.39 | K58: 6037.51
A59: Borrowings | B59: 354.41 | C59: 406.21 | D59: 422.17 | E59: 752.94 | F59: 766.9 | G59: 633.76 | H59: 1013.53 | I59: 1188.97 | J59: 753.29 | K59: 670.27
A60: Other Liabilities | B60: 960.29 | C60: 1131.8 | D60: 1325.97 | E60: 1359.92 | F60: 1472.47 | G60: 1907.01 | H60: 2270.97 | I60: 2283.32 | J60: 2235.54 | K60: 2300.45
A61: Total | B61: 2876.79 | C61: 3439.57 | D61: 3942.65 | E61: 4556.67 | F61: 4899.5 | G61: 5917.64 | H61: 7211.49 | I61: 7966.41 | J61: 8367.8 | K61: 9124.82
A62: Net Block | B62: 962.92 | C62: 1135.96 | D62: 1267.17 | E62: 1582.65 | F62: 1915.57 | G62: 2044.22 | H62: 2186.81 | I62: 3331.57 | J62: 3499.72 | K62: 3676.99
A63: Capital Work in Progress | B63: 51.06 | C63: 62.21 | D63: 97.16 | E63: 169.89 | F63: 178.49 | G63: 106.75 | H63: 605.51 | I63: 110.54 | J63: 188.95 | K63: 125.32
A64: Investments | B64: 347.54 | C64: 472.13 | D64: 333.13 | E64: 394.92 | F64: 315.17 | G64: 355.67 | H64: 234.33 | I64: 183.11 | J64: 255.07 | K64: 532.63
A65: Other Assets | B65: 1515.27 | C65: 1769.27 | D65: 2245.19 | E65: 2409.21 | F65: 2490.27 | G65: 3411 | H65: 4184.84 | I65: 4341.19 | J65: 4424.06 | K65: 4789.88
A66: Total | B66: 2876.79 | C66: 3439.57 | D66: 3942.65 | E66: 4556.67 | F66: 4899.5 | G66: 5917.64 | H66: 7211.49 | I66: 7966.41 | J66: 8367.8 | K66: 9124.82
A67: Receivables | B67: 545.4 | C67: 578.14 | D67: 692.4 | E67: 671.48 | F67: 714.11 | G67: 1019.72 | H67: 1053.68 | I67: 1243.12 | J67: 1302.02 | K67: 1535.67
... A70: No. of Equity Shares | B70: 693477912 | C70: 970986647 | D70: 970986647 | E70: 971122908 | F70: 971219780 | G70: 971295037 | H70: 971295037 | I70: 971422485 | J70: 1165796049 | K70: 1165894779
A71: New Bonus Shares | J71: 194284497
A72: Face value | B72: 1 | C72: 1 | D72: 1 | E72: 1 | F72: 1 | G72: 1 | H72: 1 | I72: 1 | J72: 1 | K72: 1
A80: CASH FLOW:
A81: Report Date | B81: 42460 | C81: 42825 | D81: 43190 | E81: 43555 | F81: 43921 | G81: 44286 | H81: 44651 | I81: 45016 | J81: 45382 | K81: 45747
A82: Cash from Operating Activity | B82: 594.57 | C82: 394.5 | D82: 421.9 | E82: 610.84 | F82: 724.64 | G82: 795.76 | H82: 566.5 | I82: 975.57 | J82: 1591.05 | K82: 1269.05
A83: Cash from Investing Activity | B83: -259.21 | C83: -308.4 | D83: -183.43 | E83: -378.59 | F83: -223.37 | G83: -456.7 | H83: -521.29 | I83: -599.85 | J83: -398.09 | K83: -649.82
A84: Cash from Financing Activity | B84: -367.63 | C84: -82.42 | D84: -200.13 | E84: -258.77 | F84: -479.42 | G84: -281.76 | H84: -78.13 | I84: -362.85 | J84: -1068.87 | K84: -605.54
A85: Net Cash Flow | B85: -32.27 | C85: 3.68 | D85: 38.34 | E85: -26.52 | F85: 21.85 | G85: 57.3 | H85: -32.92 | I85: 12.87 | J85: 124.09 | K85: 13.69
B87: 41699 | C87: 42064 | D87: 42430 | E87: 42795 | F87: 43160 | G87: 43525 | H87: 43891 | I87: 44256 | J87: 44621 | K87: 44986 | L87: 45352 | M87: 45717
A88: Cash from Operating Activity - | B88: 310 | C88: 414 | D88: 595 | E88: 394 | F88: 422 | G88: 611 | H88: 725 | I88: 796 | J88: 566 | K88: 976 | L88: 1591 | M88: 1269
A89: Profit from operations | B89: 438 | C89: 524 | D89: 659 | E89: 742 | F89: 827 | G89: 946 | H89: 1087 | I89: 1216 | J89: 1356 | K89: 1543 | L89: 1909 | M89: 1917
A90: Receivables | B90: -101 | C90: -49 | D90: -44 | E90: -34 | F90: -114 | G90: 21 | H90: -43 | I90: -306 | J90: -34 | K90: -212 | L90: -103 | M90: -132
A91: Inventory | B91: -60 | C91: -24 | D91: -39 | E91: -203 | F91: -72 | G91: -226 | H91: -45 | I91: -338 | J91: -700 | K91: -3 | L91: 139 | M91: -183
A92: Payables | B92: 136 | C92: 15 | D92: 132 | E92: 92 | F92: 194 | G92: 46 | H92: 63 | I92: 433 | J92: 314 | K92: -37 | L92: -83 | M92: 4
A93: Loans Advances | B93: 0 | C93: 53 | D93: 0 | E93: 2 | F93: 4 | G93: -1 | H93: -5 | I93: -30 | J93: -8 | K93: -41 | L93: 15 | M93: 8
A94: Other WC items | B94: 0 | C94: 16 | D94: 65 | E94: 16 | F94: -140 | G94: 69 | H94: -71 | I94: 72 | J94: -62 | K94: 35 | L94: 61 | M94: 33
A95: Working capital changes | B95: -26 | C95: 12 | D95: 114 | E95: -128 | F95: -128 | G95: -92 | H95: -100 | I95: -168 | J95: -490 | K95: -259 | L95: 30 | M95: -270
A96: Direct taxes | B96: -102 | C96: -122 | D96: -178 | E96: -220 | F96: -277 | G96: -243 | H96: -263 | I96: -252 | J96: -299 | K96: -308 | L96: -349 | M96: -378
A97: Cash from Investing Activity - | B97: -301 | C97: -184 | D97: -259 | E97: -308 | F97: -183 | G97: -379 | H97: -223 | I97: -457 | J97: -521 | K97: -600 | L97: -398 | M97: -650
A98: Fixed assets purchased | B98: -243 | C98: -162 | D98: -122 | E98: -269 | F98: -293 | G98: -293 | H98: -435 | I98: -186 | J98: -774 | K98: -748 | L98: -275 | M98: -429
A99: Fixed assets sold | B99: 1 | C99: 1 | D99: 4 | E99: 4 | F99: 3 | G99: 2 | H99: 4 | I99: 1 | J99: 14 | K99: 4 | L99: 4 | M99: 5
... A117: Net Cash Flow | B117: -43 | C117: 32 | D117: -32 | E117: 4 | F117: 38 | G117: -27 | H117: 22 | I117: 57 | J117: -33 | K117: 13 | L117: 124 | M117: 14
A121: PRICE: | B121: 145.71 | C121: 201.75 | D121: 213.92 | E121: 269.79 | F121: 414.96 | G121: 637.5 | H121: 583.08 | I121: 484.75 | J121: 573.05 | K121: 500.2
A123: DERIVED:
A124: Adjusted Equity Shares in Cr | B124: 116.51 | C124: 116.52 | D124: 116.52 | E124: 116.54 | F124: 116.55 | G124: 116.56 | H124: 116.56 | I124: 116.57 | J124: 116.58 | K124: 116.59
A127: Balance Sheet
B129: 41699 | C129: 42064 | D129: 42430 | E129: 42795 | F129: 43160 | G129: 43525 | H129: 43891 | I129: 44256 | J129: 44621 | K129: 44986 | L129: 45352 | M129: 45717
A130: Equity Capital | B130: 69 | C130: 69 | D130: 69 | E130: 97 | F130: 97 | G130: 97 | H130: 97 | I130: 97 | J130: 97 | K130: 97 | L130: 117 | M130: 117
A131: Reserves | B131: 1051 | C131: 1191 | D131: 1493 | E131: 1804 | F131: 2097 | G131: 2347 | H131: 2563 | I131: 3280 | J131: 3830 | K131: 4397 | L131: 5262 | M131: 6038
A132: Borrowings + | B132: 624 | C132: 610 | D132: 354 | E132: 406 | F132: 422 | G132: 753 | H132: 767 | I132: 634 | J132: 1014 | K132: 1189 | L132: 753 | M132: 670
A133: Other Liabilities - | B133: 851 | C133: 846 | D133: 960 | E133: 1132 | F133: 1326 | G133: 1360 | H133: 1472 | I133: 1907 | J133: 2271 | K133: 2283 | L133: 2236 | M133: 2300
A134: Non controlling int | B134: 0 | C134: 0 | D134: 0 | E134: 0 | F134: 0 | G134: 3 | H134: 7 | I134: 7 | J134: 7 | K134: 8 | L134: 10 | M134: 13
A135: Trade Payables | B135: 544 | C135: 560 | D135: 670 | E135: 761 | F135: 955 | G135: 999 | H135: 1066 | I135: 1497 | J135: 1803 | K135: 1766 | L135: 1679 | M135: 1740
A136: Advance from Customers | B136: 9 | C136: 10 | D136: 11 | E136: 13 | F136: 19 | G136: 19 | H136: 17 | I136: 25 | J136: 24 | K136: 25 | L136: 29 | M136: 30
A137: Other liability items | B137: 298 | C137: 276 | D137: 280 | E137: 358 | F137: 351 | G137: 338 | H137: 383 | I137: 378 | J137: 437 | K137: 485 | L137: 517 | M137: 518
A138: Total Liabilities | B138: 2595 | C138: 2716 | D138: 2877 | E138: 3440 | F138: 3943 | G138: 4557 | H138: 4900 | I138: 5918 | J138: 7211 | K138: 7966 | L138: 8368 | M138: 9125
A139: Fixed Assets -
A140: Land | B140: 21 | C140: 23 | D140: 20 | E140: 21 | F140: 22 | G140: 61 | H140: 159 | I140: 170 | J140: 169 | K140: 183 | L140: 243 | M140: 247
A141: Building | B141: 289 | C141: 344 | D141: 325 | E141: 405 | F141: 426 | G141: 656 | H141: 832 | I141: 884 | J141: 1009 | K141: 1626 | L141: 1769 | M141: 1875
A142: Plant Machinery | B142: 610 | C142: 709 | D142: 436 | E142: 607 | F142: 729 | G142: 835 | H142: 1011 | I142: 1206 | J142: 1306 | K142: 2023 | L142: 2181 | M142: 2419
A143: Equipments | B143: 74 | C143: 9 | D143: 7 | E143: 9 | F143: 11 | G143: 15 | H143: 19 | I143: 23 | J143: 27 | K143: 37 | L143: 44 | M143: 52
A144: Computers | B144: 0 | C144: 69 | D144: 25 | E144: 36 | F144: 47 | G144: 49 | H144: 56 | I144: 58 | J144: 54 | K144: 61 | L144: 66 | M144: 56
A145: Furniture n fittings | B145: 33 | C145: 36 | D145: 22 | E145: 26 | F145: 37 | G145: 40 | H145: 44 | I145: 47 | J145: 49 | K145: 55 | L145: 64 | M145: 73
A146: Vehicles | B146: 24 | C146: 25 | D146: 13 | E146: 14 | F146: 19 | G146: 24 | H146: 27 | I146: 23 | J146: 20 | K146: 20 | L146: 22 | M146: 23
A147: Intangible Assets | B147: 224 | C147: 198 | D147: 186 | E147: 179 | F147: 265 | G147: 269 | H147: 279 | I147: 288 | J147: 276 | K147: 282 | L147: 305 | M147: 336
A148: Other fixed assets | B148: 47 | C148: 48 | D148: 14 | E148: 12 | F148: 16 | G148: 23 | H148: 25 | I148: 34 | J148: 43 | K148: 36 | L148: 44 | M148: 40
A149: Gross Block | B149: 1322 | C149: 1461 | D149: 1048 | E149: 1310 | F149: 1571 | G149: 1971 | H149: 2452 | I149: 2734 | J149: 2955 | K149: 4324 | L149: 4736 | M149: 5121
A150: Accumulated Depreciation | B150: 458 | C150: 531 | D150: 85 | E150: 174 | F150: 304 | G150: 388 | H150: 536 | I150: 690 | J150: 768 | K150: 992 | L150: 1236 | M150: 1444
A151: CWIP | B151: 133 | C151: 100 | D151: 51 | E151: 62 | F151: 97 | G151: 170 | H151: 178 | I151: 107 | J151: 606 | K151: 111 | L151: 189 | M151: 125
... A158: Total Assets | B158: 2595 | C158: 2716 | D158: 2877 | E158: 3440 | F158: 3943 | G158: 4557 | H158: 4900 | I158: 5918 | J158: 7211 | K158: 7966 | L158: 8368 | M158: 9125
